Workbook

Sheet Тарифы
A1: Товар | B1: Объем Л | C1: Тариф, рубли | D1: межкласстерный коэффицент | E1: Дальний Восток | F1: Калининград | G1: Санкт-Петербург и СЗО | H1: Воронеж | I1: Москва, МО и Дальние регионы | J1: Уфа | K1: Казань | L1: Самара | M1: Красноярск | N1: Тюмень | O1: Невинномысск | P1: Махачкала | Q1: Саратов | R1: Ярославль | S1: Краснодар | T1: Екатеринбург | U1: Новосибирск | V1: Омск | W1: Оренбург | X1: Пермь | Y1: Ростов | Z1: Тверь | AB1: Объём товара, литры | AC1: Тариф, рубли
A2: ШБС 01-17 | B2: 348 | C2: 1859 | E2: =2.4*C2 -> 4461.6 | F2: =1.7*C2 -> 3160.3 | G2: =1.5*C2 -> 2788.5 | H2: =1.4*C2 -> 2602.6 | I2: =1.3*C2 -> 2416.7 | J2: =1.2*C2 -> 2230.8 | K2: =1*C2 -> 1859 | L2: =1.1*C2 -> 2044.9 | M2: =1.7*C2 -> 3160.3 | N2: =1.7*C2 -> 3160.3 | O2: =1.6*C2 -> 2974.4 | P2: =1.6*C2 -> 2974.4 | Q2: =1.1*C2 -> 2044.9 | R2: =1.3*C2 -> 2416.7 | S2: =1.6*C2 -> 2974.4 | T2: =1.3*C2 -> 2416.7 | U2: =1.7*C2 -> 3160.3 | V2: =1.7*C2 -> 3160.3 | W2: =1.2*C2 -> 2230.8 | X2: =1.3*C2 -> 2416.7 | Y2: =1.6*C2 -> 2974.4 | Z2: =1.3*C2 -> 2416.7 | AB2: 0 - 0.2 | AC2: 50
A3: ШБС 02-17 | B3: 348 | C3: 1859 | E3: =2.4*C3 -> 4461.6 | F3: =1.7*C3 -> 3160.3 | G3: =1.5*C3 -> 2788.5 | H3: =1.4*C3 -> 2602.6 | I3: =1.3*C3 -> 2416.7 | J3: =1.2*C3 -> 2230.8 | K3: =1*C3 -> 1859 | L3: =1.1*C3 -> 2044.9 | M3: =1.7*C3 -> 3160.3 | N3: =1.7*C3 -> 3160.3 | O3: =1.6*C3 -> 2974.4 | P3: =1.6*C3 -> 2974.4 | Q3: =1.1*C3 -> 2044.9 | R3: =1.3*C3 -> 2416.7 | S3: =1.6*C3 -> 2974.4 | T3: =1.3*C3 -> 2416.7 | U3: =1.7*C3 -> 3160.3 | V3: =1.7*C3 -> 3160.3 | W3: =1.2*C3 -> 2230.8 | X3: =1.3*C3 -> 2416.7 | Y3: =1.6*C3 -> 2974.4 | Z3: =1.3*C3 -> 2416.7 | AB3: 0.21 - 0.4 | AC3: 55
A4: СМ 30 | B4: 37 | C4: 263 | E4: =2.4*C4 -> 631.2 | F4: =1.7*C4 -> 447.1 | G4: =1.5*C4 -> 394.5 | H4: =1.4*C4 -> 368.2 | I4: =1.3*C4 -> 341.9 | J4: =1.2*C4 -> 315.6 | K4: =1*C4 -> 263 | L4: =1.1*C4 -> 289.3 | M4: =1.7*C4 -> 447.1 | N4: =1.7*C4 -> 447.1 | O4: =1.6*C4 -> 420.8 | P4: =1.6*C4 -> 420.8 | Q4: =1.1*C4 -> 289.3 | R4: =1.3*C4 -> 341.9 | S4: =1.6*C4 -> 420.8 | T4: =1.3*C4 -> 341.9 | U4: =1.7*C4 -> 447.1 | V4: =1.7*C4 -> 447.1 | W4: =1.2*C4 -> 315.6 | X4: =1.3*C4 -> 341.9 | Y4: =1.6*C4 -> 420.8 | Z4: =1.3*C4 -> 341.9 | AB4: 0.41 - 0.6 | AC4: 58
A5: СМ 30-Э | B5: 37 | C5: 263 | E5: =2.4*C5 -> 631.2 | F5: =1.7*C5 -> 447.1 | G5: =1.5*C5 -> 394.5 | H5: =1.4*C5 -> 368.2 | I5: =1.3*C5 -> 341.9 | J5: =1.2*C5 -> 315.6 | K5: =1*C5 -> 263 | L5: =1.1*C5 -> 289.3 | M5: =1.7*C5 -> 447.1 | N5: =1.7*C5 -> 447.1 | O5: =1.6*C5 -> 420.8 | P5: =1.6*C5 -> 420.8 | Q5: =1.1*C5 -> 289.3 | R5: =1.3*C5 -> 341.9 | S5: =1.6*C5 -> 420.8 | T5: =1.3*C5 -> 341.9 | U5: =1.7*C5 -> 447.1 | V5: =1.7*C5 -> 447.1 | W5: =1.2*C5 -> 315.6 | X5: =1.3*C5 -> 341.9 | Y5: =1.6*C5 -> 420.8 | Z5: =1.3*C5 -> 341.9 | AB5: 0.61 - 0.8 | AC5: 61
A6: СМ 50 | B6: 59 | C6: 334 | E6: =2.4*C6 -> 801.6 | F6: =1.7*C6 -> 567.8 | G6: =1.5*C6 -> 501 | H6: =1.4*C6 -> 467.6 | I6: =1.3*C6 -> 434.2 | J6: =1.2*C6 -> 400.8 | K6: =1*C6 -> 334 | L6: =1.1*C6 -> 367.4 | M6: =1.7*C6 -> 567.8 | N6: =1.7*C6 -> 567.8 | O6: =1.6*C6 -> 534.4 | P6: =1.6*C6 -> 534.4 | Q6: =1.1*C6 -> 367.4 | R6: =1.3*C6 -> 434.2 | S6: =1.6*C6 -> 534.4 | T6: =1.3*C6 -> 434.2 | U6: =1.7*C6 -> 567.8 | V6: =1.7*C6 -> 567.8 | W6: =1.2*C6 -> 400.8 | X6: =1.3*C6 -> 434.2 | Y6: =1.6*C6 -> 534.4 | Z6: =1.3*C6 -> 434.2 | AB6: 0.81 - 1 | AC6: 63
A7: СМ 50-Э | B7: 59 | C7: 334 | E7: =2.4*C7 -> 801.6 | F7: =1.7*C7 -> 567.8 | G7: =1.5*C7 -> 501 | H7: =1.4*C7 -> 467.6 | I7: =1.3*C7 -> 434.2 | J7: =1.2*C7 -> 400.8 | K7: =1*C7 -> 334 | L7: =1.1*C7 -> 367.4 | M7: =1.7*C7 -> 567.8 | N7: =1.7*C7 -> 567.8 | O7: =1.6*C7 -> 534.4 | P7: =1.6*C7 -> 534.4 | Q7: =1.1*C7 -> 367.4 | R7: =1.3*C7 -> 434.2 | S7: =1.6*C7 -> 534.4 | T7: =1.3*C7 -> 434.2 | U7: =1.7*C7 -> 567.8 | V7: =1.7*C7 -> 567.8 | W7: =1.2*C7 -> 400.8 | X7: =1.3*C7 -> 434.2 | Y7: =1.6*C7 -> 534.4 | Z7: =1.3*C7 -> 434.2 | AB7: 1.01 - 1.25 | AC7: 71
A8: СМ 25 | B8: 24 | C8: 210 | E8: =2.4*C8 -> 504 | F8: =1.7*C8 -> 357 | G8: =1.5*C8 -> 315 | H8: =1.4*C8 -> 294 | I8: =1.3*C8 -> 273 | J8: =1.2*C8 -> 252 | K8: =1*C8 -> 210 | L8: =1.1*C8 -> 231 | M8: =1.7*C8 -> 357 | N8: =1.7*C8 -> 357 | O8: =1.6*C8 -> 336 | P8: =1.6*C8 -> 336 | Q8: =1.1*C8 -> 231 | R8: =1.3*C8 -> 273 | S8: =1.6*C8 -> 336 | T8: =1.3*C8 -> 273 | U8: =1.7*C8 -> 357 | V8: =1.7*C8 -> 357 | W8: =1.2*C8 -> 252 | X8: =1.3*C8 -> 273 | Y8: =1.6*C8 -> 336 | Z8: =1.3*C8 -> 273 | AB8: 1.26 - 1.5 | AC8: 74
A9: СМ 25-Э | B9: 24 | C9: 210 | E9: =2.4*C9 -> 504 | F9: =1.7*C9 -> 357 | G9: =1.5*C9 -> 315 | H9: =1.4*C9 -> 294 | I9: =1.3*C9 -> 273 | J9: =1.2*C9 -> 252 | K9: =1*C9 -> 210 | L9: =1.1*C9 -> 231 | M9: =1.7*C9 -> 357 | N9: =1.7*C9 -> 357 | O9: =1.6*C9 -> 336 | P9: =1.6*C9 -> 336 | Q9: =1.1*C9 -> 231 | R9: =1.3*C9 -> 273 | S9: =1.6*C9 -> 336 | T9: =1.3*C9 -> 273 | U9: =1.7*C9 -> 357 | V9: =1.7*C9 -> 357 | W9: =1.2*C9 -> 252 | X9: =1.3*C9 -> 273 | Y9: =1.6*C9 -> 336 | Z9: =1.3*C9 -> 273 | AB9: 1.51 - 1.75 | AC9: 77
A10: СМ 23-Э | B10: 34 | C10: 215 | E10: =2.4*C10 -> 516 | F10: =1.7*C10 -> 365.5 | G10: =1.5*C10 -> 322.5 | H10: =1.4*C10 -> 301 | I10: =1.3*C10 -> 279.5 | J10: =1.2*C10 -> 258 | K10: =1*C10 -> 215 | L10: =1.1*C10 -> 236.5 | M10: =1.7*C10 -> 365.5 | N10: =1.7*C10 -> 365.5 | O10: =1.6*C10 -> 344 | P10: =1.6*C10 -> 344 | Q10: =1.1*C10 -> 236.5 | R10: =1.3*C10 -> 279.5 | S10: =1.6*C10 -> 344 | T10: =1.3*C10 -> 279.5 | U10: =1.7*C10 -> 365.5 | V10: =1.7*C10 -> 365.5 | W10: =1.2*C10 -> 258 | X10: =1.3*C10 -> 279.5 | Y10: =1.6*C10 -> 344 | Z10: =1.3*C10 -> 279.5 | AB10: 1.76 - 2 | AC10: 81
A11: СМ 23 | B11: 35 | C11: 263 | E11: =2.4*C11 -> 631.2 | F11: =1.7*C11 -> 447.1 | G11: =1.5*C11 -> 394.5 | H11: =1.4*C11 -> 368.2 | I11: =1.3*C11 -> 341.9 | J11: =1.2*C11 -> 315.6 | K11: =1*C11 -> 263 | L11: =1.1*C11 -> 289.3 | M11: =1.7*C11 -> 447.1 | N11: =1.7*C11 -> 447.1 | O11: =1.6*C11 -> 420.8 | P11: =1.6*C11 -> 420.8 | Q11: =1.1*C11 -> 289.3 | R11: =1.3*C11 -> 341.9 | S11: =1.6*C11 -> 420.8 | T11: =1.3*C11 -> 341.9 | U11: =1.7*C11 -> 447.1 | V11: =1.7*C11 -> 447.1 | W11: =1.2*C11 -> 315.6 | X11: =1.3*C11 -> 341.9 | Y11: =1.6*C11 -> 420.8 | Z11: =1.3*C11 -> 341.9 | AB11: 2.01 - 3 | AC11: 81
A12: СМ 20 | B12: 14 | C12: 170 | E12: =2.4*C12 -> 408 | F12: =1.7*C12 -> 289 | G12: =1.5*C12 -> 255 | H12: =1.4*C12 -> 238 | I12: =1.3*C12 -> 221 | J12: =1.2*C12 -> 204 | K12: =1*C12 -> 170 | L12: =1.1*C12 -> 187 | M12: =1.7*C12 -> 289 | N12: =1.7*C12 -> 289 | O12: =1.6*C12 -> 272 | P12: =1.6*C12 -> 272 | Q12: =1.1*C12 -> 187 | R12: =1.3*C12 -> 221 | S12: =1.6*C12 -> 272 | T12: =1.3*C12 -> 221 | U12: =1.7*C12 -> 289 | V12: =1.7*C12 -> 289 | W12: =1.2*C12 -> 204 | X12: =1.3*C12 -> 221 | Y12: =1.6*C12 -> 272 | Z12: =1.3*C12 -> 221 | AB12: 3.01 - 4 | AC12: 87
A13: СМ 20-Э | B13: 14 | C13: 170 | E13: =2.4*C13 -> 408 | F13: =1.7*C13 -> 289 | G13: =1.5*C13 -> 255 | H13: =1.4*C13 -> 238 | I13: =1.3*C13 -> 221 | J13: =1.2*C13 -> 204 | K13: =1*C13 -> 170 | L13: =1.1*C13 -> 187 | M13: =1.7*C13 -> 289 | N13: =1.7*C13 -> 289 | O13: =1.6*C13 -> 272 | P13: =1.6*C13 -> 272 | Q13: =1.1*C13 -> 187 | R13: =1.3*C13 -> 221 | S13: =1.6*C13 -> 272 | T13: =1.3*C13 -> 221 | U13: =1.7*C13 -> 289 | V13: =1.7*C13 -> 289 | W13: =1.2*C13 -> 204 | X13: =1.3*C13 -> 221 | Y13: =1.6*C13 -> 272 | Z13: =1.3*C13 -> 221 | AB13: 4.01 - 5 | AC13: 99
... A27: 200*100*40 4п | B27: 44 | C27: 269 | E27: =2.4*C27 -> 645.6 | F27: =1.7*C27 -> 457.3 | G27: =1.5*C27 -> 403.5 | H27: =1.4*C27 -> 376.6 | I27: =1.3*C27 -> 349.7 | J27: =1.2*C27 -> 322.8 | K27: =1*C27 -> 269 | L27: =1.1*C27 -> 295.9 | M27: =1.7*C27 -> 457.3 | N27: =1.7*C27 -> 457.3 | O27: =1.6*C27 -> 430.4 | P27: =1.6*C27 -> 430.4 | Q27: =1.1*C27 -> 295.9 | R27: =1.3*C27 -> 349.7 | S27: =1.6*C27 -> 430.4 | T27: =1.3*C27 -> 349.7 | U27: =1.7*C27 -> 457.3 | V27: =1.7*C27 -> 457.3 | W27: =1.2*C27 -> 322.8 | X27: =1.3*C27 -> 349.7 | Y27: =1.6*C27 -> 430.4 | Z27: =1.3*C27 -> 349.7 | AB27: 25.01 - 30 | AC27: 210
AB28: 30.01 - 35 | AC28: 215
AB29: 35.01 - 40 | AC29: 263
A30: Объём отгрузки* | B30: Тариф на литр отгрузки | D30: Тип точки отгрузки | E30: Тариф за отправление | G30: ДОСТАВКА ДО ПВЗ | I30: Выдача товара | K30: Обработка возврата | M30: Обратная логистика | O30: если коэф меньше 1,7 | P30: если коэф больше 1,6 | AB30: 40.01 - 45 | AC30: 269
A31: до 1000 л | B31: 1,9 ₽ | D31: ПВЗ/ППЗ | E31: 30 ₽ | G31: до 25р | I31: от 5% до 10% от цены товара, но не превышает 250 ₽. | K31: 15р за товар | M31: Тариф на обратную логистику равен тарифу на логистику, но без учёта межкластерного коэффициента. | AB31: 45.01 - 50 | AC31: 283
A32: от 1000 до 4000 л | B32: 1,7 ₽ | D32: СЦ | E32: 20 ₽ | AB32: 50.01 - 60 | AC32: 334
A33: от 4000 до 16 000 л | B33: 1,5 ₽ | AB33: 60.01 - 70 | AC33: 364
A34: более 16 000 л | B34: 1,3 ₽ | E34: Комиссия за отгрузку+отправление в сц 20р+ доставка до пвз 25р+выдача товара 250р+обработка возврата 15р+тариф на обратную логистику+межкласстерный коэффицент+вознаграждение МП | AB34: 70.01 - 80 | AC34: 443
AB35: 80.01 - 90 | AC35: 443
AB36: 90.01 - 100 | AC36: 455
AB37: 100.01 - 125 | AC37: 535
AB38: 125.01 - 150 | AC38: 659
AB39: 150.01 - 175 | AC39: 747
AB40: 175.01 - 190 | AC40: 905
AB41: 190.01 - 191 | AC41: 911
AB42: 191.01 - 192 | AC42: 917
AB43: 192.01 - 193 | AC43: 923
AB44: 193.01 - 194 | AC44: 929
AB45: 194.01 - 195 | AC45: 935
AB46: 195.01 - 196 | AC46: 941
... AB850: 999.01 - 1000 | AC850: 5765

Sheet Калькуляция
A1: Наименование | B1: SKU | C1: Размер | D1: Фактическая себестоимость | E1: Цена + НДС ближ | F1: Цена + НДС сред | G1: Цена + НДС дальн | H1: Общая комиссия на OZON за ед. товара FBS (1,5% - эквайринг, обработка отправления - 30 руб, доставка до места выдачи - 25 руб+логистика+вознаграждение OZON) БЛИЖ | I1: Общая комиссия на OZON за ед. товара FBS (1,5% - эквайринг, обработка отправления - 30 руб, доставка до места выдачи - 25 руб+логистика+вознаграждение OZON) СРЕД | J1: Общая комиссия на OZON за ед. товара FBS (1,5% - эквайринг, обработка отправления - 30 руб, доставка до места выдачи - 25 руб+логистика+вознаграждение OZON) ДАЛЬН | K1: Чистая цена после вычета комиссий БЛИЖ | L1: Чистая цена после вычета комиссий СРЕД | M1: Чистая цена после вычета комиссий ДАЛЬН | N1: Прибыль БЛИЖ | O1: Прибыль СРЕД | P1: Прибыль ДАЛЬН | Q1: Рекоменндованная цена ближ | R1: Рекоменндованная цена сред | S1: Рекоменндованная цена дальн | T1: Желаемая рент | U1: Цена от 01.04.2026 | V1: Разница с нынешними БЛИЖ | W1: Разница с нынешними СРЕД | X1: Разница с нынешними ДАЛЬН
A2: Аптечка АМУ-1 | B2: 907247263 | C2: 385х300х160 | D2: ='[1]АМУ-1'!F43/1.07 -> 535.30474 | E2: 2620.3758 | F2: 2859.3716 | G2: 3150.6549 | H2: =('Общая комиссия'!G2+'Общая комиссия'!J2+'Общая комиссия'!K2+'Общая комиссия'!L2+'Общая комиссия'!M2+'Общая комиссия'!N2+'Общая комиссия'!Q2)*1.22 -> 1925.6713 | I2: =('Общая комиссия'!H2+'Общая комиссия'!J2+'Общая комиссия'!K2+'Общая комиссия'!L2+'Общая комиссия'!M2+'Общая комиссия'!O2+'Общая комиссия'!Q2)*1.22 -> 2164.8013 | J2: =('Общая комиссия'!I2+'Общая комиссия'!J2+'Общая комиссия'!K2+'Общая комиссия'!L2+'Общая комиссия'!M2+'Общая комиссия'!P2+'Общая комиссия'!Q2)*1.22 -> 2618.5981 | K2: =E2-H2 -> 694.70447 | L2: =F2-I2 -> 694.57036 | M2: =G2-J2 -> 532.05677 | N2: =K2/D2-1 -> 0.29777381 | O2: =L2/D2-1 -> 0.29752328 | P2: =M2/D2-1 -> -0.0060675168 | Q2: =D2*($T$2/100+1)+H2 -> 2621.5675 | R2: =D2*($T$2/100+1)+I2 -> 2860.6974 | S2: =D2*($T$2/100+1)+J2 -> 3314.4943 | T2: 30 | U2: 3919 | V2: =U2-E2 -> 1298.6242 | W2: =U2-F2 -> 1059.6284 | X2: =U2-G2 -> 768.3451
A3: Ключница К-148 | B3: 629880865 | C3: 430х343х70 | D3: ='[1]К-148'!F46/1.07 -> 1529.4786 | E3: 5069.8174 | F3: 5175.958 | G3: 5021.8939 | H3: =('Общая комиссия'!G3+'Общая комиссия'!J3+'Общая комиссия'!K3+'Общая комиссия'!L3+'Общая комиссия'!M3+'Общая комиссия'!N3+'Общая комиссия'!Q3)*1.22 -> 3082.964 | I3: =('Общая комиссия'!H3+'Общая комиссия'!J3+'Общая комиссия'!K3+'Общая комиссия'!L3+'Общая комиссия'!M3+'Общая комиссия'!O3+'Общая комиссия'!Q3)*1.22 -> 3189.1534 | J3: =('Общая комиссия'!I3+'Общая комиссия'!J3+'Общая комиссия'!K3+'Общая комиссия'!L3+'Общая комиссия'!M3+'Общая комиссия'!P3+'Общая комиссия'!Q3)*1.22 -> 3300.5423 | K3: =E3-H3 -> 1986.8534 | L3: =F3-I3 -> 1986.8047 | M3: =G3-J3 -> 1721.3516 | N3: =K3/D3-1 -> 0.29903967 | O3: =L3/D3-1 -> 0.29900781 | P3: =M3/D3-1 -> 0.12544992 | Q3: =D3*($T$2/100+1)+H3 -> 5071.2862 | R3: =D3*($T$2/100+1)+I3 -> 5177.4756 | S3: =D3*($T$2/100+1)+J3 -> 5288.8645 | U3: 5853.1888 | V3: =U3-E3 -> 783.3714 | W3: =U3-F3 -> 677.23076 | X3: =U3-G3 -> 831.29488
A4: Ключница К-20 | B4: 633898130 | C4: 275x195x70 | D4: ='[1]К-20'!F41/1.07 -> 302.76908 | E4: 1330.7173 | F4: 1422.1162 | G4: 1473.6112 | H4: =('Общая комиссия'!G4+'Общая комиссия'!J4+'Общая комиссия'!K4+'Общая комиссия'!L4+'Общая комиссия'!M4+'Общая комиссия'!N4+'Общая комиссия'!Q4)*1.22 -> 937.58904 | I4: =('Общая комиссия'!H4+'Общая комиссия'!J4+'Общая комиссия'!K4+'Общая комиссия'!L4+'Общая комиссия'!M4+'Общая комиссия'!O4+'Общая комиссия'!Q4)*1.22 -> 1029.0299 | J4: =('Общая комиссия'!I4+'Общая комиссия'!J4+'Общая комиссия'!K4+'Общая комиссия'!L4+'Общая комиссия'!M4+'Общая комиссия'!P4+'Общая комиссия'!Q4)*1.22 -> 1158.4632 | K4: =E4-H4 -> 393.12825 | L4: =F4-I4 -> 393.08628 | M4: =G4-J4 -> 315.14802 | N4: =K4/D4-1 -> 0.29844252 | O4: =L4/D4-1 -> 0.29830389 | P4: =M4/D4-1 -> 0.040885748 | Q4: =D4*($T$2/100+1)+H4 -> 1331.1889 | R4: =D4*($T$2/100+1)+I4 -> 1422.6297 | S4: =D4*($T$2/100+1)+J4 -> 1552.063 | U4: 1511.9205 | V4: =U4-E4 -> 181.20324 | W4: =U4-F4 -> 89.804356 | X4: =U4-G4 -> 38.309311
A5: Ключница К-40 | B5: 629825193 | C5: 430х343х70 | D5: ='[1]К-40'!F44/1.07 -> 716.9912 | E5: 2790.7106 | F5: 2896.8512 | G5: 2970.6978 | H5: =('Общая комиссия'!G5+'Общая комиссия'!J5+'Общая комиссия'!K5+'Общая комиссия'!L5+'Общая комиссия'!M5+'Общая комиссия'!N5+'Общая комиссия'!Q5)*1.22 -> 1859.5394 | I5: =('Общая комиссия'!H5+'Общая комиссия'!J5+'Общая комиссия'!K5+'Общая комиссия'!L5+'Общая комиссия'!M5+'Общая комиссия'!O5+'Общая комиссия'!Q5)*1.22 -> 1965.7288 | J5: =('Общая комиссия'!I5+'Общая комиссия'!J5+'Общая комиссия'!K5+'Общая комиссия'!L5+'Общая комиссия'!M5+'Общая комиссия'!P5+'Общая комиссия'!Q5)*1.22 -> 2196.6797 | K5: =E5-H5 -> 931.17115 | L5: =F5-I5 -> 931.12241 | M5: =G5-J5 -> 774.01806 | N5: =K5/D5-1 -> 0.29872048 | O5: =L5/D5-1 -> 0.2986525 | P5: =M5/D5-1 -> 0.079536353 | Q5: =D5*($T$2/100+1)+H5 -> 2791.628 | R5: =D5*($T$2/100+1)+I5 -> 2897.8174 | S5: =D5*($T$2/100+1)+J5 -> 3128.7683 | U5: 3514.0143 | V5: =U5-E5 -> 723.30367 | W5: =U5-F5 -> 617.16304 | X5: =U5-G5 -> 543.31648
A6: Ключница К-60 | B6: 629844259 | C6: 430х343х70 | D6: ='[1]К-60'!F44/1.07 -> 850.1986 | E6: 3196.5966 | F6: 3287.9955 | G6: 3346.6093 | H6: =('Общая комиссия'!G6+'Общая комиссия'!J6+'Общая комиссия'!K6+'Общая комиссия'!L6+'Общая комиссия'!M6+'Общая комиссия'!N6+'Общая комиссия'!Q6)*1.22 -> 2092.3641 | I6: =('Общая комиссия'!H6+'Общая комиссия'!J6+'Общая комиссия'!K6+'Общая комиссия'!L6+'Общая комиссия'!M6+'Общая комиссия'!O6+'Общая комиссия'!Q6)*1.22 -> 2183.8049 | J6: =('Общая комиссия'!I6+'Общая комиссия'!J6+'Общая комиссия'!K6+'Общая комиссия'!L6+'Общая комиссия'!M6+'Общая комиссия'!P6+'Общая комиссия'!Q6)*1.22 -> 2419.3917 | K6: =E6-H6 -> 1104.2326 | L6: =F6-I6 -> 1104.1906 | M6: =G6-J6 -> 927.21758 | N6: =K6/D6-1 -> 0.29879367 | O6: =L6/D6-1 -> 0.2987443 | P6: =M6/D6-1 -> 0.090589395 | Q6: =D6*($T$2/100+1)+H6 -> 3197.6223 | R6: =D6*($T$2/100+1)+I6 -> 3289.0631 | S6: =D6*($T$2/100+1)+J6 -> 3524.6499 | U6: 3980.4151 | V6: =U6-E6 -> 783.81842 | W6: =U6-F6 -> 692.41953 | X6: =U6-G6 -> 633.80576
A7: Почтовый ящик ЯП-04 с замками | B7: 632063202 | C7: 474х377х190 | D7: ='[1]ЯП-04 NEW'!F39/1.07 -> 1032.8655 | E7: 4755.0731 | F7: 5037.7341 | G7: 5571.1092 | H7: =('Общая комиссия'!G7+'Общая комиссия'!J7+'Общая комиссия'!K7+'Общая комиссия'!L7+'Общая комиссия'!M7+'Общая комиссия'!N7+'Общая комиссия'!Q7)*1.22 -> 3414.882 | I7: =('Общая комиссия'!H7+'Общая комиссия'!J7+'Общая комиссия'!K7+'Общая комиссия'!L7+'Общая комиссия'!M7+'Общая комиссия'!O7+'Общая комиссия'!Q7)*1.22 -> 3697.7359 | J7: =('Общая комиссия'!I7+'Общая комиссия'!J7+'Общая комиссия'!K7+'Общая комиссия'!L7+'Общая комиссия'!M7+'Общая комиссия'!P7+'Общая комиссия'!Q7)*1.22 -> 4511.0719 | K7: =E7-H7 -> 1340.1911 | L7: =F7-I7 -> 1339.9982 | M7: =G7-J7 -> 1060.0374 | N7: =K7/D7-1 -> 0.29754653 | O7: =L7/D7-1 -> 0.29735979 | P7: =M7/D7-1 -> 0.026307249 | Q7: =D7*($T$2/100+1)+H7 -> 4757.6072 | R7: =D7*($T$2/100+1)+I7 -> 5040.4611 | S7: =D7*($T$2/100+1)+J7 -> 5853.797 | U7: 6828.5089 | V7: =U7-E7 -> 2073.4358 | W7: =U7-F7 -> 1790.7748 | X7: =U7-G7 -> 1257.3997
A8: Почтовый ящик ЯП-05 с замками | B8: 631939684 | C8: 559х377х190 | D8: ='[1]ЯП-05 NEW'!F39/1.07 -> 1219.2204 | E8: 5538.2857 | F8: 5814.7344 | G8: 6357.0715 | H8: =('Общая комиссия'!G8+'Общая комиссия'!J8+'Общая комиссия'!K8+'Общая комиссия'!L8+'Общая комиссия'!M8+'Общая комиссия'!N8+'Общая комиссия'!Q8)*1.22 -> 3956.2299 | I8: =('Общая комиссия'!H8+'Общая комиссия'!J8+'Общая комиссия'!K8+'Общая комиссия'!L8+'Общая комиссия'!M8+'Общая комиссия'!O8+'Общая комиссия'!Q8)*1.22 -> 4232.8672 | J8: =('Общая комиссия'!I8+'Общая комиссия'!J8+'Общая комиссия'!K8+'Общая комиссия'!L8+'Общая комиссия'!M8+'Общая комиссия'!P8+'Общая комиссия'!Q8)*1.22 -> 5094.6163 | K8: =E8-H8 -> 1582.0557 | L8: =F8-I8 -> 1581.8671 | M8: =G8-J8 -> 1262.4551 | N8: =K8/D8-1 -> 0.29759621 | O8: =L8/D8-1 -> 0.29744149 | P8: =M8/D8-1 -> 0.035460987 | Q8: =D8*($T$2/100+1)+H8 -> 5541.2164 | R8: =D8*($T$2/100+1)+I8 -> 5817.8537 | S8: =D8*($T$2/100+1)+J8 -> 6679.6028 | U8: 7997.6248 | V8: =U8-E8 -> 2459.3392 | W8: =U8-F8 -> 2182.8905 | X8: =U8-G8 -> 1640.5534
A9: Почтовый ящик ЯП-06 с замками | B9: 631949713 | C9: 643х377х190 | D9: ='[1]ЯП-06 NEW'!F39/1.07 -> 1270.36 | E9: 6006.4496 | F9: 6369.871 | G9: 7108.2938 | H9: =('Общая комиссия'!G9+'Общая комиссия'!J9+'Общая комиссия'!K9+'Общая комиссия'!L9+'Общая комиссия'!M9+'Общая комиссия'!N9+'Общая комиссия'!Q9)*1.22 -> 4358.2265 | I9: =('Общая комиссия'!H9+'Общая комиссия'!J9+'Общая комиссия'!K9+'Общая комиссия'!L9+'Общая комиссия'!M9+'Общая комиссия'!O9+'Общая комиссия'!Q9)*1.22 -> 4721.8958 | J9: =('Общая комиссия'!I9+'Общая комиссия'!J9+'Общая комиссия'!K9+'Общая комиссия'!L9+'Общая комиссия'!M9+'Общая комиссия'!P9+'Общая комиссия'!Q9)*1.22 -> 5817.566 | K9: =E9-H9 -> 1648.2231 | L9: =F9-I9 -> 1647.9751 | M9: =G9-J9 -> 1290.7278 | N9: =K9/D9-1 -> 0.2974457 | O9: =L9/D9-1 -> 0.29725049 | P9: =M9/D9-1 -> 0.016033108 | Q9: =D9*($T$2/100+1)+H9 -> 6009.6945 | R9: =D9*($T$2/100+1)+I9 -> 6373.3638 | S9: =D9*($T$2/100+1)+J9 -> 7469.034 | U9: 8582.266 | V9: =U9-E9 -> 2575.8164 | W9: =U9-F9 -> 2212.3951 | X9: =U9-G9 -> 1473.9723
A10: Почтовый ящик ЯП-08 с замками | B10: 631946118 | C10: 812х377х190 | D10: ='[1]ЯП-08 NEW'!F39/1.07 -> 1776.5508 | E10: 7836.3059 | F10: 8561.5279 | G10: 9720.9657 | H10: =('Общая комиссия'!G10+'Общая комиссия'!J10+'Общая комиссия'!K10+'Общая комиссия'!L10+'Общая комиссия'!M10+'Общая комиссия'!N10+'Общая комиссия'!Q10)*1.22 -> 5530.8709 | I10: =('Общая комиссия'!H10+'Общая комиссия'!J10+'Общая комиссия'!K10+'Общая комиссия'!L10+'Общая комиссия'!M10+'Общая комиссия'!O10+'Общая комиссия'!Q10)*1.22 -> 6256.5877 | J10: =('Общая комиссия'!I10+'Общая комиссия'!J10+'Общая комиссия'!K10+'Общая комиссия'!L10+'Общая комиссия'!M10+'Общая комиссия'!P10+'Общая комиссия'!Q10)*1.22 -> 7904.6821 | K10: =E10-H10 -> 2305.435 | L10: =F10-I10 -> 2304.9402 | M10: =G10-J10 -> 1816.2836 | N10: =K10/D10-1 -> 0.29770282 | O10: =L10/D10-1 -> 0.29742427 | P10: =M10/D10-1 -> 0.022365109 | Q10: =D10*($T$2/100+1)+H10 -> 7840.3869 | R10: =D10*($T$2/100+1)+I10 -> 8566.1038 | S10: =D10*($T$2/100+1)+J10 -> 10214.198 | U10: 12009.336 | V10: =U10-E10 -> 4173.0299 | W10: =U10-F10 -> 3447.8079 | X10: =U10-G10 -> 2288.3701
A11: Сейф мебельный СМ-20 | B11: 1667684227 | C11: 200х310х200 | D11: ='[1]СМ-20'!F45/1.07 -> 1757.9447 | E11: 5324.119 | F11: 5409.0258 | G11: 5228.0186 | H11: =('Общая комиссия'!G11+'Общая комиссия'!J11+'Общая комиссия'!K11+'Общая комиссия'!L11+'Общая комиссия'!M11+'Общая комиссия'!N11+'Общая комиссия'!Q11)*1.22 -> 3039.5553 | I11: =('Общая комиссия'!H11+'Общая комиссия'!J11+'Общая комиссия'!K11+'Общая комиссия'!L11+'Общая комиссия'!M11+'Общая комиссия'!O11+'Общая комиссия'!Q11)*1.22 -> 3124.4828 | J11: =('Общая комиссия'!I11+'Общая комиссия'!J11+'Общая комиссия'!K11+'Общая комиссия'!L11+'Общая комиссия'!M11+'Общая комиссия'!P11+'Общая комиссия'!Q11)*1.22 -> 3240.9893 | K11: =E11-H11 -> 2284.5637 | L11: =F11-I11 -> 2284.543 | M11: =G11-J11 -> 1987.0292 | N11: =K11/D11-1 -> 0.29956515 | O11: =L11/D11-1 -> 0.29955337 | P11: =M11/D11-1 -> 0.13031385 | Q11: =D11*($T$2/100+1)+H11 -> 5324.8834 | R11: =D11*($T$2/100+1)+I11 -> 5409.811 | S11: =D11*($T$2/100+1)+J11 -> 5526.3174 | U11: 6083.7761 | V11: =U11-E11 -> 759.6571 | W11: =U11-F11 -> 674.75029 | X11: =U11-G11 -> 855.75755
A12: Сейф мебельный СМ-20Э | B12: 1667684137 | C12: 200х310х200 | D12: ='[1]СМ-20Э'!F53/1.07 -> 2118.0062 | E12: 6260.4327 | F12: 6345.3395 | G12: 6070.7009 | H12: =('Общая комиссия'!G12+'Общая комиссия'!J12+'Общая комиссия'!K12+'Общая комиссия'!L12+'Общая комиссия'!M12+'Общая комиссия'!N12+'Общая комиссия'!Q12)*1.22 -> 3507.8995 | I12: =('Общая комиссия'!H12+'Общая комиссия'!J12+'Общая комиссия'!K12+'Общая комиссия'!L12+'Общая комиссия'!M12+'Общая комиссия'!O12+'Общая комиссия'!Q12)*1.22 -> 3592.827 | J12: =('Общая комиссия'!I12+'Общая комиссия'!J12+'Общая комиссия'!K12+'Общая комиссия'!L12+'Общая комиссия'!M12+'Общая комиссия'!P12+'Общая комиссия'!Q12)*1.22 -> 3663.6413 | K12: =E12-H12 -> 2752.5333 | L12: =F12-I12 -> 2752.5126 | M12: =G12-J12 -> 2407.0596 | N12: =K12/D12-1 -> 0.29958696 | O12: =L12/D12-1 -> 0.29957718 | P12: =M12/D12-1 -> 0.13647427 | Q12: =D12*($T$2/100+1)+H12 -> 6261.3076 | R12: =D12*($T$2/100+1)+I12 -> 6346.2351 | S12: =D12*($T$2/100+1)+J12 -> 6417.0494 | U12: 7040.2145 | V12: =U12-E12 -> 779.7818 | W12: =U12-F12 -> 694.87499 | X12: =U12-G12 -> 969.51362
A13: Сейф мебельный СМ-23 | B13: 1672231528 | C13: 229х405х335 | D13: ='[1]СМ-23'!F48/1.07 -> 2310.3243 | E13: 7486.2973 | F13: 7735.5399 | G13: 7876.5144 | H13: =('Общая комиссия'!G13+'Общая комиссия'!J13+'Общая комиссия'!K13+'Общая комиссия'!L13+'Общая комиссия'!M13+'Общая комиссия'!N13+'Общая комиссия'!Q13)*1.22 -> 4484.0269 | I13: =('Общая комиссия'!H13+'Общая комиссия'!J13+'Общая комиссия'!K13+'Общая комиссия'!L13+'Общая комиссия'!M13+'Общая комиссия'!O13+'Общая комиссия'!Q13)*1.22 -> 4733.3303 | J13: =('Общая комиссия'!I13+'Общая комиссия'!J13+'Общая комиссия'!K13+'Общая комиссия'!L13+'Общая комиссия'!M13+'Общая комиссия'!P13+'Общая комиссия'!Q13)*1.22 -> 5322.6389 | K13: =E13-H13 -> 3002.2704 | L13: =F13-I13 -> 3002.2096 | M13: =G13-J13 -> 2553.8756 | N13: =K13/D13-1 -> 0.2995017 | O13: =L13/D13-1 -> 0.29947539 | P13: =M13/D13-1 -> 0.10541863 | Q13: =D13*($T$2/100+1)+H13 -> 7487.4485 | R13: =D13*($T$2/100+1)+I13 -> 7736.7519 | S13: =D13*($T$2/100+1)+J13 -> 8326.0605 | U13: 9118.4065 | V13: =U13-E13 -> 1632.1092 | W13: =U13-F13 -> 1382.8666 | X13: =U13-G13 -> 1241.8921
A14: Сейф мебельный СМ-23Э | B14: 1672231536 | C14: 229х405х335 | D14: ='[1]СМ-23Э'!F50/1.07 -> 2662.5406 | E14: 8274.1354 | F14: 8460.3826 | G14: 8400.691 | H14: =('Общая комиссия'!G14+'Общая комиссия'!J14+'Общая комиссия'!K14+'Общая комиссия'!L14+'Общая комиссия'!M14+'Общая комиссия'!N14+'Общая комиссия'!Q14)*1.22 -> 4814.0535 | I14: =('Общая комиссия'!H14+'Общая комиссия'!J14+'Общая комиссия'!K14+'Общая комиссия'!L14+'Общая комиссия'!M14+'Общая комиссия'!O14+'Общая комиссия'!Q14)*1.22 -> 5000.3462 | J14: =('Общая комиссия'!I14+'Общая комиссия'!J14+'Общая комиссия'!K14+'Общая комиссия'!L14+'Общая комиссия'!M14+'Общая комиссия'!P14+'Общая комиссия'!Q14)*1.22 -> 5418.7737 | K14: =E14-H14 -> 3460.0819 | L14: =F14-I14 -> 3460.0365 | M14: =G14-J14 -> 2981.9173 | N14: =K14/D14-1 -> 0.29954148 | O14: =L14/D14-1 -> 0.29952441 | P14: =M14/D14-1 -> 0.1199519 | Q14: =D14*($T$2/100+1)+H14 -> 8275.3563 | R14: =D14*($T$2/100+1)+I14 -> 8461.6489 | S14: =D14*($T$2/100+1)+J14 -> 8880.0764 | U14: 9977.525 | V14: =U14-E14 -> 1703.3896 | W14: =U14-F14 -> 1517.1424 | X14: =U14-G14 -> 1576.834
A15: Сейф мебельный СМ-25 | B15: 1672261347 | C15: 250х350х250 | D15: ='[1]СМ-25'!F45/1.07 -> 1970.8381 | E15: 6103.6318 | F15: 6320.0072 | G15: 6210.5943 | H15: =('Общая комиссия'!G15+'Общая комиссия'!J15+'Общая комиссия'!K15+'Общая комиссия'!L15+'Общая комиссия'!M15+'Общая комиссия'!N15+'Общая комиссия'!Q15)*1.22 -> 3542.4396 | I15: =('Общая комиссия'!H15+'Общая комиссия'!J15+'Общая комиссия'!K15+'Общая комиссия'!L15+'Общая комиссия'!M15+'Общая комиссия'!O15+'Общая комиссия'!Q15)*1.22 -> 3758.8678 | J15: =('Общая комиссия'!I15+'Общая комиссия'!J15+'Общая комиссия'!K15+'Общая комиссия'!L15+'Общая комиссия'!M15+'Общая комиссия'!P15+'Общая комиссия'!Q15)*1.22 -> 4002.9103 | K15: =E15-H15 -> 2561.1922 | L15: =F15-I15 -> 2561.1394 | M15: =G15-J15 -> 2207.6839 | N15: =K15/D15-1 -> 0.29954467 | O15: =L15/D15-1 -> 0.29951788 | P15: =M15/D15-1 -> 0.12017517 | Q15: =D15*($T$2/100+1)+H15 -> 6104.5292 | R15: =D15*($T$2/100+1)+I15 -> 6320.9574 | S15: =D15*($T$2/100+1)+J15 -> 6564.9999 | U15: 7396.2062 | V15: =U15-E15 -> 1292.5744 | W15: =U15-F15 -> 1076.199 | X15: =U15-G15 -> 1185.612
A16: Сейф мебельный СМ-25Э | B16: 1672260987 | C16: 250х350х250 | D16: ='[1]СМ-25Э'!F50/1.07 -> 2358.8977 | E16: 7112.7525 | F16: 7329.1279 | G16: 7118.8029 | H16: =('Общая комиссия'!G16+'Общая комиссия'!J16+'Общая комиссия'!K16+'Общая комиссия'!L16+'Общая комиссия'!M16+'Общая комиссия'!N16+'Общая комиссия'!Q16)*1.22 -> 4047.2018 | I16: =('Общая комиссия'!H16+'Общая комиссия'!J16+'Общая комиссия'!K16+'Общая комиссия'!L16+'Общая комиссия'!M16+'Общая комиссия'!O16+'Общая комиссия'!Q16)*1.22 -> 4263.63 | J16: =('Общая комиссия'!I16+'Общая комиссия'!J16+'Общая комиссия'!K16+'Общая комиссия'!L16+'Общая комиссия'!M16+'Общая комиссия'!P16+'Общая комиссия'!Q16)*1.22 -> 4458.4274 | K16: =E16-H16 -> 3065.5507 | L16: =F16-I16 -> 3065.4979 | M16: =G16-J16 -> 2660.3755 | N16: =K16/D16-1 -> 0.29956914 | O16: =L16/D16-1 -> 0.29954676 | P16: =M16/D16-1 -> 0.1278045 | Q16: =D16*($T$2/100+1)+H16 -> 7113.7689 | R16: =D16*($T$2/100+1)+I16 -> 7330.1971 | S16: =D16*($T$2/100+1)+J16 -> 7524.9944 | U16: 8427.0167 | V16: =U16-E16 -> 1314.2642 | W16: =U16-F16 -> 1097.8888 | X16: =U16-G16 -> 1308.2138
A17: Сейф мебельный СМ-30 | B17: 1706788520 | C17: 300х380х300 | D17: ='[1]СМ-30'!F45/1.07 -> 2298.7606 | E17: 7465.4968 | F17: 7714.7394 | G17: 7857.7939 | H17: =('Общая комиссия'!G17+'Общая комиссия'!J17+'Общая комиссия'!K17+'Общая комиссия'!L17+'Общая комиссия'!M17+'Общая комиссия'!N17+'Общая комиссия'!Q17)*1.22 -> 4478.2585 | I17: =('Общая комиссия'!H17+'Общая комиссия'!J17+'Общая комиссия'!K17+'Общая комиссия'!L17+'Общая комиссия'!M17+'Общая комиссия'!O17+'Общая комиссия'!Q17)*1.22 -> 4727.5619 | J17: =('Общая комиссия'!I17+'Общая комиссия'!J17+'Общая комиссия'!K17+'Общая комиссия'!L17+'Общая комиссия'!M17+'Общая комиссия'!P17+'Общая комиссия'!Q17)*1.22 -> 5317.8855 | K17: =E17-H17 -> 2987.2383 | L17: =F17-I17 -> 2987.1775 | M17: =G17-J17 -> 2539.9084 | N17: =K17/D17-1 -> 0.29949953 | O17: =L17/D17-1 -> 0.29947308 | P17: =M17/D17-1 -> 0.10490343 | Q17: =D17*($T$2/100+1)+H17 -> 7466.6472 | R17: =D17*($T$2/100+1)+I17 -> 7715.9506 | S17: =D17*($T$2/100+1)+J17 -> 8306.2743 | U17: 9237.6693 | V17: =U17-E17 -> 1772.1725 | W17: =U17-F17 -> 1522.93 | X17: =U17-G17 -> 1379.8754
A18: Сейф мебельный СМ-30Э | B18: 1706788784 | C18: 300х380х300 | D18: ='[1]СМ-30Э'!F53/1.07 -> 2799.4389 | E18: 8767.4741 | F18: 9016.7167 | G18: 9029.5735 | H18: =('Общая комиссия'!G18+'Общая комиссия'!J18+'Общая комиссия'!K18+'Общая комиссия'!L18+'Общая комиссия'!M18+'Общая комиссия'!N18+'Общая комиссия'!Q18)*1.22 -> 5129.5075 | I18: =('Общая комиссия'!H18+'Общая комиссия'!J18+'Общая комиссия'!K18+'Общая комиссия'!L18+'Общая комиссия'!M18+'Общая комиссия'!O18+'Общая комиссия'!Q18)*1.22 -> 5378.8109 | J18: =('Общая комиссия'!I18+'Общая комиссия'!J18+'Общая комиссия'!K18+'Общая комиссия'!L18+'Общая комиссия'!M18+'Общая комиссия'!P18+'Общая комиссия'!Q18)*1.22 -> 5905.5981 | K18: =E18-H18 -> 3637.9666 | L18: =F18-I18 -> 3637.9058 | M18: =G18-J18 -> 3123.9755 | N18: =K18/D18-1 -> 0.29953421 | O18: =L18/D18-1 -> 0.29951249 | P18: =M18/D18-1 -> 0.11592917 | Q18: =D18*($T$2/100+1)+H18 -> 8768.7781 | R18: =D18*($T$2/100+1)+I18 -> 9018.0814 | S18: =D18*($T$2/100+1)+J18 -> 9544.8686 | U18: 10567.631 | V18: =U18-E18 -> 1800.1568 | W18: =U18-F18 -> 1550.9142 | X18: =U18-G18 -> 1538.0573
A19: Сейф мебельный СМ-50 | B19: 1672277739 | C19: 500х350х310 | D19: ='[1]СМ-50'!F48/1.07 -> 2878.1785 | E19: 9500.6294 | F19: 9821.0842 | G19: 10051.774 | H19: =('Общая комиссия'!G19+'Общая комиссия'!J19+'Общая комиссия'!K19+'Общая комиссия'!L19+'Общая комиссия'!M19+'Общая комиссия'!N19+'Общая комиссия'!Q19)*1.22 -> 5760.4838 | I19: =('Общая комиссия'!H19+'Общая комиссия'!J19+'Общая комиссия'!K19+'Общая комиссия'!L19+'Общая комиссия'!M19+'Общая комиссия'!O19+'Общая комиссия'!Q19)*1.22 -> 6081.0168 | J19: =('Общая комиссия'!I19+'Общая комиссия'!J19+'Общая комиссия'!K19+'Общая комиссия'!L19+'Общая комиссия'!M19+'Общая комиссия'!P19+'Общая комиссия'!Q19)*1.22 -> 6883.8692 | K19: =E19-H19 -> 3740.1456 | L19: =F19-I19 -> 3740.0674 | M19: =G19-J19 -> 3167.9045 | N19: =K19/D19-1 -> 0.29948356 | O19: =L19/D19-1 -> 0.2994564 | P19: =M19/D19-1 -> 0.10066297 | Q19: =D19*($T$2/100+1)+H19 -> 9502.1158 | R19: =D19*($T$2/100+1)+I19 -> 9822.6487 | S19: =D19*($T$2/100+1)+J19 -> 10625.501 | U19: 12417.621 | V19: =U19-E19 -> 2916.9918 | W19: =U19-F19 -> 2596.5371 | X19: =U19-G19 -> 2365.8476
A20: Сейф мебельный СМ-50Э | B20: 1672277747 | C20: 500х350х310 | D20: ='[1]СМ-50Э'!F53/1.07 -> 3279.2426 | E20: 10543.567 | F20: 10864.022 | G20: 10990.418 | H20: =('Общая комиссия'!G20+'Общая комиссия'!J20+'Общая комиссия'!K20+'Общая комиссия'!L20+'Общая комиссия'!M20+'Общая комиссия'!N20+'Общая комиссия'!Q20)*1.22 -> 6282.1615 | I20: =('Общая комиссия'!H20+'Общая комиссия'!J20+'Общая комиссия'!K20+'Общая комиссия'!L20+'Общая комиссия'!M20+'Общая комиссия'!O20+'Общая комиссия'!Q20)*1.22 -> 6602.6944 | J20: =('Общая комиссия'!I20+'Общая комиссия'!J20+'Общая комиссия'!K20+'Общая комиссия'!L20+'Общая комиссия'!M20+'Общая комиссия'!P20+'Общая комиссия'!Q20)*1.22 -> 7354.6515 | K20: =E20-H20 -> 4261.406 | L20: =F20-I20 -> 4261.3279 | M20: =G20-J20 -> 3635.7665 | N20: =K20/D20-1 -> 0.29950923 | O20: =L20/D20-1 -> 0.29948539 | P20: =M20/D20-1 -> 0.1087214 | Q20: =D20*($T$2/100+1)+H20 -> 10545.177 | R20: =D20*($T$2/100+1)+I20 -> 10865.71 | S20: =D20*($T$2/100+1)+J20 -> 11617.667 | U20: 13482.976 | V20: =U20-E20 -> 2939.4082 | W20: =U20-F20 -> 2618.9534 | X20: =U20-G20 -> 2492.5577
A21: Стеллаж металлический СТ-СП | B21: 258467589 | C21: 2000x1000x400, 4 150кг | D21: ='[1]40(4) NEW'!F44/1.07 -> 2793.8175 | E21: 7814.1939 | F21: 8027.5475 | G21: 8092.1113 | H21: =('Общая комиссия'!G21+'Общая комиссия'!J21+'Общая комиссия'!K21+'Общая комиссия'!L21+'Общая комиссия'!M21+'Общая комиссия'!N21+'Общая комиссия'!Q21)*1.22 -> 4182.4868 | I21: =('Общая комиссия'!H21+'Общая комиссия'!J21+'Общая комиссия'!K21+'Общая комиссия'!L21+'Общая комиссия'!M21+'Общая комиссия'!O21+'Общая комиссия'!Q21)*1.22 -> 4395.8529 | J21: =('Общая комиссия'!I21+'Общая комиссия'!J21+'Общая комиссия'!K21+'Общая комиссия'!L21+'Общая комиссия'!M21+'Общая комиссия'!P21+'Общая комиссия'!Q21)*1.22 -> 4986.6399 | K21: =E21-H21 -> 3631.7071 | L21: =F21-I21 -> 3631.6947 | M21: =G21-J21 -> 3105.4713 | N21: =K21/D21-1 -> 0.29990849 | O21: =L21/D21-1 -> 0.29990403 | P21: =M21/D21-1 -> 0.11155125 | Q21: =D21*($T$2/100+1)+H21 -> 7814.4496 | R21: =D21*($T$2/100+1)+I21 -> 8027.8157 | S21: =D21*($T$2/100+1)+J21 -> 8618.6027 | U21: 9587.7421 | V21: =U21-E21 -> 1773.5482 | W21: =U21-F21 -> 1560.1946 | X21: =U21-G21 -> 1495.6309
A22: Стеллаж металлический СТ-СП | B22: 258473499 | C22: 2000x1000x500, 4 150кг | D22: ='[1]50(4) NEW'!F44/1.07 -> 3063.8194 | E22: 9152.8146 | F22: 8996.8845 | G22: 9158.6903 | H22: =('Общая комиссия'!G22+'Общая комиссия'!J22+'Общая комиссия'!K22+'Общая комиссия'!L22+'Общая комиссия'!M22+'Общая комиссия'!N22+'Общая комиссия'!Q22)*1.22 -> 5170.1512 | I22: =('Общая комиссия'!H22+'Общая комиссия'!J22+'Общая комиссия'!K22+'Общая комиссия'!L22+'Общая комиссия'!M22+'Общая комиссия'!O22+'Общая комиссия'!Q22)*1.22 -> 5014.2315 | J22: =('Общая комиссия'!I22+'Общая комиссия'!J22+'Общая комиссия'!K22+'Общая комиссия'!L22+'Общая комиссия'!M22+'Общая комиссия'!P22+'Общая комиссия'!Q22)*1.22 -> 5771.6246 | K22: =E22-H22 -> 3982.6634 | L22: =F22-I22 -> 3982.653 | M22: =G22-J22 -> 3387.0658 | N22: =K22/D22-1 -> 0.29990149 | O22: =L22/D22-1 -> 0.29989809 | P22: =M22/D22-1 -> 0.10550437 | Q22: =D22*($T$2/100+1)+H22 -> 9153.1164 | R22: =D22*($T$2/100+1)+I22 -> 8997.1968 | S22: =D22*($T$2/100+1)+J22 -> 9754.5898 | U22: 11568.409 | V22: =U22-E22 -> 2415.594 | W22: =U22-F22 -> 2571.5241 | X22: =U22-G22 -> 2409.7183
A23: Стеллаж металлический СТ-СП | B23: 888213183 | C23: 2000х1000х400, 6 150кг | D23: ='[1]40(6) NEW'!F44/1.07 -> 3625.801 | E23: 9768.511 | F23: 10533.338 | G23: 10813.345 | H23: =('Общая комиссия'!G23+'Общая комиссия'!J23+'Общая комиссия'!K23+'Общая комиссия'!L23+'Общая комиссия'!M23+'Общая комиссия'!N23+'Общая комиссия'!Q23)*1.22 -> 5055.2958 | I23: =('Общая комиссия'!H23+'Общая комиссия'!J23+'Общая комиссия'!K23+'Общая комиссия'!L23+'Общая комиссия'!M23+'Общая комиссия'!O23+'Общая комиссия'!Q23)*1.22 -> 5820.1479 | J23: =('Общая комиссия'!I23+'Общая комиссия'!J23+'Общая комиссия'!K23+'Общая комиссия'!L23+'Общая комиссия'!M23+'Общая комиссия'!P23+'Общая комиссия'!Q23)*1.22 -> 6803.3487 | K23: =E23-H23 -> 4713.2152 | L23: =F23-I23 -> 4713.1901 | M23: =G23-J23 -> 4009.9959 | N23: =K23/D23-1 -> 0.29991005 | O23: =L23/D23-1 -> 0.29990312 | P23: =M23/D23-1 -> 0.10596138 | Q23: =D23*($T$2/100+1)+H23 -> 9768.8372 | R23: =D23*($T$2/100+1)+I23 -> 10533.689 | S23: =D23*($T$2/100+1)+J23 -> 11516.89 | U23: 12214.235 | V23: =U23-E23 -> 2445.7243 | W23: =U23-F23 -> 1680.8973 | X23: =U23-G23 -> 1400.8908
A24: ШБС-01 мини | B24: 906309058 | C24: 350х440х360 | D24: ='[1]ШБС-01 мини'!F49/1.07 -> 2638.1991 | E24: 9149.4402 | F24: 9524.6735 | G24: 10095.599 | H24: =('Общая комиссия'!G24+'Общая комиссия'!J24+'Общая комиссия'!K24+'Общая комиссия'!L24+'Общая комиссия'!M24+'Общая комиссия'!N24+'Общая комиссия'!Q24)*1.22 -> 5721.276 | I24: =('Общая комиссия'!H24+'Общая комиссия'!J24+'Общая комиссия'!K24+'Общая комиссия'!L24+'Общая комиссия'!M24+'Общая комиссия'!O24+'Общая комиссия'!Q24)*1.22 -> 6096.6008 | J24: =('Общая комиссия'!I24+'Общая комиссия'!J24+'Общая комиссия'!K24+'Общая комиссия'!L24+'Общая комиссия'!M24+'Общая комиссия'!P24+'Общая комиссия'!Q24)*1.22 -> 7242.2663 | K24: =E24-H24 -> 3428.1642 | L24: =F24-I24 -> 3428.0727 | M24: =G24-J24 -> 2853.3324 | N24: =K24/D24-1 -> 0.29943348 | O24: =L24/D24-1 -> 0.29939878 | P24: =M24/D24-1 -> 0.081545511 | Q24: =D24*($T$2/100+1)+H24 -> 9150.9348 | R24: =D24*($T$2/100+1)+I24 -> 9526.2596 | S24: =D24*($T$2/100+1)+J24 -> 10671.925 | U24: 12153.617 | V24: =U24-E24 -> 3004.1773 | W24: =U24-F24 -> 2628.944 | X24: =U24-G24 -> 2058.0188
A25: ШБС-01 мини Т | B25: 906309023 | C25: 350х440х360 | D25: ='[1]ШБС-01 мини Т'!F48/1.07 -> 2818.2769 | E25: 9608.4492 | F25: 9983.6826 | G25: 10508.707 | H25: =('Общая комиссия'!G25+'Общая комиссия'!J25+'Общая комиссия'!K25+'Общая комиссия'!L25+'Общая комиссия'!M25+'Общая комиссия'!N25+'Общая комиссия'!Q25)*1.22 -> 5946.2363 | I25: =('Общая комиссия'!H25+'Общая комиссия'!J25+'Общая комиссия'!K25+'Общая комиссия'!L25+'Общая комиссия'!M25+'Общая комиссия'!O25+'Общая комиссия'!Q25)*1.22 -> 6321.5612 | J25: =('Общая комиссия'!I25+'Общая комиссия'!J25+'Общая комиссия'!K25+'Общая комиссия'!L25+'Общая комиссия'!M25+'Общая комиссия'!P25+'Общая комиссия'!Q25)*1.22 -> 7444.827 | K25: =E25-H25 -> 3662.2129 | L25: =F25-I25 -> 3662.1214 | M25: =G25-J25 -> 3063.8798 | N25: =K25/D25-1 -> 0.29945108 | O25: =L25/D25-1 -> 0.2994186 | P25: =M25/D25-1 -> 0.087146492 | Q25: =D25*($T$2/100+1)+H25 -> 9609.9963 | R25: =D25*($T$2/100+1)+I25 -> 9985.3211 | S25: =D25*($T$2/100+1)+J25 -> 11108.587 | U25: 12481.982 | V25: =U25-E25 -> 2873.5327 | W25: =U25-F25 -> 2498.2994 | X25: =U25-G25 -> 1973.2751
A26: Шкаф бухгалтерский ШБС-01-17 | B26: 2948118892 | C26: 1700x500x400 | D26: =9734/1.07 -> 9097.1963 | E26: 31197.987 | F26: 34076.602 | G26: 36915.344 | H26: =('Общая комиссия'!G26+'Общая комиссия'!J26+'Общая комиссия'!K26+'Общая комиссия'!L26+'Общая комиссия'!M26+'Общая комиссия'!N26+'Общая комиссия'!Q26)*1.22 -> 19376.68 | I26: =('Общая комиссия'!H26+'Общая комиссия'!J26+'Общая комиссия'!K26+'Общая комиссия'!L26+'Общая комиссия'!M26+'Общая комиссия'!O26+'Общая комиссия'!Q26)*1.22 -> 22255.997 | J26: =('Общая комиссия'!I26+'Общая комиссия'!J26+'Общая комиссия'!K26+'Общая комиссия'!L26+'Общая комиссия'!M26+'Общая комиссия'!P26+'Общая комиссия'!Q26)*1.22 -> 27196.505 | K26: =E26-H26 -> 11821.307 | L26: =F26-I26 -> 11820.605 | M26: =G26-J26 -> 9718.8386 | N26: =K26/D26-1 -> 0.29944506 | O26: =L26/D26-1 -> 0.29936787 | P26: =M26/D26-1 -> 0.068333397 | Q26: =D26*($T$2/100+1)+H26 -> 31203.035 | R26: =D26*($T$2/100+1)+I26 -> 34082.352 | S26: =D26*($T$2/100+1)+J26 -> 39022.86 | U26: 42319.478 | V26: =U26-E26 -> 11121.491 | W26: =U26-F26 -> 8242.8762 | X26: =U26-G26 -> 5404.1339
A27: Шкаф бухгалтерский ШБС-02-17 | B27: 2806318479 | C27: 1700x500x400 | D27: =10727/1.07 -> 10025.234 | E27: 33611.28 | F27: 36489.895 | G27: 39087.308 | H27: =('Общая комиссия'!G27+'Общая комиссия'!J27+'Общая комиссия'!K27+'Общая комиссия'!L27+'Общая комиссия'!M27+'Общая комиссия'!N27+'Общая комиссия'!Q27)*1.22 -> 20583.809 | I27: =('Общая комиссия'!H27+'Общая комиссия'!J27+'Общая комиссия'!K27+'Общая комиссия'!L27+'Общая комиссия'!M27+'Общая комиссия'!O27+'Общая комиссия'!Q27)*1.22 -> 23463.126 | J27: =('Общая комиссия'!I27+'Общая комиссия'!J27+'Общая комиссия'!K27+'Общая комиссия'!L27+'Общая комиссия'!M27+'Общая комиссия'!P27+'Общая комиссия'!Q27)*1.22 -> 28285.866 | K27: =E27-H27 -> 13027.471 | L27: =F27-I27 -> 13026.769 | M27: =G27-J27 -> 10801.442 | N27: =K27/D27-1 -> 0.29946805 | O27: =L27/D27-1 -> 0.29939801 | P27: =M27/D27-1 -> 0.077425469 | Q27: =D27*($T$2/100+1)+H27 -> 33616.613 | R27: =D27*($T$2/100+1)+I27 -> 36495.93 | S27: =D27*($T$2/100+1)+J27 -> 41318.67 | U27: 44784.641 | V27: =U27-E27 -> 11173.361 | W27: =U27-F27 -> 8294.7463 | X27: =U27-G27 -> 5697.3334
A28: Стеллаж металлический СТ-СПЭ | B28: 3558967942 | C28: 2000x1000x400, 4 | D28: ='[1]СПЭ(4)'!S42/1.07 -> 2072.4981 | E28: 7080.6951 | F28: 7324.4598 | G28: 7582.9585 | H28: =('Общая комиссия'!G28+'Общая комиссия'!J28+'Общая комиссия'!K28+'Общая комиссия'!L28+'Общая комиссия'!M28+'Общая комиссия'!N28+'Общая комиссия'!Q28)*1.22 -> 4387.5897 | I28: =('Общая комиссия'!H28+'Общая комиссия'!J28+'Общая комиссия'!K28+'Общая комиссия'!L28+'Общая комиссия'!M28+'Общая комиссия'!O28+'Общая комиссия'!Q28)*1.22 -> 4631.4139 | J28: =('Общая комиссия'!I28+'Общая комиссия'!J28+'Общая комиссия'!K28+'Общая комиссия'!L28+'Общая комиссия'!M28+'Общая комиссия'!P28+'Общая комиссия'!Q28)*1.22 -> 5321.5672 | K28: =E28-H28 -> 2693.1054 | L28: =F28-I28 -> 2693.0459 | M28: =G28-J28 -> 2261.3913 | N28: =K28/D28-1 -> 0.29944893 | O28: =L28/D28-1 -> 0.29942024 | P28: =M28/D28-1 -> 0.091142757 | Q28: =D28*($T$2/100+1)+H28 -> 7081.8372 | R28: =D28*($T$2/100+1)+I28 -> 7325.6613 | S28: =D28*($T$2/100+1)+J28 -> 8015.8147 | U28: 8671.1246 | V28: =U28-E28 -> 1590.4295 | W28: =U28-F28 -> 1346.6648 | X28: =U28-G28 -> 1088.1661
A29: Стеллаж металлический СТ-СПЭ | B29: 3558953998 | C29: 2000x1000x500, 4 | D29: ='[1]СПЭ(5)'!U36/1.07 -> 2282.1002 | E29: 8426.4492 | F29: 8275.9949 | G29: 8661.1933 | H29: =('Общая комиссия'!G29+'Общая комиссия'!J29+'Общая комиссия'!K29+'Общая комиссия'!L29+'Общая комиссия'!M29+'Общая комиссия'!N29+'Общая комиссия'!Q29)*1.22 -> 5461.089 | I29: =('Общая комиссия'!H29+'Общая комиссия'!J29+'Общая комиссия'!K29+'Общая комиссия'!L29+'Общая комиссия'!M29+'Общая комиссия'!O29+'Общая комиссия'!Q29)*1.22 -> 5310.665 | J29: =('Общая комиссия'!I29+'Общая комиссия'!J29+'Общая комиссия'!K29+'Общая комиссия'!L29+'Общая комиссия'!M29+'Общая комиссия'!P29+'Общая комиссия'!Q29)*1.22 -> 6188.9179 | K29: =E29-H29 -> 2965.3603 | L29: =F29-I29 -> 2965.3299 | M29: =G29-J29 -> 2472.2755 | N29: =K29/D29-1 -> 0.29939968 | O29: =L29/D29-1 -> 0.29938637 | P29: =M29/D29-1 -> 0.083333459 | Q29: =D29*($T$2/100+1)+H29 -> 8427.8192 | R29: =D29*($T$2/100+1)+I29 -> 8277.3953 | S29: =D29*($T$2/100+1)+J29 -> 9155.6481 | U29: 9331.338 | V29: =U29-E29 -> 904.88872 | W29: =U29-F29 -> 1055.3431 | X29: =U29-G29 -> 670.14461
A30: Стеллаж металлический СТ-СПЭ | B30: 3558882434 | C30: 2000х1000х400, 6 | D30: ='[1]СПЭ(4)'!S43/1.07 -> 2738.5513 | E30: 8920.6157 | F30: 9766.7582 | G30: 10313.475 | H30: =('Общая комиссия'!G30+'Общая комиссия'!J30+'Общая комиссия'!K30+'Общая комиссия'!L30+'Общая комиссия'!M30+'Общая комиссия'!N30+'Общая комиссия'!Q30)*1.22 -> 5361.9539 | I30: =('Общая комиссия'!H30+'Общая комиссия'!J30+'Общая комиссия'!K30+'Общая комиссия'!L30+'Общая комиссия'!M30+'Общая комиссия'!O30+'Общая комиссия'!Q30)*1.22 -> 6208.2357 | J30: =('Общая комиссия'!I30+'Общая комиссия'!J30+'Общая комиссия'!K30+'Общая комиссия'!L30+'Общая комиссия'!M30+'Общая комиссия'!P30+'Общая комиссия'!Q30)*1.22 -> 7342.0874 | K30: =E30-H30 -> 3558.6618 | L30: =F30-I30 -> 3558.5225 | M30: =G30-J30 -> 2971.3875 | N30: =K30/D30-1 -> 0.29946874 | O30: =L30/D30-1 -> 0.29941786 | P30: =M30/D30-1 -> 0.085021648 | Q30: =D30*($T$2/100+1)+H30 -> 8922.0706 | R30: =D30*($T$2/100+1)+I30 -> 9768.3524 | S30: =D30*($T$2/100+1)+J30 -> 10902.204 | U30: 12027.023 | V30: =U30-E30 -> 3106.4072 | W30: =U30-F30 -> 2260.2648 | X30: =U30-G30 -> 1713.5481
A31: ШО-5 | B31: 3541466873 | C31: =C26 -> 1700x500x400 | D31: =D26+2500 -> 11597.196 | E31: 42907.582 | F31: 46172.161 | G31: 48638.865 | H31: =('Общая комиссия'!G31+'Общая комиссия'!J31+'Общая комиссия'!K31+'Общая комиссия'!L31+'Общая комиссия'!M31+'Общая комиссия'!N31+'Общая комиссия'!Q31)*1.22 -> 27851.182 | I31: =('Общая комиссия'!H31+'Общая комиссия'!J31+'Общая комиссия'!K31+'Общая комиссия'!L31+'Общая комиссия'!M31+'Общая комиссия'!O31+'Общая комиссия'!Q31)*1.22 -> 31117.989 | J31: =('Общая комиссия'!I31+'Общая комиссия'!J31+'Общая комиссия'!K31+'Общая комиссия'!L31+'Общая комиссия'!M31+'Общая комиссия'!P31+'Общая комиссия'!Q31)*1.22 -> 36027.412 | K31: =E31-H31 -> 15056.4 | L31: =F31-I31 -> 15054.172 | M31: =G31-J31 -> 12611.454 | N31: =K31/D31-1 -> 0.29827931 | O31: =L31/D31-1 -> 0.29808722 | P31: =M31/D31-1 -> 0.087457133 | Q31: =D31*($T$2/100+1)+H31 -> 42927.537 | R31: =D31*($T$2/100+1)+I31 -> 46194.344 | S31: =D31*($T$2/100+1)+J31 -> 51103.767 | U31: 56203.001 | V31: =U31-E31 -> 13295.419 | W31: =U31-F31 -> 10030.84 | X31: =U31-G31 -> 7564.1359
A32: ШО-1 | B32: 3541430418 | D32: ='расход ШО1'!F40/1.07 -> 5469.87 | E32: 18800.428 | F32: 19225.973 | G32: 19031.025 | H32: =('Общая комиссия'!G32+'Общая комиссия'!J32+'Общая комиссия'!K32+'Общая комиссия'!L32+'Общая комиссия'!M32+'Общая комиссия'!N32+'Общая комиссия'!Q32)*1.22 -> 11697.844 | I32: =('Общая комиссия'!H32+'Общая комиссия'!J32+'Общая комиссия'!K32+'Общая комиссия'!L32+'Общая комиссия'!M32+'Общая комиссия'!O32+'Общая комиссия'!Q32)*1.22 -> 12123.679 | J32: =('Общая комиссия'!I32+'Общая комиссия'!J32+'Общая комиссия'!K32+'Общая комиссия'!L32+'Общая комиссия'!M32+'Общая комиссия'!P32+'Общая комиссия'!Q32)*1.22 -> 12883.707 | K32: =E32-H32 -> 7102.584 | L32: =F32-I32 -> 7102.2936 | M32: =G32-J32 -> 6147.318 | N32: =K32/D32-1 -> 0.29849229 | O32: =L32/D32-1 -> 0.2984392 | P32: =M32/D32-1 -> 0.12385084 | Q32: =D32*($T$2/100+1)+H32 -> 18808.675 | R32: =D32*($T$2/100+1)+I32 -> 19234.51 | S32: =D32*($T$2/100+1)+J32 -> 19994.538 | U32: 22673.872 | V32: =U32-E32 -> 3873.4433 | W32: =U32-F32 -> 3447.8986 | X32: =U32-G32 -> 3642.8469
A33: ШО-2 | B33: 3541476893 | D33: ='расход ШО2'!F40/1.07 -> 3522.7853 | E33: 12341.182 | F33: 12617.631 | G33: 12479.678 | H33: =('Общая комиссия'!G33+'Общая комиссия'!J33+'Общая комиссия'!K33+'Общая комиссия'!L33+'Общая комиссия'!M33+'Общая комиссия'!N33+'Общая комиссия'!Q33)*1.22 -> 7767.0612 | I33: =('Общая комиссия'!H33+'Общая комиссия'!J33+'Общая комиссия'!K33+'Общая комиссия'!L33+'Общая комиссия'!M33+'Общая комиссия'!O33+'Общая комиссия'!Q33)*1.22 -> 8043.6986 | J33: =('Общая комиссия'!I33+'Общая комиссия'!J33+'Общая комиссия'!K33+'Общая комиссия'!L33+'Общая комиссия'!M33+'Общая комиссия'!P33+'Общая комиссия'!Q33)*1.22 -> 8531.9687 | K33: =E33-H33 -> 4574.1206 | L33: =F33-I33 -> 4573.932 | M33: =G33-J33 -> 3947.7094 | N33: =K33/D33-1 -> 0.29843866 | O33: =L33/D33-1 -> 0.29838511 | P33: =M33/D33-1 -> 0.12062163 | Q33: =D33*($T$2/100+1)+H33 -> 12346.682 | R33: =D33*($T$2/100+1)+I33 -> 12623.319 | S33: =D33*($T$2/100+1)+J33 -> 13111.59 | U33: 14765.313 | V33: =U33-E33 -> 2424.1313 | W33: =U33-F33 -> 2147.6826 | X33: =U33-G33 -> 2285.6351
A34: ШО-3 | B34: 3541448015 | D34: ='расход ШО3'!F41/1.07 -> 3511.8574 | E34: 12087.791 | F34: 12370.452 | G34: 12170.556 | H34: =('Общая комиссия'!G34+'Общая комиссия'!J34+'Общая комиссия'!K34+'Общая комиссия'!L34+'Общая комиссия'!M34+'Общая комиссия'!N34+'Общая комиссия'!Q34)*1.22 -> 7527.6855 | I34: =('Общая комиссия'!H34+'Общая комиссия'!J34+'Общая комиссия'!K34+'Общая комиссия'!L34+'Общая комиссия'!M34+'Общая комиссия'!O34+'Общая комиссия'!Q34)*1.22 -> 7810.5394 | J34: =('Общая комиссия'!I34+'Общая комиссия'!J34+'Общая комиссия'!K34+'Общая комиссия'!L34+'Общая комиссия'!M34+'Общая комиссия'!P34+'Общая комиссия'!Q34)*1.22 -> 8221.3091 | K34: =E34-H34 -> 4560.1058 | L34: =F34-I34 -> 4559.913 | M34: =G34-J34 -> 3949.2465 | N34: =K34/D34-1 -> 0.29848831 | O34: =L34/D34-1 -> 0.29843339 | P34: =M34/D34-1 -> 0.12454638 | Q34: =D34*($T$2/100+1)+H34 -> 12093.1 | R34: =D34*($T$2/100+1)+I34 -> 12375.954 | S34: =D34*($T$2/100+1)+J34 -> 12786.724 | U34: 14303.289 | V34: =U34-E34 -> 2215.4975 | W34: =U34-F34 -> 1932.8364 | X34: =U34-G34 -> 2132.7331
A35: ШО-4 | B35: 3541452420 | D35: ='расход ШО4'!F41/1.07 -> 6486.9429 | E35: 22478.051 | F35: 23096.178 | G35: 23059.341 | H35: =('Общая комиссия'!G35+'Общая комиссия'!J35+'Общая комиссия'!K35+'Общая комиссия'!L35+'Общая комиссия'!M35+'Общая комиссия'!N35+'Общая комиссия'!Q35)*1.22 -> 14054.953 | I35: =('Общая комиссия'!H35+'Общая комиссия'!J35+'Общая комиссия'!K35+'Общая комиссия'!L35+'Общая комиссия'!M35+'Общая комиссия'!O35+'Общая комиссия'!Q35)*1.22 -> 14673.502 | J35: =('Общая комиссия'!I35+'Общая комиссия'!J35+'Общая комиссия'!K35+'Общая комиссия'!L35+'Общая комиссия'!M35+'Общая комиссия'!P35+'Общая комиссия'!Q35)*1.22 -> 15793.918 | K35: =E35-H35 -> 8423.0979 | L35: =F35-I35 -> 8422.6761 | M35: =G35-J35 -> 7265.4237 | N35: =K35/D35-1 -> 0.29846957 | O35: =L35/D35-1 -> 0.29840454 | P35: =M35/D35-1 -> 0.12000735 | Q35: =D35*($T$2/100+1)+H35 -> 22487.979 | R35: =D35*($T$2/100+1)+I35 -> 23106.528 | S35: =D35*($T$2/100+1)+J35 -> 24226.943 | U35: 27743.138 | V35: =U35-E35 -> 5265.0872 | W35: =U35-F35 -> 4646.9603 | X35: =U35-G35 -> 4683.7971
A36: Верстак 1200 0 0 | D36: ='ВС-О Опора'!F26+'ВС-ПС.1200.0 Полка-стенка'!F25+'ВС-С.1200х22'!F22+'ВС-О Опора'!F26 -> 5215.2221 | G36: 17189.904 | J36: =('Общая комиссия'!I36+'Общая комиссия'!J36+'Общая комиссия'!K36+'Общая комиссия'!L36+'Общая комиссия'!M36+'Общая комиссия'!P36+'Общая комиссия'!Q36)*1.22 -> 11292.999 | M36: =G36-J36 -> 5896.9047 | P36: =M36/D36-1 -> 0.13071016 | S36: =D36*($T$2/100+1)+J36 -> 18072.788
A37: Верстак 1400 0 0 | D37: ='ВС-С.1400х22'!F22+'ВС-ПС.1400.0 Полка-стенка'!F25+'ВС-О Опора'!F26+'ВС-О Опора'!F26 -> 5985.4852 | G37: 21159.397 | J37: =('Общая комиссия'!I37+'Общая комиссия'!J37+'Общая комиссия'!K37+'Общая комиссия'!L37+'Общая комиссия'!M37+'Общая комиссия'!P37+'Общая комиссия'!Q37)*1.22 -> 14465.026 | M37: =G37-J37 -> 6694.371 | P37: =M37/D37-1 -> 0.11843415 | S37: =D37*($T$2/100+1)+J37 -> 22246.157
A38: Стеллаж СТ-СПЭ 10.3 4 п | C38: 1035*360*100 | D38: ='10.3 100 кг'!X30 -> 2894.2678 | G38: 7939.4497 | J38: =('Общая комиссия'!I38+'Общая комиссия'!J38+'Общая комиссия'!K38+'Общая комиссия'!L38+'Общая комиссия'!M38+'Общая комиссия'!P38+'Общая комиссия'!Q38)*1.22 -> 4685.4867 | M38: =G38-J38 -> 3253.9629 | P38: =M38/D38-1 -> 0.12427845 | S38: =D38*($T$2/100+1)+J38 -> 8448.0349
A39: Стеллаж СТ-СПЭ 10.3 6 п | C39: 1035*360*140 | D39: ='10.3 100 кг'!X31 -> 3605.0872 | G39: 10045.249 | J39: =('Общая комиссия'!I39+'Общая комиссия'!J39+'Общая комиссия'!K39+'Общая комиссия'!L39+'Общая комиссия'!M39+'Общая комиссия'!P39+'Общая комиссия'!Q39)*1.22 -> 6013.2394 | M39: =G39-J39 -> 4032.0098 | P39: =M39/D39-1 -> 0.11842229 | S39: =D39*($T$2/100+1)+J39 -> 10699.853
A40: Стеллаж СТ-СПЭ 10.6 4 п | C40: 1035*660*100 | D40: ='10.6 100кг'!T31 -> 5000.8017 | G40: 13392.741 | J40: =('Общая комиссия'!I40+'Общая комиссия'!J40+'Общая комиссия'!K40+'Общая комиссия'!L40+'Общая комиссия'!M40+'Общая комиссия'!P40+'Общая комиссия'!Q40)*1.22 -> 7768.5718 | M40: =G40-J40 -> 5624.1688 | P40: =M40/D40-1 -> 0.12465343 | S40: =D40*($T$2/100+1)+J40 -> 14269.614
A41: Стеллаж СТ-СПЭ 10.6 6 п | C41: 1035*660*140 | D41: ='10.6 100кг'!T32 -> 6041.3396 | G41: 16486.314 | J41: =('Общая комиссия'!I41+'Общая комиссия'!J41+'Общая комиссия'!K41+'Общая комиссия'!L41+'Общая комиссия'!M41+'Общая комиссия'!P41+'Общая комиссия'!Q41)*1.22 -> 9714.8561 | M41: =G41-J41 -> 6771.458 | P41: =M41/D41-1 -> 0.12085373 | S41: =D41*($T$2/100+1)+J41 -> 17568.598

Sheet Лист1
B1: SKU | C1: Цена + НДС дальн
A2: Аптечка АМУ-1 | B2: 907247263 | C2: =Калькуляция!G2 -> 3150.6549
A3: Ключница К-148 | B3: 629880865 | C3: =Калькуляция!G3 -> 5021.8939
A4: Ключница К-20 | B4: 633898130 | C4: =Калькуляция!G4 -> 1473.6112
A5: Ключница К-40 | B5: 629825193 | C5: =Калькуляция!G5 -> 2970.6978
A6: Ключница К-60 | B6: 629844259 | C6: =Калькуляция!G6 -> 3346.6093
A7: Почтовый ящик ЯП-04 с замками | B7: 632063202 | C7: =Калькуляция!G7 -> 5571.1092
A8: Почтовый ящик ЯП-05 с замками | B8: 631939684 | C8: =Калькуляция!G8 -> 6357.0715
A9: Почтовый ящик ЯП-06 с замками | B9: 631949713 | C9: =Калькуляция!G9 -> 7108.2938
A10: Почтовый ящик ЯП-08 с замками | B10: 631946118 | C10: =Калькуляция!G10 -> 9720.9657
A11: Сейф мебельный СМ-20 | B11: 1667684227 | C11: =Калькуляция!G11 -> 5228.0186
A12: Сейф мебельный СМ-20Э | B12: 1667684137 | C12: =Калькуляция!G12 -> 6070.7009
A13: Сейф мебельный СМ-23 | B13: 1672231528 | C13: =Калькуляция!G13 -> 7876.5144
... A35: ШО-4 | B35: 3541452420 | C35: =Калькуляция!G35 -> 23059.341
A36: Верстак 1200 0 0
A37: Верстак 1400 0 0

Sheet Общая комиссия
A1: Товар | B1: Цена на мп БЛИЖ | C1: Цена на мп СРЕД | D1: Цена на мп ДАЛЬН | E1: Объем Л | F1: Вознаграждение МП процент | G1: Вознаграждение МП руб БЛИЖ | H1: Вознаграждение МП руб СРЕД | I1: Вознаграждение МП руб ДАЛЬН | J1: Тариф отгрузки 1,9 руб/л | K1: Отгрузка в СЦ | L1: Доставка в ПВЗ | M1: Обработка возврата | N1: логистика + обратная ближ | O1: логистика + обратная сред | P1: логистика + обратная дальн | Q1: Эквайринг 1,5%
A2: АМУ-1 | B2: =Калькуляция!E2 -> 2620.3758 | C2: =Калькуляция!F2 -> 2859.3716 | D2: =Калькуляция!G2 -> 3150.6549 | E2: 23 | F2: 0.44 | G2: =B2*F2 -> 1152.9653 | H2: =C2*F2 -> 1258.1235 | I2: =D2*F2 -> 1386.2882 | J2: =1.9*E2 -> 43.7 | K2: 20 | L2: 25 | M2: 15 | N2: ='Тарифы логистика 20-25л'!D11*1.15 -> 295.55 | O2: ='Тарифы логистика 20-25л'!D21*1.15 -> 386.4 | P2: ='Тарифы логистика 20-25л'!D30*1.15 -> 630.2 | Q2: =B2*0.01 -> 26.203758
A3: К148 | B3: =Калькуляция!E3 -> 5069.8174 | C3: =Калькуляция!F3 -> 5175.958 | D3: =Калькуляция!G3 -> 5021.8939 | E3: 13 | F3: 0.43 | G3: =B3*F3 -> 2180.0215 | H3: =C3*F3 -> 2225.662 | I3: =D3*F3 -> 2159.4144 | J3: =1.9*E3 -> 24.7 | K3: 20 | L3: 25 | M3: 15 | N3: ='Тарифы логистика 13-14л '!D12*1.15 -> 211.6 | O3: ='Тарифы логистика 13-14л '!D21*1.15 -> 253 | P3: ='Тарифы логистика 13-14л '!D30*1.15 -> 410.55 | Q3: =B3*0.01 -> 50.698174
A4: К20 | B4: =Калькуляция!E4 -> 1330.7173 | C4: =Калькуляция!F4 -> 1422.1162 | D4: =Калькуляция!G4 -> 1473.6112 | E4: 3 | F4: 0.43 | G4: =B4*F4 -> 572.20844 | H4: =C4*F4 -> 611.50996 | I4: =D4*F4 -> 633.65283 | J4: =1.9*E4 -> 5.7 | K4: 20 | L4: 25 | M4: 15 | N4: ='Тарифы логистика 3-4л'!D13*1.15 -> 117.3 | O4: ='Тарифы логистика 3-4л'!D22*1.15 -> 152.95 | P4: ='Тарифы логистика 3-4л'!D31*1.15 -> 236.9 | Q4: =B4*0.01 -> 13.307173
A5: К40 | B5: =Калькуляция!E5 -> 2790.7106 | C5: =Калькуляция!F5 -> 2896.8512 | D5: =Калькуляция!G5 -> 2970.6978 | E5: 13 | F5: 0.43 | G5: =B5*F5 -> 1200.0056 | H5: =C5*F5 -> 1245.646 | I5: =D5*F5 -> 1277.4001 | J5: =1.9*E5 -> 24.7 | K5: 20 | L5: 25 | M5: 15 | N5: 211.6 | O5: 253 | P5: 410.55 | Q5: =B5*0.01 -> 27.907106
A6: К60 | B6: =Калькуляция!E6 -> 3196.5966 | C6: =Калькуляция!F6 -> 3287.9955 | D6: =Калькуляция!G6 -> 3346.6093 | E6: 14 | F6: 0.43 | G6: =B6*F6 -> 1374.5366 | H6: =C6*F6 -> 1413.8381 | I6: =D6*F6 -> 1439.042 | J6: =1.9*E6 -> 26.6 | K6: 20 | L6: 25 | M6: 15 | N6: ='Тарифы логистика 14-15л'!D12*1.15 -> 221.95 | O6: ='Тарифы логистика 14-15л'!D21*1.15 -> 257.6 | P6: ='Тарифы логистика 14-15л'!D30*1.15 -> 425.5 | Q6: =B6*0.01 -> 31.965966
A7: Почтовый ящик ЯП-4 | B7: =Калькуляция!E7 -> 4755.0731 | C7: =Калькуляция!F7 -> 5037.7341 | D7: =Калькуляция!G7 -> 5571.1092 | E7: 38 | F7: 0.45 | G7: =B7*F7 -> 2139.7829 | H7: =C7*F7 -> 2266.9803 | I7: =D7*F7 -> 2506.9992 | J7: =1.9*E7 -> 72.2 | K7: 20 | L7: 25 | M7: 15 | N7: 479.55 | O7: 584.2 | P7: 1010.85 | Q7: =B7*0.01 -> 47.550731
A8: Почтовый ящик ЯП-5 | B8: =Калькуляция!E8 -> 5538.2857 | C8: =Калькуляция!F8 -> 5814.7344 | D8: =Калькуляция!G8 -> 6357.0715 | E8: 45 | F8: 0.45 | G8: =B8*F8 -> 2492.2285 | H8: =C8*F8 -> 2616.6305 | I8: =D8*F8 -> 2860.6822 | J8: =1.9*E8 -> 85.5 | K8: 20 | L8: 25 | M8: 15 | N8: ='Тарифы логистика 40-45л'!D12*1.15 -> 549.7 | O8: ='Тарифы логистика 40-45л'!D21*1.15 -> 652.05 | P8: ='Тарифы логистика 40-45л'!D30*1.15 -> 1114.35 | Q8: =B8*0.01 -> 55.382857
A9: Почтовый ящик ЯП-6 | B9: =Калькуляция!E9 -> 6006.4496 | C9: =Калькуляция!F9 -> 6369.871 | D9: =Калькуляция!G9 -> 7108.2938 | E9: 50 | F9: 0.45 | G9: =B9*F9 -> 2702.9023 | H9: =C9*F9 -> 2866.4419 | I9: =D9*F9 -> 3198.7322 | J9: =1.9*E9 -> 95 | K9: 20 | L9: 25 | M9: 15 | N9: ='Тарифы логистика 50-60л'!D12*1.15 -> 654.35 | O9: ='Тарифы логистика 50-60л'!D21*1.15 -> 788.9 | P9: ='Тарифы логистика 50-60л'!D30*1.15 -> 1354.7 | Q9: =B9*0.01 -> 60.064496
A10: Почтовый ящик ЯП-8 | B10: =Калькуляция!E10 -> 7836.3059 | C10: =Калькуляция!F10 -> 8561.5279 | D10: =Калькуляция!G10 -> 9720.9657 | E10: 72 | F10: 0.45 | G10: =B10*F10 -> 3526.3376 | H10: =C10*F10 -> 3852.6876 | I10: =D10*F10 -> 4374.4345 | J10: =1.9*E10 -> 136.8 | K10: 20 | L10: 25 | M10: 15 | N10: ='Тарифы логистика 70-80л'!D12 -> 732 | O10: ='Тарифы логистика 70-80л'!D21*1.15 -> 1000.5 | P10: ='Тарифы логистика 70-80л'!D30*1.15 -> 1829.65 | Q10: =B10*0.01 -> 78.363059
A11: СМ 20 | B11: =Калькуляция!E11 -> 5324.119 | C11: =Калькуляция!F11 -> 5409.0258 | D11: =Калькуляция!G11 -> 5228.0186 | E11: 14 | F11: 0.4 | G11: =B11*F11 -> 2129.6476 | H11: =C11*F11 -> 2163.6103 | I11: =D11*F11 -> 2091.2074 | J11: =1.9*E11 -> 26.6 | K11: 20 | L11: 25 | M11: 15 | N11: 221.95 | O11: 257.6 | P11: 425.5 | Q11: =B11*0.01 -> 53.24119
A12: СМ 20-Э | B12: =Калькуляция!E12 -> 6260.4327 | C12: =Калькуляция!F12 -> 6345.3395 | D12: =Калькуляция!G12 -> 6070.7009 | E12: 14 | F12: 0.4 | G12: =B12*F12 -> 2504.1731 | H12: =C12*F12 -> 2538.1358 | I12: =D12*F12 -> 2428.2804 | J12: =1.9*E12 -> 26.6 | K12: 20 | L12: 25 | M12: 15 | N12: 221.95 | O12: 257.6 | P12: 425.5 | Q12: =B12*0.01 -> 62.604327
A13: СМ 23 | B13: =Калькуляция!E13 -> 7486.2973 | C13: =Калькуляция!F13 -> 7735.5399 | D13: =Калькуляция!G13 -> 7876.5144 | E13: 35 | F13: 0.4 | G13: =B13*F13 -> 2994.5189 | H13: =C13*F13 -> 3094.216 | I13: =D13*F13 -> 3150.6058 | J13: =1.9*E13 -> 66.5 | K13: 20 | L13: 25 | M13: 15 | N13: ='Тарифы логистика 35-40л'!D12*1.15 -> 479.55 | O13: ='Тарифы логистика 35-40л'!D21*1.15 -> 584.2 | P13: ='Тарифы логистика 35-40л'!D30*1.15 -> 1010.85 | Q13: =B13*0.01 -> 74.862973
A14: СМ 23-Э | B14: =Калькуляция!E14 -> 8274.1354 | C14: =Калькуляция!F14 -> 8460.3826 | D14: =Калькуляция!G14 -> 8400.691 | E14: 34 | F14: 0.4 | G14: =B14*F14 -> 3309.6542 | H14: =C14*F14 -> 3384.1531 | I14: =D14*F14 -> 3360.2764 | J14: =1.9*E14 -> 64.6 | K14: 20 | L14: 25 | M14: 15 | N14: ='Тарифы логистика 30-35л'!D12*1.15 -> 428.95 | O14: ='Тарифы логистика 30-35л'!D21*1.15 -> 507.15 | P14: ='Тарифы логистика 30-35л'!D30*1.15 -> 874 | Q14: =B14*0.01 -> 82.741354
A15: СМ 25 | B15: =Калькуляция!E15 -> 6103.6318 | C15: =Калькуляция!F15 -> 6320.0072 | D15: =Калькуляция!G15 -> 6210.5943 | E15: 24 | F15: 0.4 | G15: =B15*F15 -> 2441.4527 | H15: =C15*F15 -> 2528.0029 | I15: =D15*F15 -> 2484.2377 | J15: =1.9*E15 -> 45.6 | K15: 20 | L15: 25 | M15: 15 | N15: 295.55 | O15: 386.4 | P15: 630.2 | Q15: =B15*0.01 -> 61.036318
A16: СМ 25-Э | B16: =Калькуляция!E16 -> 7112.7525 | C16: =Калькуляция!F16 -> 7329.1279 | D16: =Калькуляция!G16 -> 7118.8029 | E16: 24 | F16: 0.4 | G16: =B16*F16 -> 2845.101 | H16: =C16*F16 -> 2931.6512 | I16: =D16*F16 -> 2847.5212 | J16: =1.9*E16 -> 45.6 | K16: 20 | L16: 25 | M16: 15 | N16: 295.55 | O16: 386.4 | P16: 630.2 | Q16: =B16*0.01 -> 71.127525
A17: СМ 30 | B17: =Калькуляция!E17 -> 7465.4968 | C17: =Калькуляция!F17 -> 7714.7394 | D17: =Калькуляция!G17 -> 7857.7939 | E17: 37 | F17: 0.4 | G17: =B17*F17 -> 2986.1987 | H17: =C17*F17 -> 3085.8957 | I17: =D17*F17 -> 3143.1176 | J17: =1.9*E17 -> 70.3 | K17: 20 | L17: 25 | M17: 15 | N17: ='Тарифы логистика 35-40л'!D12*1.15 -> 479.55 | O17: ='Тарифы логистика 35-40л'!D21*1.15 -> 584.2 | P17: ='Тарифы логистика 35-40л'!D30*1.15 -> 1010.85 | Q17: =B17*0.01 -> 74.654968
A18: СМ 30-Э | B18: =Калькуляция!E18 -> 8767.4741 | C18: =Калькуляция!F18 -> 9016.7167 | D18: =Калькуляция!G18 -> 9029.5735 | E18: 37 | F18: 0.4 | G18: =B18*F18 -> 3506.9896 | H18: =C18*F18 -> 3606.6867 | I18: =D18*F18 -> 3611.8294 | J18: =1.9*E18 -> 70.3 | K18: 20 | L18: 25 | M18: 15 | N18: 479.55 | O18: 584.2 | P18: 1010.85 | Q18: =B18*0.01 -> 87.674741
A19: СМ 50 | B19: =Калькуляция!E19 -> 9500.6294 | C19: =Калькуляция!F19 -> 9821.0842 | D19: =Калькуляция!G19 -> 10051.774 | E19: 59 | F19: 0.4 | G19: =B19*F19 -> 3800.2518 | H19: =C19*F19 -> 3928.4337 | I19: =D19*F19 -> 4020.7095 | J19: =1.9*E19 -> 112.1 | K19: 20 | L19: 25 | M19: 15 | N19: 654.35 | O19: 788.9 | P19: 1354.7 | Q19: =B19*0.01 -> 95.006294
A20: СМ 50-Э | B20: =Калькуляция!E20 -> 10543.567 | C20: =Калькуляция!F20 -> 10864.022 | D20: =Калькуляция!G20 -> 10990.418 | E20: 59 | F20: 0.4 | G20: =B20*F20 -> 4217.427 | H20: =C20*F20 -> 4345.6089 | I20: =D20*F20 -> 4396.1672 | J20: =1.9*E20 -> 112.1 | K20: 20 | L20: 25 | M20: 15 | N20: 654.35 | O20: 788.9 | P20: 1354.7 | Q20: =B20*0.01 -> 105.43567
A21: Стеллаж металлический200*100*40 4п | B21: =Калькуляция!E21 -> 7814.1939 | C21: =Калькуляция!F21 -> 8027.5475 | D21: =Калькуляция!G21 -> 8092.1113 | E21: 44 | F21: 0.34 | G21: =B21*F21 -> 2656.8259 | H21: =C21*F21 -> 2729.3662 | I21: =D21*F21 -> 2751.3178 | J21: =1.9*E21 -> 83.6 | K21: 20 | L21: 25 | M21: 15 | N21: 549.7 | O21: 652.05 | P21: 1114.35 | Q21: =B21*0.01 -> 78.141939
A22: Стеллаж металлический200*100*50 4п | B22: =Калькуляция!E23 -> 9768.511 | C22: =Калькуляция!F22 -> 8996.8845 | D22: =Калькуляция!G22 -> 9158.6903 | E22: 55 | F22: 0.34 | G22: =B22*F22 -> 3321.2937 | H22: =C22*F22 -> 3058.9407 | I22: =D22*F22 -> 3113.9547 | J22: =1.9*E22 -> 104.5 | K22: 20 | L22: 25 | M22: 15 | N22: 654.35 | O22: 788.9 | P22: 1354.7 | Q22: =B22*0.01 -> 97.68511
A23: Стеллаж металлический200*100*40 6п | B23: =Калькуляция!E22 -> 9152.8146 | C23: =Калькуляция!F23 -> 10533.338 | D23: =Калькуляция!G23 -> 10813.345 | E23: 65 | F23: 0.34 | G23: =B23*F23 -> 3111.957 | H23: =C23*F23 -> 3581.3349 | I23: =D23*F23 -> 3676.5371 | J23: =1.9*E23 -> 123.5 | K23: 20 | L23: 25 | M23: 15 | N23: 756.7 | O23: 914.25 | P23: 1624.95 | Q23: =B23*0.01 -> 91.528146
A24: ШБС 01-МИНИ | B24: =Калькуляция!E24 -> 9149.4402 | C24: =Калькуляция!F24 -> 9524.6735 | D24: =Калькуляция!G24 -> 10095.599 | E24: 64 | F24: 0.4 | G24: =B24*F24 -> 3659.7761 | H24: =C24*F24 -> 3809.8694 | I24: =D24*F24 -> 4038.2395 | J24: =1.9*E24 -> 121.6 | K24: 20 | L24: 25 | M24: 15 | N24: ='Тарифы логистика 60-70л'!D12*1.15 -> 756.7 | O24: ='Тарифы логистика 60-70л'!D21*1.15 -> 914.25 | P24: ='Тарифы логистика 60-70л'!D30*1.15 -> 1624.95 | Q24: =B24*0.01 -> 91.494402
A25: ШБС 01-МИНИ-Т | B25: =Калькуляция!E25 -> 9608.4492 | C25: =Калькуляция!F25 -> 9983.6826 | D25: =Калькуляция!G25 -> 10508.707 | E25: 62 | F25: 0.4 | G25: =B25*F25 -> 3843.3797 | H25: =C25*F25 -> 3993.473 | I25: =D25*F25 -> 4203.4827 | J25: =1.9*E25 -> 117.8 | K25: 20 | L25: 25 | M25: 15 | N25: 756.7 | O25: 914.25 | P25: 1624.95 | Q25: =B25*0.01 -> 96.084492
A26: Шкаф бухгалтерский ШБС-01-17 | B26: =Калькуляция!E26 -> 31197.987 | C26: =Калькуляция!F26 -> 34076.602 | D26: =Калькуляция!G26 -> 36915.344 | E26: 348 | F26: 0.4 | G26: =B26*F26 -> 12479.195 | H26: =C26*F26 -> 13630.641 | I26: =D26*F26 -> 14766.138 | J26: =1.9*E26 -> 661.2 | K26: 20 | L26: 25 | M26: 15 | N26: ='Тарифы логистика 200-400л'!D7*1.15 -> 2370.15 | O26: ='Тарифы логистика 200-400л'!D21*1.15 -> 3578.8 | P26: ='Тарифы логистика 200-400л'!D30*1.15 -> 6492.9 | Q26: =B26*0.01 -> 311.97987
A27: Шкаф бухгалтерский ШБС-02-17 | B27: =Калькуляция!E27 -> 33611.28 | C27: =Калькуляция!F27 -> 36489.895 | D27: =Калькуляция!G27 -> 39087.308 | E27: 348 | F27: 0.4 | G27: =B27*F27 -> 13444.512 | H27: =C27*F27 -> 14595.958 | I27: =D27*F27 -> 15634.923 | J27: =1.9*E27 -> 661.2 | K27: 20 | L27: 25 | M27: 15 | N27: 2370.15 | O27: 3578.8 | P27: 6492.9 | Q27: =B27*0.01 -> 336.1128
A28: Стеллаж металлический СТ-СПЭ 4(4) | B28: =Калькуляция!E28 -> 7080.6951 | C28: =Калькуляция!F28 -> 7324.4598 | D28: =Калькуляция!G28 -> 7582.9585 | E28: 44 | F28: 0.4 | G28: =B28*F28 -> 2832.278 | H28: =C28*F28 -> 2929.7839 | I28: =D28*F28 -> 3033.1834 | J28: =1.9*E28 -> 83.6 | K28: 20 | L28: 25 | M28: 15 | N28: 549.7 | O28: 652.05 | P28: 1114.35 | Q28: =B28*0.01 -> 70.806951
A29: Стеллаж металлический СТ-СПЭ 5(4) | B29: =Калькуляция!E30 -> 8920.6157 | C29: =Калькуляция!F29 -> 8275.9949 | D29: =Калькуляция!G29 -> 8661.1933 | E29: 55 | F29: 0.4 | G29: =B29*F29 -> 3568.2463 | H29: =C29*F29 -> 3310.398 | I29: =D29*F29 -> 3464.4773 | J29: =1.9*E29 -> 104.5 | K29: 20 | L29: 25 | M29: 15 | N29: 654.35 | O29: 788.9 | P29: 1354.7 | Q29: =B29*0.01 -> 89.206157
A30: Стеллаж металлический СТ-СПЭ 4(6) | B30: =Калькуляция!E29 -> 8426.4492 | C30: =Калькуляция!F30 -> 9766.7582 | D30: =Калькуляция!G30 -> 10313.475 | E30: 65 | F30: 0.4 | G30: =B30*F30 -> 3370.5797 | H30: =C30*F30 -> 3906.7033 | I30: =D30*F30 -> 4125.39 | J30: =1.9*E30 -> 123.5 | K30: 20 | L30: 25 | M30: 15 | N30: 756.7 | O30: 914.25 | P30: 1624.95 | Q30: =B30*0.01 -> 84.264492
A31: ШО-5 | B31: =Калькуляция!E31 -> 42907.582 | C31: =Калькуляция!F31 -> 46172.161 | D31: =Калькуляция!G31 -> 48638.865 | E31: 348 | F31: 0.45 | G31: =B31*F31 -> 19308.412 | H31: =C31*F31 -> 20777.473 | I31: =D31*F31 -> 21887.489 | J31: =1.9*E31 -> 661.2 | K31: 20 | L31: 25 | M31: 15 | N31: 2370.15 | O31: 3578.8 | P31: 6492.9 | Q31: =B31*0.01 -> 429.07582
A32: ШО-1 | B32: =Калькуляция!E32 -> 18800.428 | C32: =Калькуляция!F32 -> 19225.973 | D32: =Калькуляция!G32 -> 19031.025 | E32: 65 | F32: 0.45 | G32: =B32*F32 -> 8460.1928 | H32: =C32*F32 -> 8651.6879 | I32: =D32*F32 -> 8563.9612 | J32: =1.9*E32 -> 123.5 | K32: 20 | L32: 25 | M32: 15 | N32: 756.7 | O32: 914.25 | P32: 1624.95 | Q32: =B32*0.01 -> 188.00428
A33: ШО-2 | B33: =Калькуляция!E33 -> 12341.182 | C33: =Калькуляция!F33 -> 12617.631 | D33: =Калькуляция!G33 -> 12479.678 | E33: 42 | F33: 0.45 | G33: =B33*F33 -> 5553.5318 | H33: =C33*F33 -> 5677.9337 | I33: =D33*F33 -> 5615.8551 | J33: =1.9*E33 -> 79.8 | K33: 20 | L33: 25 | M33: 15 | N33: ='Тарифы логистика 40-45л'!D12*1.15 -> 549.7 | O33: ='Тарифы логистика 40-45л'!D21*1.15 -> 652.05 | P33: ='Тарифы логистика 40-45л'!D30*1.15 -> 1114.35 | Q33: =B33*0.01 -> 123.41182
A34: ШО-3 | B34: =Калькуляция!E34 -> 12087.791 | C34: =Калькуляция!F34 -> 12370.452 | D34: =Калькуляция!G34 -> 12170.556 | E34: 37 | F34: 0.45 | G34: =B34*F34 -> 5439.5061 | H34: =C34*F34 -> 5566.7036 | I34: =D34*F34 -> 5476.75 | J34: =1.9*E34 -> 70.3 | K34: 20 | L34: 25 | M34: 15 | N34: 479.55 | O34: 584.2 | P34: 1010.85 | Q34: =B34*0.01 -> 120.87791
A35: ШО-4 | B35: =Калькуляция!E35 -> 22478.051 | C35: =Калькуляция!F35 -> 23096.178 | D35: =Калькуляция!G35 -> 23059.341 | E35: 88 | F35: 0.45 | G35: =B35*F35 -> 10115.123 | H35: =C35*F35 -> 10393.28 | I35: =D35*F35 -> 10376.704 | J35: =1.9*E35 -> 167.2 | K35: 20 | L35: 25 | M35: 15 | N35: ='Тарифы логистика 80-90л'!D12*1.15 -> 953.35 | O35: ='Тарифы логистика 80-90л'!D21*1.15 -> 1182.2 | P35: ='Тарифы логистика 80-90л'!D30*1.15 -> 2117.15 | Q35: =B35*0.01 -> 224.78051
A36: Верстак 1200 0 0 | B36: =Калькуляция!E36 -> 0 | C36: =Калькуляция!F36 -> 0 | D36: =Калькуляция!G36 -> 17189.904 | E36: 56 | F36: 0.45 | G36: =B36*F36 -> 0 | H36: =C36*F36 -> 0 | I36: =D36*F36 -> 7735.4568 | J36: =1.9*E36 -> 106.4 | K36: 20 | L36: 25 | M36: 15 | N36: ='Тарифы логистика 80-90л'!D13*1.15 -> 1100.55 | O36: ='Тарифы логистика 80-90л'!D22*1.15 -> 1406.45 | P36: ='Тарифы логистика 50-60л'!D30*1.15 -> 1354.7 | Q36: =B36*0.01 -> 0
A37: Верстак 1400 0 0 | B37: =Калькуляция!E37 -> 0 | C37: =Калькуляция!F37 -> 0 | D37: =Калькуляция!G37 -> 21159.397 | E37: 83 | F37: 0.45 | G37: =B37*F37 -> 0 | H37: =C37*F37 -> 0 | I37: =D37*F37 -> 9521.7286 | J37: =1.9*E37 -> 157.7 | K37: 20 | L37: 25 | M37: 15 | N37: ='Тарифы логистика 80-90л'!D14*1.15 -> 1110.9 | O37: ='Тарифы логистика 80-90л'!D23*1.15 -> 1455.9 | P37: ='Тарифы логистика 80-90л'!D30*1.15 -> 2117.15 | Q37: =B37*0.01 -> 0
A38: Стеллаж СТ-СПЭ 10.3 4 п | D38: =Калькуляция!G38 -> 7939.4497 | E38: 37 | F38: 0.34 | I38: =D38*F38 -> 2699.4129 | J38: =1.9*E38 -> 70.3 | K38: 20 | L38: 25 | M38: 15 | P38: ='Тарифы логистика 35-40л'!D30*1.15 -> 1010.85 | Q38: =B38*0.01 -> 0
A39: Стеллаж СТ-СПЭ 10.3 6 п | D39: =Калькуляция!G39 -> 10045.249 | E39: 52 | F39: 0.34 | I39: =D39*F39 -> 3415.3847 | J39: =1.9*E39 -> 98.8 | K39: 20 | L39: 25 | M39: 15 | P39: ='Тарифы логистика 50-60л'!D30*1.15 -> 1354.7 | Q39: =B39*0.01 -> 0
A40: Стеллаж СТ-СПЭ 10.6 4 п | D40: =Калькуляция!G40 -> 13392.741 | E40: 68 | F40: 0.34 | I40: =D40*F40 -> 4553.5318 | J40: =1.9*E40 -> 129.2 | K40: 20 | L40: 25 | M40: 15 | P40: ='Тарифы логистика 60-70л'!D30*1.15 -> 1624.95 | Q40: =B40*0.01 -> 0
A41: Стеллаж СТ-СПЭ 10.6 6 п | D41: =Калькуляция!G41 -> 16486.314 | E41: 95 | F41: 0.34 | I41: =D41*F41 -> 5605.3468 | J41: =1.9*E41 -> 180.5 | K41: 20 | L41: 25 | M41: 15 | P41: ='Тарифы логистика 80-90л'!D30*1.15 -> 2117.15 | Q41: =B41*0.01 -> 0

Sheet Общая комиссия (2)
A1: Товар | B1: Цена на мп | C1: Объем Л | D1: Вознаграждение МП процент | E1: Вознаграждение МП руб | F1: Тариф отгрузки 1,9 руб/л | G1: Отгрузка в СЦ | H1: Доставка в ПВЗ | I1: Обработка возврата | J1: логистика + обратная ближ | K1: логистика + обратная сред | L1: логистика + обратная дальн | M1: Общая Комиссия Дальние Регионы | N1: Общая Комиссия Ближние Регионы | O1: Эквайринг 1,5%
A2: К20 | B2: =Калькуляция!E4 -> 1330.7173 | C2: 3 | D2: 0.43 | E2: =B2*D2 -> 572.20844 | F2: =1.9*C2 -> 5.7 | G2: 20 | H2: 25 | I2: 15 | J2: ='Тарифы логистика 3-4л'!D13*1.15 -> 117.3 | K2: ='Тарифы логистика 3-4л'!D22*1.15 -> 152.95 | L2: ='Тарифы логистика 3-4л'!D31*1.15 -> 236.9 | M2: =#REF!+E2+F2+G2+H2+I2+J2+O2 -> #REF! | N2: =#REF!+E2+F2+G2+H2+I2+J2+O2 -> #REF! | O2: =B2*0.01 -> 13.307173
A3: К148 | B3: =Калькуляция!E3 -> 5069.8174 | C3: 13 | D3: 0.43 | E3: =B3*D3 -> 2180.0215 | F3: =1.9*C3 -> 24.7 | G3: 20 | H3: 25 | I3: 15 | J3: ='Тарифы логистика 13-14л '!D12*1.15 -> 211.6 | K3: ='Тарифы логистика 13-14л '!D21*1.15 -> 253 | L3: ='Тарифы логистика 13-14л '!D30*1.15 -> 410.55 | M3: =#REF!+E3+F3+G3+H3+I3+J3+O3 -> #REF! | N3: =#REF!+E3+F3+G3+H3+I3+J3+O3 -> #REF! | O3: =B3*0.01 -> 50.698174
A4: К40 | B4: =Калькуляция!E5 -> 2790.7106 | C4: 13 | D4: 0.43 | E4: =B4*D4 -> 1200.0056 | F4: =1.9*C4 -> 24.7 | G4: 20 | H4: 25 | I4: 15 | J4: 211.6 | K4: 253 | L4: 410.55 | M4: =#REF!+E4+F4+G4+H4+I4+J4+O4 -> #REF! | N4: =#REF!+E4+F4+G4+H4+I4+J4+O4 -> #REF! | O4: =B4*0.01 -> 27.907106
A5: К60 | B5: =Калькуляция!E6 -> 3196.5966 | C5: 14 | D5: 0.43 | E5: =B5*D5 -> 1374.5366 | F5: =1.9*C5 -> 26.6 | G5: 20 | H5: 25 | I5: 15 | J5: ='Тарифы логистика 14-15л'!D12*1.15 -> 221.95 | K5: ='Тарифы логистика 14-15л'!D21*1.15 -> 257.6 | L5: ='Тарифы логистика 14-15л'!D30*1.15 -> 425.5 | M5: =#REF!+E5+F5+G5+H5+I5+J5+O5 -> #REF! | N5: =#REF!+E5+F5+G5+H5+I5+J5+O5 -> #REF! | O5: =B5*0.01 -> 31.965966
A6: СМ 20 | B6: =Калькуляция!E11 -> 5324.119 | C6: 14 | D6: 0.4 | E6: =B6*D6 -> 2129.6476 | F6: =1.9*C6 -> 26.6 | G6: 20 | H6: 25 | I6: 15 | J6: 221.95 | K6: 257.6 | L6: 425.5 | M6: =#REF!+E6+F6+G6+H6+I6+J6+O6 -> #REF! | N6: =#REF!+E6+F6+G6+H6+I6+J6+O6 -> #REF! | O6: =B6*0.01 -> 53.24119
A7: СМ 20-Э | B7: =Калькуляция!E12 -> 6260.4327 | C7: 14 | D7: 0.4 | E7: =B7*D7 -> 2504.1731 | F7: =1.9*C7 -> 26.6 | G7: 20 | H7: 25 | I7: 15 | J7: 221.95 | K7: 257.6 | L7: 425.5 | M7: =#REF!+E7+F7+G7+H7+I7+J7+O7 -> #REF! | N7: =#REF!+E7+F7+G7+H7+I7+J7+O7 -> #REF! | O7: =B7*0.01 -> 62.604327
A8: АМУ-1 | B8: =Калькуляция!E2 -> 2620.3758 | C8: 23 | D8: 0.44 | E8: =B8*D8 -> 1152.9653 | F8: =1.9*C8 -> 43.7 | G8: 20 | H8: 25 | I8: 15 | J8: ='Тарифы логистика 20-25л'!D11*1.15 -> 295.55 | K8: ='Тарифы логистика 20-25л'!D21*1.15 -> 386.4 | L8: ='Тарифы логистика 20-25л'!D30*1.15 -> 630.2 | M8: =#REF!+E8+F8+G8+H8+I8+J8+O8 -> #REF! | N8: =#REF!+E8+F8+G8+H8+I8+J8+O8 -> #REF! | O8: =B8*0.01 -> 26.203758
A9: СМ 25 | B9: =Калькуляция!E15 -> 6103.6318 | C9: 24 | D9: 0.4 | E9: =B9*D9 -> 2441.4527 | F9: =1.9*C9 -> 45.6 | G9: 20 | H9: 25 | I9: 15 | J9: 295.55 | K9: 386.4 | L9: 630.2 | M9: =#REF!+E9+F9+G9+H9+I9+J9+O9 -> #REF! | N9: =#REF!+E9+F9+G9+H9+I9+J9+O9 -> #REF! | O9: =B9*0.01 -> 61.036318
A10: СМ 25-Э | B10: =Калькуляция!E16 -> 7112.7525 | C10: 24 | D10: 0.4 | E10: =B10*D10 -> 2845.101 | F10: =1.9*C10 -> 45.6 | G10: 20 | H10: 25 | I10: 15 | J10: 295.55 | K10: 386.4 | L10: 630.2 | M10: =#REF!+E10+F10+G10+H10+I10+J10+O10 -> #REF! | N10: =#REF!+E10+F10+G10+H10+I10+J10+O10 -> #REF! | O10: =B10*0.01 -> 71.127525
A11: СМ 23-Э | B11: =Калькуляция!E14 -> 8274.1354 | C11: 34 | D11: 0.4 | E11: =B11*D11 -> 3309.6542 | F11: =1.9*C11 -> 64.6 | G11: 20 | H11: 25 | I11: 15 | M11: =#REF!+E11+F11+G11+H11+I11+J11+O11 -> #REF! | N11: =#REF!+E11+F11+G11+H11+I11+J11+O11 -> #REF! | O11: =B11*0.01 -> 82.741354
A12: СМ 23 | B12: =Калькуляция!E13 -> 7486.2973 | C12: 35 | D12: 0.4 | E12: =B12*D12 -> 2994.5189 | F12: =1.9*C12 -> 66.5 | G12: 20 | H12: 25 | I12: 15 | M12: =#REF!+E12+F12+G12+H12+I12+J12+O12 -> #REF! | N12: =#REF!+E12+F12+G12+H12+I12+J12+O12 -> #REF! | O12: =B12*0.01 -> 74.862973
A13: СМ 30 | B13: =Калькуляция!E17 -> 7465.4968 | C13: 37 | D13: 0.4 | E13: =B13*D13 -> 2986.1987 | F13: =1.9*C13 -> 70.3 | G13: 20 | H13: 25 | I13: 15 | M13: =#REF!+E13+F13+G13+H13+I13+J13+O13 -> #REF! | N13: =#REF!+E13+F13+G13+H13+I13+J13+O13 -> #REF! | O13: =B13*0.01 -> 74.654968
A14: СМ 30-Э | B14: =Калькуляция!E18 -> 8767.4741 | C14: 37 | D14: 0.4 | E14: =B14*D14 -> 3506.9896 | F14: =1.9*C14 -> 70.3 | G14: 20 | H14: 25 | I14: 15 | M14: =#REF!+E14+F14+G14+H14+I14+J14+O14 -> #REF! | N14: =#REF!+E14+F14+G14+H14+I14+J14+O14 -> #REF! | O14: =B14*0.01 -> 87.674741
A15: ШО-3 | B15: =Калькуляция!E34 -> 12087.791 | C15: 37 | D15: 0.45 | E15: =B15*D15 -> 5439.5061 | F15: =1.9*C15 -> 70.3 | G15: 20 | H15: 25 | I15: 15 | O15: =B15*0.01 -> 120.87791
A16: Почтовый ящик ЯП-4 | B16: =Калькуляция!E7 -> 4755.0731 | C16: 38 | D16: 0.45 | E16: =B16*D16 -> 2139.7829 | F16: =1.9*C16 -> 72.2 | G16: 20 | H16: 25 | I16: 15 | M16: =#REF!+E16+F16+G16+H16+I16+J16+O16 -> #REF! | N16: =#REF!+E16+F16+G16+H16+I16+J16+O16 -> #REF! | O16: =B16*0.01 -> 47.550731
A17: ШО-2 | B17: =Калькуляция!E33 -> 12341.182 | C17: 42 | D17: 0.45 | E17: =B17*D17 -> 5553.5318 | F17: =1.9*C17 -> 79.8 | G17: 20 | H17: 25 | I17: 15 | O17: =B17*0.01 -> 123.41182
A18: Стеллаж металлический200*100*40 4п | B18: =Калькуляция!E21 -> 7814.1939 | C18: 44 | D18: 0.34 | E18: =B18*D18 -> 2656.8259 | F18: =1.9*C18 -> 83.6 | G18: 20 | H18: 25 | I18: 15 | M18: =#REF!+E18+F18+G18+H18+I18+J18+O18 -> #REF! | N18: =#REF!+E18+F18+G18+H18+I18+J18+O18 -> #REF! | O18: =B18*0.01 -> 78.141939
A19: Стеллаж металлический СТ-СПЭ 4(4) | B19: =Калькуляция!E28 -> 7080.6951 | C19: 44 | D19: 0.4 | E19: =B19*D19 -> 2832.278 | F19: =1.9*C19 -> 83.6 | G19: 20 | H19: 25 | I19: 15 | O19: =B19*0.01 -> 70.806951
A20: Почтовый ящик ЯП-5 | B20: =Калькуляция!E8 -> 5538.2857 | C20: 45 | D20: 0.45 | E20: =B20*D20 -> 2492.2285 | F20: =1.9*C20 -> 85.5 | G20: 20 | H20: 25 | I20: 15 | M20: =#REF!+E20+F20+G20+H20+I20+J20+O20 -> #REF! | N20: =#REF!+E20+F20+G20+H20+I20+J20+O20 -> #REF! | O20: =B20*0.01 -> 55.382857
A21: Почтовый ящик ЯП-6 | B21: =Калькуляция!E9 -> 6006.4496 | C21: 50 | D21: 0.45 | E21: =B21*D21 -> 2702.9023 | F21: =1.9*C21 -> 95 | G21: 20 | H21: 25 | I21: 15 | M21: =#REF!+E21+F21+G21+H21+I21+J21+O21 -> #REF! | N21: =#REF!+E21+F21+G21+H21+I21+J21+O21 -> #REF! | O21: =B21*0.01 -> 60.064496
A22: Стеллаж металлический200*100*50 4п | B22: =Калькуляция!E23 -> 9768.511 | C22: 55 | D22: 0.34 | E22: =B22*D22 -> 3321.2937 | F22: =1.9*C22 -> 104.5 | G22: 20 | H22: 25 | I22: 15 | M22: =#REF!+E22+F22+G22+H22+I22+J22+O22 -> #REF! | N22: =#REF!+E22+F22+G22+H22+I22+J22+O22 -> #REF! | O22: =B22*0.01 -> 97.68511
A23: Стеллаж металлический СТ-СПЭ 5(4) | B23: =Калькуляция!E30 -> 8920.6157 | C23: 55 | D23: 0.4 | E23: =B23*D23 -> 3568.2463 | F23: =1.9*C23 -> 104.5 | G23: 20 | H23: 25 | I23: 15 | O23: =B23*0.01 -> 89.206157
A24: СМ 50 | B24: =Калькуляция!E19 -> 9500.6294 | C24: 59 | D24: 0.4 | E24: =B24*D24 -> 3800.2518 | F24: =1.9*C24 -> 112.1 | G24: 20 | H24: 25 | I24: 15 | M24: =#REF!+E24+F24+G24+H24+I24+J24+O24 -> #REF! | N24: =#REF!+E24+F24+G24+H24+I24+J24+O24 -> #REF! | O24: =B24*0.01 -> 95.006294
A25: СМ 50-Э | B25: =Калькуляция!E20 -> 10543.567 | C25: 59 | D25: 0.4 | E25: =B25*D25 -> 4217.427 | F25: =1.9*C25 -> 112.1 | G25: 20 | H25: 25 | I25: 15 | M25: =#REF!+E25+F25+G25+H25+I25+J25+O25 -> #REF! | N25: =#REF!+E25+F25+G25+H25+I25+J25+O25 -> #REF! | O25: =B25*0.01 -> 105.43567
A26: ШБС 01-МИНИ-Т | B26: =Калькуляция!E25 -> 9608.4492 | C26: 62 | D26: 0.4 | E26: =B26*D26 -> 3843.3797 | F26: =1.9*C26 -> 117.8 | G26: 20 | H26: 25 | I26: 15 | M26: =#REF!+E26+F26+G26+H26+I26+J26+O26 -> #REF! | N26: =#REF!+E26+F26+G26+H26+I26+J26+O26 -> #REF! | O26: =B26*0.01 -> 96.084492
A27: ШБС 01-МИНИ | B27: =Калькуляция!E24 -> 9149.4402 | C27: 64 | D27: 0.4 | E27: =B27*D27 -> 3659.7761 | F27: =1.9*C27 -> 121.6 | G27: 20 | H27: 25 | I27: 15 | M27: =#REF!+E27+F27+G27+H27+I27+J27+O27 -> #REF! | N27: =#REF!+E27+F27+G27+H27+I27+J27+O27 -> #REF! | O27: =B27*0.01 -> 91.494402
A28: Стеллаж металлический200*100*40 6п | B28: =Калькуляция!E22 -> 9152.8146 | C28: 65 | D28: 0.34 | E28: =B28*D28 -> 3111.957 | F28: =1.9*C28 -> 123.5 | G28: 20 | H28: 25 | I28: 15 | M28: =#REF!+E28+F28+G28+H28+I28+J28+O28 -> #REF! | N28: =#REF!+E28+F28+G28+H28+I28+J28+O28 -> #REF! | O28: =B28*0.01 -> 91.528146
A29: Стеллаж металлический СТ-СПЭ 4(6) | B29: =Калькуляция!E29 -> 8426.4492 | C29: 65 | D29: 0.4 | E29: =B29*D29 -> 3370.5797 | F29: =1.9*C29 -> 123.5 | G29: 20 | H29: 25 | I29: 15 | O29: =B29*0.01 -> 84.264492
A30: ШО-1 | B30: =Калькуляция!E32 -> 18800.428 | C30: 65 | D30: 0.45 | E30: =B30*D30 -> 8460.1928 | F30: =1.9*C30 -> 123.5 | G30: 20 | H30: 25 | I30: 15 | O30: =B30*0.01 -> 188.00428
A31: Почтовый ящик ЯП-8 | B31: =Калькуляция!E10 -> 7836.3059 | C31: 72 | D31: 0.45 | E31: =B31*D31 -> 3526.3376 | F31: =1.9*C31 -> 136.8 | G31: 20 | H31: 25 | I31: 15 | M31: =#REF!+E31+F31+G31+H31+I31+J31+O31 -> #REF! | N31: =#REF!+E31+F31+G31+H31+I31+J31+O31 -> #REF! | O31: =B31*0.01 -> 78.363059
A32: ШО-4 | B32: =Калькуляция!E35 -> 22478.051 | C32: 88 | D32: 0.45 | E32: =B32*D32 -> 10115.123 | F32: =1.9*C32 -> 167.2 | G32: 20 | H32: 25 | I32: 15 | O32: =B32*0.01 -> 224.78051
A33: Шкаф бухгалтерский ШБС-01-17 | B33: =Калькуляция!E26 -> 31197.987 | C33: 348 | D33: 0.4 | E33: =B33*D33 -> 12479.195 | F33: =1.9*C33 -> 661.2 | G33: 20 | H33: 25 | I33: 15 | M33: =#REF!+E33+F33+G33+H33+I33+J33+O33 -> #REF! | N33: =#REF!+E33+F33+G33+H33+I33+J33+O33 -> #REF! | O33: =B33*0.01 -> 311.97987
A34: Шкаф бухгалтерский ШБС-02-17 | B34: =Калькуляция!E27 -> 33611.28 | C34: 348 | D34: 0.4 | E34: =B34*D34 -> 13444.512 | F34: =1.9*C34 -> 661.2 | G34: 20 | H34: 25 | I34: 15 | M34: =#REF!+E34+F34+G34+H34+I34+J34+O34 -> #REF! | N34: =#REF!+E34+F34+G34+H34+I34+J34+O34 -> #REF! | O34: =B34*0.01 -> 336.1128
A35: ШО-5 | B35: =Калькуляция!E31 -> 42907.582 | C35: 348 | D35: 0.45 | E35: =B35*D35 -> 19308.412 | F35: =1.9*C35 -> 661.2 | G35: 20 | H35: 25 | I35: 15 | O35: =B35*0.01 -> 429.07582

Sheet Тарифы логистика 3-4л
A2: 3,001-4 л | B2: Казань | C2: Казань | D2: 78
A3: 3,001-4 л | B3: Казань | C3: Самара | D3: 82
A4: 3,001-4 л | B4: Казань | C4: Саратов | D4: 82
A5: 3,001-4 л | B5: Казань | C5: Тверь | D5: 91
A6: 3,001-4 л | B6: Казань | C6: Москва, МО и Дальние регионы | D6: 92
A7: 3,001-4 л | B7: Казань | C7: Екатеринбург | D7: 93
A8: 3,001-4 л | B8: Казань | C8: Оренбург | D8: 94
A9: 3,001-4 л | B9: Казань | C9: Пермь | D9: 94
A10: 3,001-4 л | B10: Казань | C10: Уфа | D10: 94
A11: 3,001-4 л | B11: Казань | C11: Ярославль | D11: 95
A12: 3,001-4 л | B12: Казань | C12: Беларусь | D12: 97
A13: 3,001-4 л | B13: Казань | C13: Воронеж | D13: 102 | E13: ближ
A14: 3,001-4 л | B14: Казань | C14: Калининград | D14: 111
A15: 3,001-4 л | B15: Казань | C15: Санкт-Петербург и СЗО | D15: 112
A16: 3,001-4 л | B16: Казань | C16: Краснодар | D16: 126
A17: 3,001-4 л | B17: Казань | C17: Махачкала | D17: 126
A18: 3,001-4 л | B18: Казань | C18: Невинномысск | D18: 127
A19: 3,001-4 л | B19: Казань | C19: Ростов | D19: 127
A20: 3,001-4 л | B20: Казань | C20: Азербайджан | D20: 133
A21: 3,001-4 л | B21: Казань | C21: Армения | D21: 133
A22: 3,001-4 л | B22: Казань | C22: Грузия | D22: 133 | E22: сред
A23: 3,001-4 л | B23: Казань | C23: Новосибирск | D23: 146
A24: 3,001-4 л | B24: Казань | C24: Омск | D24: 146
A25: 3,001-4 л | B25: Казань | C25: Красноярск | D25: 147
A26: 3,001-4 л | B26: Казань | C26: Тюмень | D26: 147
A27: 3,001-4 л | B27: Казань | C27: Алматы | D27: 154
A28: 3,001-4 л | B28: Казань | C28: Астана | D28: 154
A29: 3,001-4 л | B29: Казань | C29: Кыргызстан | D29: 154
A30: 3,001-4 л | B30: Казань | C30: Узбекистан | D30: 154
A31: 3,001-4 л | B31: Казань | C31: Дальний Восток | D31: 206 | E31: дальн

Sheet Тарифы логистика 13-14л 
A1: 13,001-14 л | B1: Казань | C1: Казань | D1: 107
A2: 13,001-14 л | B2: Казань | C2: Самара | D2: 112
A3: 13,001-14 л | B3: Казань | C3: Саратов | D3: 112
A4: 13,001-14 л | B4: Казань | C4: Уфа | D4: 146
A5: 13,001-14 л | B5: Казань | C5: Оренбург | D5: 149
A6: 13,001-14 л | B6: Казань | C6: Пермь | D6: 149
A7: 13,001-14 л | B7: Казань | C7: Екатеринбург | D7: 153
A8: 13,001-14 л | B8: Казань | C8: Ярославль | D8: 158
A9: 13,001-14 л | B9: Казань | C9: Москва, МО и Дальние регионы | D9: 159
A10: 13,001-14 л | B10: Казань | C10: Тверь | D10: 159
A11: 13,001-14 л | B11: Казань | C11: Беларусь | D11: 167
A12: 13,001-14 л | B12: Казань | C12: Воронеж | D12: 184 | E12: ближ
A13: 13,001-14 л | B13: Казань | C13: Санкт-Петербург и СЗО | D13: 199
A14: 13,001-14 л | B14: Казань | C14: Калининград | D14: 206
A15: 13,001-14 л | B15: Казань | C15: Махачкала | D15: 209
A16: 13,001-14 л | B16: Казань | C16: Краснодар | D16: 213
A17: 13,001-14 л | B17: Казань | C17: Ростов | D17: 216
A18: 13,001-14 л | B18: Казань | C18: Невинномысск | D18: 219
A19: 13,001-14 л | B19: Казань | C19: Азербайджан | D19: 220
A20: 13,001-14 л | B20: Казань | C20: Армения | D20: 220
A21: 13,001-14 л | B21: Казань | C21: Грузия | D21: 220 | E21: сред
A22: 13,001-14 л | B22: Казань | C22: Омск | D22: 247
A23: 13,001-14 л | B23: Казань | C23: Новосибирск | D23: 251
A24: 13,001-14 л | B24: Казань | C24: Тюмень | D24: 251
A25: 13,001-14 л | B25: Казань | C25: Красноярск | D25: 254
A26: 13,001-14 л | B26: Казань | C26: Астана | D26: 260
A27: 13,001-14 л | B27: Казань | C27: Алматы | D27: 264
A28: 13,001-14 л | B28: Казань | C28: Кыргызстан | D28: 264
A29: 13,001-14 л | B29: Казань | C29: Узбекистан | D29: 264
A30: 13,001-14 л | B30: Казань | C30: Дальний Восток | D30: 357 | E30: дальн

Sheet Тарифы логистика 14-15л
A1: 14,001-15 л | B1: Казань | C1: Казань | D1: 112
A2: 14,001-15 л | B2: Казань | C2: Самара | D2: 118
A3: 14,001-15 л | B3: Казань | C3: Саратов | D3: 118
A4: 14,001-15 л | B4: Казань | C4: Уфа | D4: 153
A5: 14,001-15 л | B5: Казань | C5: Оренбург | D5: 156
A6: 14,001-15 л | B6: Казань | C6: Пермь | D6: 156
A7: 14,001-15 л | B7: Казань | C7: Екатеринбург | D7: 160
A8: 14,001-15 л | B8: Казань | C8: Москва, МО и Дальние регионы | D8: 167
A9: 14,001-15 л | B9: Казань | C9: Тверь | D9: 167
A10: 14,001-15 л | B10: Казань | C10: Ярославль | D10: 167
A11: 14,001-15 л | B11: Казань | C11: Беларусь | D11: 176
A12: 14,001-15 л | B12: Казань | C12: Воронеж | D12: 193 | E12: ближ
A13: 14,001-15 л | B13: Казань | C13: Санкт-Петербург и СЗО | D13: 210
A14: 14,001-15 л | B14: Казань | C14: Махачкала | D14: 213
A15: 14,001-15 л | B15: Казань | C15: Калининград | D15: 214
A16: 14,001-15 л | B16: Казань | C16: Краснодар | D16: 216
A17: 14,001-15 л | B17: Казань | C17: Ростов | D17: 223
A18: 14,001-15 л | B18: Казань | C18: Невинномысск | D18: 224
A19: 14,001-15 л | B19: Казань | C19: Азербайджан | D19: 224
A20: 14,001-15 л | B20: Казань | C20: Армения | D20: 224
A21: 14,001-15 л | B21: Казань | C21: Грузия | D21: 224 | E21: сред
A22: 14,001-15 л | B22: Казань | C22: Омск | D22: 255
A23: 14,001-15 л | B23: Казань | C23: Новосибирск | D23: 260
A24: 14,001-15 л | B24: Казань | C24: Красноярск | D24: 262
A25: 14,001-15 л | B25: Казань | C25: Тюмень | D25: 262
A26: 14,001-15 л | B26: Казань | C26: Астана | D26: 268
A27: 14,001-15 л | B27: Казань | C27: Алматы | D27: 273
A28: 14,001-15 л | B28: Казань | C28: Кыргызстан | D28: 273
A29: 14,001-15 л | B29: Казань | C29: Узбекистан | D29: 273
A30: 14,001-15 л | B30: Казань | C30: Дальний Восток | D30: 370 | E30: дальн

Sheet Тарифы логистика 20-25л
A1: 20,001-25 л | B1: Казань | C1: Казань | D1: 144
A2: 20,001-25 л | B2: Казань | C2: Самара | D2: 151
A3: 20,001-25 л | B3: Казань | C3: Саратов | D3: 153
A4: 20,001-25 л | B4: Казань | C4: Уфа | D4: 215
A5: 20,001-25 л | B5: Казань | C5: Пермь | D5: 220
A6: 20,001-25 л | B6: Казань | C6: Оренбург | D6: 225
A7: 20,001-25 л | B7: Казань | C7: Екатеринбург | D7: 230
A8: 20,001-25 л | B8: Казань | C8: Ярославль | D8: 242
A9: 20,001-25 л | B9: Казань | C9: Москва, МО и Дальние регионы | D9: 244
A10: 20,001-25 л | B10: Казань | C10: Тверь | D10: 245
A11: 20,001-25 л | B11: Казань | C11: Беларусь | D11: 257 | E11: ближ
A12: 20,001-25 л | B12: Казань | C12: Воронеж | D12: 278
A13: 20,001-25 л | B13: Казань | C13: Краснодар | D13: 318
A14: 20,001-25 л | B14: Казань | C14: Санкт-Петербург и СЗО | D14: 319
A15: 20,001-25 л | B15: Казань | C15: Махачкала | D15: 320
A16: 20,001-25 л | B16: Казань | C16: Калининград | D16: 325
A17: 20,001-25 л | B17: Казань | C17: Ростов | D17: 330
A18: 20,001-25 л | B18: Казань | C18: Невинномысск | D18: 332
A19: 20,001-25 л | B19: Казань | C19: Азербайджан | D19: 336
A20: 20,001-25 л | B20: Казань | C20: Армения | D20: 336
A21: 20,001-25 л | B21: Казань | C21: Грузия | D21: 336 | E21: сред
A22: 20,001-25 л | B22: Казань | C22: Омск | D22: 374
A23: 20,001-25 л | B23: Казань | C23: Новосибирск | D23: 384
A24: 20,001-25 л | B24: Казань | C24: Красноярск | D24: 389
A25: 20,001-25 л | B25: Казань | C25: Тюмень | D25: 390
A26: 20,001-25 л | B26: Казань | C26: Астана | D26: 393
A27: 20,001-25 л | B27: Казань | C27: Алматы | D27: 404
A28: 20,001-25 л | B28: Казань | C28: Кыргызстан | D28: 404
A29: 20,001-25 л | B29: Казань | C29: Узбекистан | D29: 404
A30: 20,001-25 л | B30: Казань | C30: Дальний Восток | D30: 548 | E30: дальн

Sheet Тарифы логистика 30-35л
A1: 30,001-35 л | B1: Казань | C1: Казань | D1: 179
A2: 30,001-35 л | B2: Казань | C2: Самара | D2: 189
A3: 30,001-35 л | B3: Казань | C3: Саратов | D3: 194
A4: 30,001-35 л | B4: Казань | C4: Уфа | D4: 290
A5: 30,001-35 л | B5: Казань | C5: Пермь | D5: 298
A6: 30,001-35 л | B6: Казань | C6: Оренбург | D6: 304
A7: 30,001-35 л | B7: Казань | C7: Екатеринбург | D7: 310
A8: 30,001-35 л | B8: Казань | C8: Ярославль | D8: 315
A9: 30,001-35 л | B9: Казань | C9: Москва, МО и Дальние регионы | D9: 320
A10: 30,001-35 л | B10: Казань | C10: Тверь | D10: 323
A11: 30,001-35 л | B11: Казань | C11: Беларусь | D11: 336
A12: 30,001-35 л | B12: Казань | C12: Воронеж | D12: 373 | E12: ближ
A13: 30,001-35 л | B13: Казань | C13: Махачкала | D13: 418
A14: 30,001-35 л | B14: Казань | C14: Краснодар | D14: 420
A15: 30,001-35 л | B15: Казань | C15: Санкт-Петербург и СЗО | D15: 426
A16: 30,001-35 л | B16: Казань | C16: Невинномысск | D16: 430
A17: 30,001-35 л | B17: Казань | C17: Азербайджан | D17: 439
A18: 30,001-35 л | B18: Казань | C18: Армения | D18: 439
A19: 30,001-35 л | B19: Казань | C19: Грузия | D19: 439
A20: 30,001-35 л | B20: Казань | C20: Калининград | D20: 441
A21: 30,001-35 л | B21: Казань | C21: Ростов | D21: 441 | E21: серд
A22: 30,001-35 л | B22: Казань | C22: Омск | D22: 503
A23: 30,001-35 л | B23: Казань | C23: Красноярск | D23: 525
A24: 30,001-35 л | B24: Казань | C24: Тюмень | D24: 526
A25: 30,001-35 л | B25: Казань | C25: Новосибирск | D25: 527
A26: 30,001-35 л | B26: Казань | C26: Астана | D26: 529
A27: 30,001-35 л | B27: Казань | C27: Алматы | D27: 554
A28: 30,001-35 л | B28: Казань | C28: Кыргызстан | D28: 554
A29: 30,001-35 л | B29: Казань | C29: Узбекистан | D29: 554
A30: 30,001-35 л | B30: Казань | C30: Дальний Восток | D30: 760 | E30: дальн

Sheet Тарифы логистика 35-40л
A1: 35,001-40 л | B1: Казань | C1: Казань | D1: 200
A2: 35,001-40 л | B2: Казань | C2: Самара | D2: 210
A3: 35,001-40 л | B3: Казань | C3: Саратов | D3: 217
A4: 35,001-40 л | B4: Казань | C4: Уфа | D4: 322
A5: 35,001-40 л | B5: Казань | C5: Пермь | D5: 337
A6: 35,001-40 л | B6: Казань | C6: Оренбург | D6: 338
A7: 35,001-40 л | B7: Казань | C7: Екатеринбург | D7: 346
A8: 35,001-40 л | B8: Казань | C8: Ярославль | D8: 349
A9: 35,001-40 л | B9: Казань | C9: Москва, МО и Дальние регионы | D9: 354
A10: 35,001-40 л | B10: Казань | C10: Тверь | D10: 358
A11: 35,001-40 л | B11: Казань | C11: Беларусь | D11: 372
A12: 35,001-40 л | B12: Казань | C12: Воронеж | D12: 417 | E12: ближ
A13: 35,001-40 л | B13: Казань | C13: Краснодар | D13: 475
A14: 35,001-40 л | B14: Казань | C14: Санкт-Петербург и СЗО | D14: 481
A15: 35,001-40 л | B15: Казань | C15: Махачкала | D15: 483
A16: 35,001-40 л | B16: Казань | C16: Ростов | D16: 484
A17: 35,001-40 л | B17: Казань | C17: Невинномысск | D17: 488
A18: 35,001-40 л | B18: Казань | C18: Калининград | D18: 504
A19: 35,001-40 л | B19: Казань | C19: Азербайджан | D19: 508
A20: 35,001-40 л | B20: Казань | C20: Армения | D20: 508
A21: 35,001-40 л | B21: Казань | C21: Грузия | D21: 508 | E21: сред
A22: 35,001-40 л | B22: Казань | C22: Омск | D22: 572
A23: 35,001-40 л | B23: Казань | C23: Новосибирск | D23: 599
A24: 35,001-40 л | B24: Казань | C24: Астана | D24: 601
A25: 35,001-40 л | B25: Казань | C25: Тюмень | D25: 604
A26: 35,001-40 л | B26: Казань | C26: Красноярск | D26: 607
A27: 35,001-40 л | B27: Казань | C27: Алматы | D27: 629
A28: 35,001-40 л | B28: Казань | C28: Кыргызстан | D28: 629
A29: 35,001-40 л | B29: Казань | C29: Узбекистан | D29: 629
A30: 35,001-40 л | B30: Казань | C30: Дальний Восток | D30: 879 | E30: дальн

Sheet Тарифы логистика 40-45л
A1: 40,001-45 л | B1: Казань | C1: Казань | D1: 215
A2: 40,001-45 л | B2: Казань | C2: Самара | D2: 230
A3: 40,001-45 л | B3: Казань | C3: Саратов | D3: 239
A4: 40,001-45 л | B4: Казань | C4: Уфа | D4: 356
A5: 40,001-45 л | B5: Казань | C5: Пермь | D5: 371
A6: 40,001-45 л | B6: Казань | C6: Оренбург | D6: 372
A7: 40,001-45 л | B7: Казань | C7: Екатеринбург | D7: 385
A8: 40,001-45 л | B8: Казань | C8: Ярославль | D8: 386
A9: 40,001-45 л | B9: Казань | C9: Москва, МО и Дальние регионы | D9: 391
A10: 40,001-45 л | B10: Казань | C10: Тверь | D10: 395
A11: 40,001-45 л | B11: Казань | C11: Беларусь | D11: 411
A12: 40,001-45 л | B12: Казань | C12: Воронеж | D12: 478 | E12: ближ
A13: 40,001-45 л | B13: Казань | C13: Санкт-Петербург и СЗО | D13: 534
A14: 40,001-45 л | B14: Казань | C14: Краснодар | D14: 539
A15: 40,001-45 л | B15: Казань | C15: Махачкала | D15: 540
A16: 40,001-45 л | B16: Казань | C16: Калининград | D16: 555
A17: 40,001-45 л | B17: Казань | C17: Ростов | D17: 556
A18: 40,001-45 л | B18: Казань | C18: Невинномысск | D18: 557
A19: 40,001-45 л | B19: Казань | C19: Азербайджан | D19: 567
A20: 40,001-45 л | B20: Казань | C20: Армения | D20: 567
A21: 40,001-45 л | B21: Казань | C21: Грузия | D21: 567 | E21: сред
A22: 40,001-45 л | B22: Казань | C22: Омск | D22: 632
A23: 40,001-45 л | B23: Казань | C23: Красноярск | D23: 660
A24: 40,001-45 л | B24: Казань | C24: Новосибирск | D24: 660
A25: 40,001-45 л | B25: Казань | C25: Астана | D25: 664
A26: 40,001-45 л | B26: Казань | C26: Тюмень | D26: 676
A27: 40,001-45 л | B27: Казань | C27: Алматы | D27: 693
A28: 40,001-45 л | B28: Казань | C28: Кыргызстан | D28: 693
A29: 40,001-45 л | B29: Казань | C29: Узбекистан | D29: 693
A30: 40,001-45 л | B30: Казань | C30: Дальний Восток | D30: 969 | E30: дальн

Sheet Тарифы логистика 50-60л
A1: 50,001-60 л | B1: Казань | C1: Казань | D1: 251
A2: 50,001-60 л | B2: Казань | C2: Самара | D2: 272
A3: 50,001-60 л | B3: Казань | C3: Саратов | D3: 284
A4: 50,001-60 л | B4: Казань | C4: Уфа | D4: 432
A5: 50,001-60 л | B5: Казань | C5: Пермь | D5: 441
A6: 50,001-60 л | B6: Казань | C6: Оренбург | D6: 462
A7: 50,001-60 л | B7: Казань | C7: Екатеринбург | D7: 463
A8: 50,001-60 л | B8: Казань | C8: Ярославль | D8: 464
A9: 50,001-60 л | B9: Казань | C9: Москва, МО и Дальние регионы | D9: 474
A10: 50,001-60 л | B10: Казань | C10: Тверь | D10: 481
A11: 50,001-60 л | B11: Казань | C11: Беларусь | D11: 498
A12: 50,001-60 л | B12: Казань | C12: Воронеж | D12: 569 | E12: ближ
A13: 50,001-60 л | B13: Казань | C13: Краснодар | D13: 639
A14: 50,001-60 л | B14: Казань | C14: Махачкала | D14: 653
A15: 50,001-60 л | B15: Казань | C15: Санкт-Петербург и СЗО | D15: 655
A16: 50,001-60 л | B16: Казань | C16: Ростов | D16: 659
A17: 50,001-60 л | B17: Казань | C17: Невинномысск | D17: 663
A18: 50,001-60 л | B18: Казань | C18: Калининград | D18: 670
A19: 50,001-60 л | B19: Казань | C19: Азербайджан | D19: 686
A20: 50,001-60 л | B20: Казань | C20: Армения | D20: 686
A21: 50,001-60 л | B21: Казань | C21: Грузия | D21: 686 | E21: сред
A22: 50,001-60 л | B22: Казань | C22: Омск | D22: 763
A23: 50,001-60 л | B23: Казань | C23: Новосибирск | D23: 786
A24: 50,001-60 л | B24: Казань | C24: Красноярск | D24: 797
A25: 50,001-60 л | B25: Казань | C25: Астана | D25: 802
A26: 50,001-60 л | B26: Казань | C26: Тюмень | D26: 803
A27: 50,001-60 л | B27: Казань | C27: Алматы | D27: 826
A28: 50,001-60 л | B28: Казань | C28: Кыргызстан | D28: 826
A29: 50,001-60 л | B29: Казань | C29: Узбекистан | D29: 826
A30: 50,001-60 л | B30: Казань | C30: Дальний Восток | D30: 1178 | E30: дальн

Sheet Тарифы логистика 60-70л
A1: 60,001-70 л | B1: Казань | C1: Казань | D1: 289
A2: 60,001-70 л | B2: Казань | C2: Самара | D2: 311
A3: 60,001-70 л | B3: Казань | C3: Саратов | D3: 324
A4: 60,001-70 л | B4: Казань | C4: Уфа | D4: 509
A5: 60,001-70 л | B5: Казань | C5: Ярославль | D5: 511
A6: 60,001-70 л | B6: Казань | C6: Тверь | D6: 517
A7: 60,001-70 л | B7: Казань | C7: Москва, МО и Дальние регионы | D7: 519
A8: 60,001-70 л | B8: Казань | C8: Оренбург | D8: 534
A9: 60,001-70 л | B9: Казань | C9: Пермь | D9: 535
A10: 60,001-70 л | B10: Казань | C10: Беларусь | D10: 545
A11: 60,001-70 л | B11: Казань | C11: Екатеринбург | D11: 546
A12: 60,001-70 л | B12: Казань | C12: Воронеж | D12: 658 | E12: ближ
A13: 60,001-70 л | B13: Казань | C13: Санкт-Петербург и СЗО | D13: 731
A14: 60,001-70 л | B14: Казань | C14: Краснодар | D14: 744
A15: 60,001-70 л | B15: Казань | C15: Калининград | D15: 748
A16: 60,001-70 л | B16: Казань | C16: Ростов | D16: 752
A17: 60,001-70 л | B17: Казань | C17: Махачкала | D17: 757
A18: 60,001-70 л | B18: Казань | C18: Невинномысск | D18: 764
A19: 60,001-70 л | B19: Казань | C19: Азербайджан | D19: 795
A20: 60,001-70 л | B20: Казань | C20: Армения | D20: 795
A21: 60,001-70 л | B21: Казань | C21: Грузия | D21: 795 | E21: сред
A22: 60,001-70 л | B22: Казань | C22: Омск | D22: 903
A23: 60,001-70 л | B23: Казань | C23: Новосибирск | D23: 922
A24: 60,001-70 л | B24: Казань | C24: Тюмень | D24: 929
A25: 60,001-70 л | B25: Казань | C25: Красноярск | D25: 948
A26: 60,001-70 л | B26: Казань | C26: Астана | D26: 949
A27: 60,001-70 л | B27: Казань | C27: Алматы | D27: 969
A28: 60,001-70 л | B28: Казань | C28: Кыргызстан | D28: 969
A29: 60,001-70 л | B29: Казань | C29: Узбекистан | D29: 969
A30: 60,001-70 л | B30: Казань | C30: Дальний Восток | D30: 1413 | E30: дальн

Sheet Тарифы логистика 70-80л
A1: 70,001-80 л | B1: Казань | C1: Казань | D1: 299
A2: 70,001-80 л | B2: Казань | C2: Самара | D2: 336
A3: 70,001-80 л | B3: Казань | C3: Саратов | D3: 348
A4: 70,001-80 л | B4: Казань | C4: Уфа | D4: 551
A5: 70,001-80 л | B5: Казань | C5: Ярославль | D5: 579
A6: 70,001-80 л | B6: Казань | C6: Тверь | D6: 593
A7: 70,001-80 л | B7: Казань | C7: Москва, МО и Дальние регионы | D7: 595
A8: 70,001-80 л | B8: Казань | C8: Пермь | D8: 601
A9: 70,001-80 л | B9: Казань | C9: Оренбург | D9: 605
A10: 70,001-80 л | B10: Казань | C10: Екатеринбург | D10: 607
A11: 70,001-80 л | B11: Казань | C11: Беларусь | D11: 625
A12: 70,001-80 л | B12: Казань | C12: Воронеж | D12: 732 | E12: ближ
A13: 70,001-80 л | B13: Казань | C13: Краснодар | D13: 815
A14: 70,001-80 л | B14: Казань | C14: Махачкала | D14: 828
A15: 70,001-80 л | B15: Казань | C15: Ростов | D15: 840
A16: 70,001-80 л | B16: Казань | C16: Невинномысск | D16: 847
A17: 70,001-80 л | B17: Казань | C17: Санкт-Петербург и СЗО | D17: 851
A18: 70,001-80 л | B18: Казань | C18: Калининград | D18: 860
A19: 70,001-80 л | B19: Казань | C19: Азербайджан | D19: 870
A20: 70,001-80 л | B20: Казань | C20: Армения | D20: 870
A21: 70,001-80 л | B21: Казань | C21: Грузия | D21: 870 | E21: сред
A22: 70,001-80 л | B22: Казань | C22: Новосибирск | D22: 1045
A23: 70,001-80 л | B23: Казань | C23: Омск | D23: 1046
A24: 70,001-80 л | B24: Казань | C24: Тюмень | D24: 1055
A25: 70,001-80 л | B25: Казань | C25: Красноярск | D25: 1069
A26: 70,001-80 л | B26: Казань | C26: Алматы | D26: 1098
A27: 70,001-80 л | B27: Казань | C27: Кыргызстан | D27: 1098
A28: 70,001-80 л | B28: Казань | C28: Узбекистан | D28: 1098
A29: 70,001-80 л | B29: Казань | C29: Астана | D29: 1099
A30: 70,001-80 л | B30: Казань | C30: Дальний Восток | D30: 1591 | E30: дальн

Sheet Тарифы логистика 80-90л
A1: 80,001-90 л | B1: Казань | C1: Казань | D1: 357
A2: 80,001-90 л | B2: Казань | C2: Самара | D2: 389
A3: 80,001-90 л | B3: Казань | C3: Саратов | D3: 413
A4: 80,001-90 л | B4: Казань | C4: Уфа | D4: 655
A5: 80,001-90 л | B5: Казань | C5: Ярославль | D5: 658
A6: 80,001-90 л | B6: Казань | C6: Москва, МО и Дальние регионы | D6: 662
A7: 80,001-90 л | B7: Казань | C7: Тверь | D7: 667
A8: 80,001-90 л | B8: Казань | C8: Пермь | D8: 682
A9: 80,001-90 л | B9: Казань | C9: Оренбург | D9: 683
A10: 80,001-90 л | B10: Казань | C10: Беларусь | D10: 696
A11: 80,001-90 л | B11: Казань | C11: Екатеринбург | D11: 721
A12: 80,001-90 л | B12: Казань | C12: Воронеж | D12: 829 | E12: ближ
A13: 80,001-90 л | B13: Казань | C13: Санкт-Петербург и СЗО | D13: 957
A14: 80,001-90 л | B14: Казань | C14: Краснодар | D14: 966
A15: 80,001-90 л | B15: Казань | C15: Калининград | D15: 975
A16: 80,001-90 л | B16: Казань | C16: Махачкала | D16: 979
A17: 80,001-90 л | B17: Казань | C17: Невинномысск | D17: 987
A18: 80,001-90 л | B18: Казань | C18: Ростов | D18: 987
A19: 80,001-90 л | B19: Казань | C19: Азербайджан | D19: 1028
A20: 80,001-90 л | B20: Казань | C20: Армения | D20: 1028
A21: 80,001-90 л | B21: Казань | C21: Грузия | D21: 1028 | E21: сред
A22: 80,001-90 л | B22: Казань | C22: Омск | D22: 1223
A23: 80,001-90 л | B23: Казань | C23: Новосибирск | D23: 1266
A24: 80,001-90 л | B24: Казань | C24: Красноярск | D24: 1275
A25: 80,001-90 л | B25: Казань | C25: Тюмень | D25: 1275
A26: 80,001-90 л | B26: Казань | C26: Астана | D26: 1285
A27: 80,001-90 л | B27: Казань | C27: Алматы | D27: 1330
A28: 80,001-90 л | B28: Казань | C28: Кыргызстан | D28: 1330
A29: 80,001-90 л | B29: Казань | C29: Узбекистан | D29: 1330
A30: 80,001-90 л | B30: Казань | C30: Дальний Восток | D30: 1841 | E30: дальн

Sheet Тарифы логистика 200-400л
A1: 200,001-400 л | B1: Казань | C1: Казань | D1: 1080
A2: 200,001-400 л | B2: Казань | C2: Самара | D2: 1147
A3: 200,001-400 л | B3: Казань | C3: Саратов | D3: 1201
A4: 200,001-400 л | B4: Казань | C4: Ярославль | D4: 1929
A5: 200,001-400 л | B5: Казань | C5: Москва, МО и Дальние регионы | D5: 1962
A6: 200,001-400 л | B6: Казань | C6: Тверь | D6: 1971
A7: 200,001-400 л | B7: Казань | C7: Беларусь | D7: 2061 | E7: ближ
A8: 200,001-400 л | B8: Казань | C8: Уфа | D8: 2313
A9: 200,001-400 л | B9: Казань | C9: Оренбург | D9: 2362
A10: 200,001-400 л | B10: Казань | C10: Пермь | D10: 2366
A11: 200,001-400 л | B11: Казань | C11: Екатеринбург | D11: 2412
A12: 200,001-400 л | B12: Казань | C12: Воронеж | D12: 2554
A13: 200,001-400 л | B13: Казань | C13: Санкт-Петербург и СЗО | D13: 2879
A14: 200,001-400 л | B14: Казань | C14: Калининград | D14: 2910
A15: 200,001-400 л | B15: Казань | C15: Махачкала | D15: 2963
A16: 200,001-400 л | B16: Казань | C16: Ростов | D16: 2993
A17: 200,001-400 л | B17: Казань | C17: Краснодар | D17: 3004
A18: 200,001-400 л | B18: Казань | C18: Невинномысск | D18: 3105
A19: 200,001-400 л | B19: Казань | C19: Азербайджан | D19: 3112
A20: 200,001-400 л | B20: Казань | C20: Армения | D20: 3112
A21: 200,001-400 л | B21: Казань | C21: Грузия | D21: 3112 | E21: сред
A22: 200,001-400 л | B22: Казань | C22: Омск | D22: 3722
A23: 200,001-400 л | B23: Казань | C23: Новосибирск | D23: 3809
A24: 200,001-400 л | B24: Казань | C24: Тюмень | D24: 3821
A25: 200,001-400 л | B25: Казань | C25: Красноярск | D25: 3887
A26: 200,001-400 л | B26: Казань | C26: Астана | D26: 3909
A27: 200,001-400 л | B27: Казань | C27: Алматы | D27: 4000
A28: 200,001-400 л | B28: Казань | C28: Кыргызстан | D28: 4000
A29: 200,001-400 л | B29: Казань | C29: Узбекистан | D29: 4000
A30: 200,001-400 л | B30: Казань | C30: Дальний Восток | D30: 5646 | E30: дальн

Sheet Общая комиссия акции
A1: Товар | B1: Цена на мп | C1: Объем Л | D1: Вознаграждение МП процент | E1: Вознаграждение МП руб | F1: Тариф отгрузки 1,9 руб/л | G1: Отгрузка в СЦ | H1: Доставка в ПВЗ | I1: Обработка возврата | J1: логистика + обратная | K1: Эквайринг 1,5%
A2: АМУ-1 | B2: =Калькуляция!#REF! -> #REF! | C2: 23 | D2: 0.44 | E2: =B2*D2 -> #REF! | F2: =1.9*C2 -> 43.7 | G2: 20 | H2: 25 | I2: 15 | J2: =Логистика!B14+(Логистика!B14*0.15) -> 700.35 | K2: =B2*0.01 -> #REF!
A3: К148 | B3: =Калькуляция!E3 -> 5069.8174 | C3: 13 | D3: 0.43 | E3: =B3*D3 -> 2180.0215 | F3: =1.9*C3 -> 24.7 | G3: 20 | H3: 25 | I3: 15 | J3: =Логистика!B23+(Логистика!B23*0.15) -> 431.25 | K3: =B3*0.01 -> 50.698174
A4: К20 | B4: =Калькуляция!E4 -> 1330.7173 | C4: 3 | D4: 0.43 | E4: =B4*D4 -> 572.20844 | F4: =1.9*C4 -> 5.7 | G4: 20 | H4: 25 | I4: 15 | J4: =Логистика!B18+(Логистика!B18*0.15) -> 162.15 | K4: =B4*0.01 -> 13.307173
A5: К40 | B5: =Калькуляция!E5 -> 2790.7106 | C5: 13 | D5: 0.43 | E5: =B5*D5 -> 1200.0056 | F5: =1.9*C5 -> 24.7 | G5: 20 | H5: 25 | I5: 15 | J5: =Логистика!B25+(Логистика!B25*0.15) -> 431.25 | K5: =B5*0.01 -> 27.907106
A6: К60 | B6: =Калькуляция!E6 -> 3196.5966 | C6: 14 | D6: 0.43 | E6: =B6*D6 -> 1374.5366 | F6: =1.9*C6 -> 26.6 | G6: 20 | H6: 25 | I6: 15 | J6: =Логистика!B24+(Логистика!B24*0.15) -> 458.85 | K6: =B6*0.01 -> 31.965966
A7: Почтовый ящик ЯП-4 | B7: =Калькуляция!E7 -> 4755.0731 | C7: 38 | D7: 0.45 | E7: =B7*D7 -> 2139.7829 | F7: =1.9*C7 -> 72.2 | G7: 20 | H7: 25 | I7: 15 | J7: =Логистика!B22+(Логистика!B22*0.15) -> 1104 | K7: =B7*0.01 -> 47.550731
A8: Почтовый ящик ЯП-5 | B8: =Калькуляция!E8 -> 5538.2857 | C8: 45 | D8: 0.45 | E8: =B8*D8 -> 2492.2285 | F8: =1.9*C8 -> 85.5 | G8: 20 | H8: 25 | I8: 15 | J8: =Логистика!B21+(Логистика!B21*0.15) -> 1292.6 | K8: =B8*0.01 -> 55.382857
A9: Почтовый ящик ЯП-6 | B9: =Калькуляция!E9 -> 6006.4496 | C9: 50 | D9: 0.45 | E9: =B9*D9 -> 2702.9023 | F9: =1.9*C9 -> 95 | G9: 20 | H9: 25 | I9: 15 | J9: =Логистика!B20+(Логистика!B20*0.15) -> 1427.15 | K9: =B9*0.01 -> 60.064496
A10: Почтовый ящик ЯП-8 | B10: =Калькуляция!E10 -> 7836.3059 | C10: 72 | D10: 0.45 | E10: =B10*D10 -> 3526.3376 | F10: =1.9*C10 -> 136.8 | G10: 20 | H10: 25 | I10: 15 | J10: =Логистика!B19+(Логистика!B19*0.15) -> 2018.25 | K10: =B10*0.01 -> 78.363059
A11: СМ 20 | B11: =Калькуляция!E11 -> 5324.119 | C11: 14 | D11: 0.4 | E11: =B11*D11 -> 2129.6476 | F11: =1.9*C11 -> 26.6 | G11: 20 | H11: 25 | I11: 15 | J11: =Логистика!B12+(Логистика!B12*0.15) -> 458.85 | K11: =B11*0.01 -> 53.24119
A12: СМ 20-Э | B12: =Калькуляция!E12 -> 6260.4327 | C12: 14 | D12: 0.4 | E12: =B12*D12 -> 2504.1731 | F12: =1.9*C12 -> 26.6 | G12: 20 | H12: 25 | I12: 15 | J12: =Логистика!B13+(Логистика!B13*0.15) -> 458.85 | K12: =B12*0.01 -> 62.604327
A13: СМ 23 | B13: =Калькуляция!E13 -> 7486.2973 | C13: 35 | D13: 0.4 | E13: =B13*D13 -> 2994.5189 | F13: =1.9*C13 -> 66.5 | G13: 20 | H13: 25 | I13: 15 | J13: =Логистика!B11+(Логистика!B11*0.15) -> 1023.5 | K13: =B13*0.01 -> 74.862973
A14: СМ 23-Э | B14: =Калькуляция!E14 -> 8274.1354 | C14: 34 | D14: 0.4 | E14: =B14*D14 -> 3309.6542 | F14: =1.9*C14 -> 64.6 | G14: 20 | H14: 25 | I14: 15 | J14: =Логистика!B10+(Логистика!B10*0.15) -> 995.9 | K14: =B14*0.01 -> 82.741354
A15: СМ 25 | B15: =Калькуляция!E15 -> 6103.6318 | C15: 24 | D15: 0.4 | E15: =B15*D15 -> 2441.4527 | F15: =1.9*C15 -> 45.6 | G15: 20 | H15: 25 | I15: 15 | J15: =Логистика!B8+(Логистика!B8*0.15) -> 727.95 | K15: =B15*0.01 -> 61.036318
A16: СМ 25-Э | B16: =Калькуляция!E16 -> 7112.7525 | C16: 24 | D16: 0.4 | E16: =B16*D16 -> 2845.101 | F16: =1.9*C16 -> 45.6 | G16: 20 | H16: 25 | I16: 15 | J16: =Логистика!B9+(Логистика!B9*0.15) -> 727.95 | K16: =B16*0.01 -> 71.127525
A17: СМ 30 | B17: =Калькуляция!E17 -> 7465.4968 | C17: 37 | D17: 0.4 | E17: =B17*D17 -> 2986.1987 | F17: =1.9*C17 -> 70.3 | G17: 20 | H17: 25 | I17: 15 | J17: =Логистика!B4+(Логистика!B4*0.15) -> 1077.55 | K17: =B17*0.01 -> 74.654968
A18: СМ 30-Э | B18: =Калькуляция!E18 -> 8767.4741 | C18: 37 | D18: 0.4 | E18: =B18*D18 -> 3506.9896 | F18: =1.9*C18 -> 70.3 | G18: 20 | H18: 25 | I18: 15 | J18: =Логистика!B5+(Логистика!B5*0.15) -> 1077.55 | K18: =B18*0.01 -> 87.674741
A19: СМ 50 | B19: =Калькуляция!E19 -> 9500.6294 | C19: 59 | D19: 0.4 | E19: =B19*D19 -> 3800.2518 | F19: =1.9*C19 -> 112.1 | G19: 20 | H19: 25 | I19: 15 | J19: =Логистика!B6+(Логистика!B6*0.15) -> 1668.65 | K19: =B19*0.01 -> 95.006294
A20: СМ 50-Э | B20: =Калькуляция!E20 -> 10543.567 | C20: 59 | D20: 0.4 | E20: =B20*D20 -> 4217.427 | F20: =1.9*C20 -> 112.1 | G20: 20 | H20: 25 | I20: 15 | J20: =Логистика!B7+(Логистика!B7*0.15) -> 1668.65 | K20: =B20*0.01 -> 105.43567
A21: Стеллаж металлический200*100*40 4п | B21: =Калькуляция!E21 -> 7814.1939 | C21: 44 | D21: 0.34 | E21: =B21*D21 -> 2656.8259 | F21: =1.9*C21 -> 83.6 | G21: 20 | H21: 25 | I21: 15 | J21: =Логистика!B27+(Логистика!B27*0.15) -> 1265 | K21: =B21*0.01 -> 78.141939
A22: Стеллаж металлический200*100*40 6п | B22: =Калькуляция!E22 -> 9152.8146 | C22: 65 | D22: 0.34 | E22: =B22*D22 -> 3111.957 | F22: =1.9*C22 -> 123.5 | G22: 20 | H22: 25 | I22: 15 | J22: =Логистика!B17+(Логистика!B17*0.15) -> 1830.8 | K22: =B22*0.01 -> 91.528146
A23: Стеллаж металлический200*100*50 4п | B23: =Калькуляция!E23 -> 9768.511 | C23: 55 | D23: 0.34 | E23: =B23*D23 -> 3321.2937 | F23: =1.9*C23 -> 104.5 | G23: 20 | H23: 25 | I23: 15 | J23: =Логистика!B26+(Логистика!B26*0.15) -> 1561.7 | K23: =B23*0.01 -> 97.68511
A24: ШБС 01-МИНИ | B24: =Калькуляция!E24 -> 9149.4402 | C24: 64 | D24: 0.4 | E24: =B24*D24 -> 3659.7761 | F24: =1.9*C24 -> 121.6 | G24: 20 | H24: 25 | I24: 15 | J24: =Логистика!B16+(Логистика!B16*0.15) -> 1803.2 | K24: =B24*0.01 -> 91.494402
A25: ШБС 01-МИНИ-Т | B25: =Калькуляция!E25 -> 9608.4492 | C25: 62 | D25: 0.4 | E25: =B25*D25 -> 3843.3797 | F25: =1.9*C25 -> 117.8 | G25: 20 | H25: 25 | I25: 15 | J25: =Логистика!B15+(Логистика!B15*0.15) -> 1749.15 | K25: =B25*0.01 -> 96.084492
A26: Шкаф бухгалтерский ШБС-01-17 | B26: =Калькуляция!E26 -> 31197.987 | C26: 348 | D26: 0.4 | E26: =B26*D26 -> 12479.195 | F26: =1.9*C26 -> 661.2 | G26: 20 | H26: 25 | I26: 15 | J26: =Логистика!B2+(Логистика!B2*0.15) -> 6281.3 | K26: =B26*0.01 -> 311.97987
A27: Шкаф бухгалтерский ШБС-02-17 | B27: =Калькуляция!E27 -> 33611.28 | C27: 348 | D27: 0.4 | E27: =B27*D27 -> 13444.512 | F27: =1.9*C27 -> 661.2 | G27: 20 | H27: 25 | I27: 15 | J27: =Логистика!B3+(Логистика!B3*0.15) -> 6281.3 | K27: =B27*0.01 -> 336.1128
A28: Стеллаж металлический СТ-СПЭ 4(4) | B28: =Калькуляция!E28 -> 7080.6951 | C28: 44 | D28: 0.4 | E28: =B28*D28 -> 2832.278 | F28: =1.9*C28 -> 83.6 | G28: 20 | H28: 25 | I28: 15 | J28: =Логистика!B4+(Логистика!B4*0.15) -> 1077.55 | K28: =B28*0.01 -> 70.806951
A29: Стеллаж металлический СТ-СПЭ 4(6) | B29: =Калькуляция!E29 -> 8426.4492 | C29: 65 | D29: 0.4 | E29: =B29*D29 -> 3370.5797 | F29: =1.9*C29 -> 123.5 | G29: 20 | H29: 25 | I29: 15 | J29: =Логистика!B5+(Логистика!B5*0.15) -> 1077.55 | K29: =B29*0.01 -> 84.264492
A30: Стеллаж металлический СТ-СПЭ 5(4) | B30: =Калькуляция!E30 -> 8920.6157 | C30: 55 | D30: 0.4 | E30: =B30*D30 -> 3568.2463 | F30: =1.9*C30 -> 104.5 | G30: 20 | H30: 25 | I30: 15 | J30: =Логистика!B6+(Логистика!B6*0.15) -> 1668.65 | K30: =B30*0.01 -> 89.206157
A31: ШО-5 | B31: =Калькуляция!E31 -> 42907.582 | C31: 348 | D31: 0.45 | E31: =B31*D31 -> 19308.412 | F31: =1.9*C31 -> 661.2 | G31: 20 | H31: 25 | I31: 15 | J31: =SUM(Логистика!B28:C28) -> 6281.3 | K31: =B31*0.01 -> 429.07582
A32: ШО-1 | B32: =Калькуляция!E32 -> 18800.428 | C32: 65 | D32: 0.45 | E32: =B32*D32 -> 8460.1928 | F32: =1.9*C32 -> 123.5 | G32: 20 | H32: 25 | I32: 15 | J32: =SUM(Логистика!B29:C29) -> 1830.8 | K32: =B32*0.01 -> 188.00428
A33: ШО-2 | B33: =Калькуляция!E33 -> 12341.182 | C33: 42 | D33: 0.45 | E33: =B33*D33 -> 5553.5318 | F33: =1.9*C33 -> 79.8 | G33: 20 | H33: 25 | I33: 15 | J33: =SUM(Логистика!B30:C30) -> 1212.1 | K33: =B33*0.01 -> 123.41182
A34: ШО-3 | B34: =Калькуляция!E34 -> 12087.791 | C34: 37 | D34: 0.45 | E34: =B34*D34 -> 5439.5061 | F34: =1.9*C34 -> 70.3 | G34: 20 | H34: 25 | I34: 15 | J34: =SUM(Логистика!B31:C31) -> 1077.55 | K34: =B34*0.01 -> 120.87791
A35: ШО-4 | B35: =Калькуляция!E35 -> 22478.051 | C35: 88 | D35: 0.45 | E35: =B35*D35 -> 10115.123 | F35: =1.9*C35 -> 167.2 | G35: 20 | H35: 25 | I35: 15 | J35: =SUM(Логистика!B32:C32) -> 2448.35 | K35: =B35*0.01 -> 224.78051

Sheet Логистика
A1: Товар | B1: цена | C1: возврат 15% залож
A2: ШБС 01-17 | B2: 5462 | C2: =0.15*B2 -> 819.3
A3: ШБС 02-17 | B3: 5462 | C3: =0.15*B3 -> 819.3
A4: СМ 30 | B4: 937 | C4: =0.15*B4 -> 140.55
A5: СМ 30-Э | B5: 937 | C5: =0.15*B5 -> 140.55
A6: СМ 50 | B6: 1451 | C6: =0.15*B6 -> 217.65
A7: СМ 50-Э | B7: 1451 | C7: =0.15*B7 -> 217.65
A8: СМ 25 | B8: 633 | C8: =0.15*B8 -> 94.95
A9: СМ 25-Э | B9: 633 | C9: =0.15*B9 -> 94.95
A10: СМ 23-Э | B10: 866 | C10: =0.15*B10 -> 129.9
A11: СМ 23 | B11: 890 | C11: =0.15*B11 -> 133.5
A12: СМ 20 | B12: 399 | C12: =0.15*B12 -> 59.85
A13: СМ 20-Э | B13: 399 | C13: =0.15*B13 -> 59.85
... A28: ШО-5 | B28: 5462 | C28: =0.15*B28 -> 819.3
A29: ШО-1 | B29: =B17 -> 1592 | C29: =0.15*B29 -> 238.8
A30: ШО-2 | B30: 1054 | C30: =0.15*B30 -> 158.1
A31: ШО-3 | B31: 937 | C31: =0.15*B31 -> 140.55
A32: ШО-4 | B32: 2129 | C32: =0.15*B32 -> 319.35
A33: Объём отгрузки* | B33: Тариф на литр отгрузки | D33: Тип точки отгрузки | E33: Тариф за отправление | G33: ДОСТАВКА ДО ПВЗ | K33: Обработка возврата | M33: Обратная логистика
A34: до 1000 л | B34: 1,9 ₽ | D34: ПВЗ/ППЗ | E34: 30 ₽ | G34: до 25р | K34: 15р за товар | M34: Тариф на обратную логистику равен тарифу на логистику
A35: от 1000 до 4000 л | B35: 1,7 ₽ | D35: СЦ | E35: 20 ₽
A36: от 4000 до 16 000 л | B36: 1,5 ₽
A37: более 16 000 л | B37: 1,3 ₽

Sheet Коэффиценты
A1: Кластер отправки/Кластер доставки | B1: Дальний Восток | C1: Калининград | D1: Санкт-Петербург и СЗО | E1: Воронеж | F1: Москва, МО и Дальние регионы | G1: Уфа | H1: Казань | I1: Самара | J1: Красноярск | K1: Тюмень | L1: Невинномысск | M1: Махачкала | N1: Саратов | O1: Ярославль | P1: Краснодар | Q1: Екатеринбург | R1: Новосибирск | S1: Омск | T1: Оренбург | U1: Пермь | V1: Ростов | W1: Тверь
A2: Беларусь | B2: 2.7 | C2: 1.3 | D2: 1.3 | E2: 1.3 | F2: 1 | G2: 1.4 | H2: 1.3 | I2: 1.4 | J2: 1.7 | K2: 1.7 | L2: 1.4 | M2: 1.4 | N2: 1.3 | O2: 1.1 | P2: 1.4 | Q2: 1.4 | R2: 1.7 | S2: 1.7 | T2: 1.4 | U2: 1.4 | V2: 1.4 | W2: 1
A3: Дальний Восток | B3: 1 | C3: 2.4 | D3: 2.7 | E3: 2.7 | F3: 2.7 | G3: 2.4 | H3: 2.4 | I3: 2.6 | J3: 1.7 | K3: 1.8 | L3: 2.8 | M3: 2.8 | N3: 2.6 | O3: 2.5 | P3: 2.8 | Q3: 2.4 | R3: 1.8 | S3: 1.8 | T3: 2.4 | U3: 2.4 | V3: 2.8 | W3: 2.7
A4: Астана | B4: 1.8 | C4: 1.7 | D4: 1.9 | E4: 1.8 | F4: 1.7 | G4: 1.4 | H4: 1.7 | I4: 1.6 | J4: 1.1 | K4: 1.1 | L4: 2 | M4: 2 | N4: 1.7 | O4: 1.7 | P4: 1.9 | Q4: 1.4 | R4: 1 | S4: 1 | T4: 1.4 | U4: 1.4 | V4: 1.9 | W4: 1.7
A5: Алматы | B5: 1.8 | C5: 1.7 | D5: 1.9 | E5: 1.8 | F5: 1.7 | G5: 1.4 | H5: 1.7 | I5: 1.6 | J5: 1.1 | K5: 1.1 | L5: 2 | M5: 2 | N5: 1.7 | O5: 1.7 | P5: 1.9 | Q5: 1.4 | R5: 1 | S5: 1 | T5: 1.4 | U5: 1.4 | V5: 1.9 | W5: 1.7
A6: Калининград | B6: 2.4 | C6: 1 | D6: 1.1 | E6: 1.6 | F6: 1.3 | G6: 1.8 | H6: 1.7 | I6: 1.7 | J6: 1.7 | K6: 1.6 | L6: 1.8 | M6: 1.8 | N6: 1.7 | O6: 1.4 | P6: 1.8 | Q6: 1.8 | R6: 1.7 | S6: 1.7 | T6: 1.8 | U6: 1.8 | V6: 1.8 | W6: 1.3
A7: Санкт-Петербург и СЗО | B7: 2.7 | C7: 1.1 | D7: 1 | E7: 1.5 | F7: 1.3 | G7: 1.7 | H7: 1.5 | I7: 1.5 | J7: 1.9 | K7: 1.9 | L7: 1.6 | M7: 1.6 | N7: 1.5 | O7: 1.3 | P7: 1.5 | Q7: 1.7 | R7: 1.9 | S7: 1.9 | T7: 1.7 | U7: 1.7 | V7: 1.5 | W7: 1.3
A8: Армения | B8: 1.8 | C8: 1.7 | D8: 1.9 | E8: 1.8 | F8: 1.7 | G8: 1.4 | H8: 1.7 | I8: 1.6 | J8: 1.1 | K8: 1.1 | L8: 2 | M8: 2 | N8: 1.7 | O8: 1.7 | P8: 1.9 | Q8: 1.4 | R8: 1 | S8: 1 | T8: 1.4 | U8: 1.4 | V8: 1.9 | W8: 1.7
A9: Воронеж | B9: 2.7 | C9: 1.6 | D9: 1.5 | E9: 1 | F9: 1.3 | G9: 1.5 | H9: 1.4 | I9: 1.3 | J9: 1.9 | K9: 1.9 | L9: 1.1 | M9: 1.1 | N9: 1.3 | O9: 1.3 | P9: 1.1 | Q9: 1.5 | R9: 1.8 | S9: 1.8 | T9: 1.5 | U9: 1.5 | V9: 1.1 | W9: 1.3
A10: Москва, МО и Дальние регионы | B10: 2.7 | C10: 1.3 | D10: 1.3 | E10: 1.3 | F10: 1 | G10: 1.4 | H10: 1.3 | I10: 1.4 | J10: 1.7 | K10: 1.7 | L10: 1.4 | M10: 1.4 | N10: 1.3 | O10: 1.1 | P10: 1.4 | Q10: 1.4 | R10: 1.7 | S10: 1.7 | T10: 1.4 | U10: 1.4 | V10: 1.4 | W10: 1
A11: Уфа | B11: 2.4 | C11: 1.8 | D11: 1.7 | E11: 1.5 | F11: 1.4 | G11: 1 | H11: 1.2 | I11: 1.2 | J11: 1.4 | K11: 1.4 | L11: 1.8 | M11: 1.8 | N11: 1.3 | O11: 1.5 | P11: 1.6 | Q11: 1.1 | R11: 1.4 | S11: 1.4 | T11: 1 | U11: 1.1 | V11: 1.6 | W11: 1.4
A12: Казань | B12: 2.4 | C12: 1.7 | D12: 1.5 | E12: 1.4 | F12: 1.3 | G12: 1.2 | H12: 1 | I12: 1.1 | J12: 1.7 | K12: 1.7 | L12: 1.6 | M12: 1.6 | N12: 1.1 | O12: 1.3 | P12: 1.6 | Q12: 1.3 | R12: 1.7 | S12: 1.7 | T12: 1.2 | U12: 1.3 | V12: 1.6 | W12: 1.3
A13: Самара | B13: 2.6 | C13: 1.7 | D13: 1.5 | E13: 1.3 | F13: 1.4 | G13: 1.2 | H13: 1.1 | I13: 1 | J13: 1.6 | K13: 1.6 | L13: 1.5 | M13: 1.5 | N13: 1.1 | O13: 1.4 | P13: 1.5 | Q13: 1.2 | R13: 1.6 | S13: 1.6 | T13: 1.2 | U13: 1.2 | V13: 1.5 | W13: 1.4
... A27: Тверь | B27: 2.7 | C27: 1.3 | D27: 1.3 | E27: 1.3 | F27: 1 | G27: 1.4 | H27: 1.3 | I27: 1.4 | J27: 1.7 | K27: 1.7 | L27: 1.4 | M27: 1.4 | N27: 1.3 | O27: 1.1 | P27: 1.4 | Q27: 1.4 | R27: 1.7 | S27: 1.7 | T27: 1.4 | U27: 1.4 | V27: 1.4 | W27: 1

Sheet Вознаграждение МП
B1: Категория | C1: Тип товара | D1: FBO свыше 1500 руб. | E1: FBS свыше 300 руб.
A2: ШБС 01-17 | B2: Сейфы и архивные шкафы | C2: Шкаф архивный | D2: 0.38 | E2: 0.4
A3: ШБС 01-17 | B3: Сейфы и архивные шкафы | C3: Сейф | D3: 0.38 | E3: 0.4
A4: СМ 30 | B4: Сейфы и архивные шкафы | C4: Сейф | D4: 0.38 | E4: 0.4
A5: СМ 30-Э | B5: Сейфы и архивные шкафы | C5: Сейф | D5: 0.38 | E5: 0.4
A6: СМ 50 | B6: Сейфы и архивные шкафы | C6: Сейф | D6: 0.38 | E6: 0.4
A7: СМ 50-Э | B7: Сейфы и архивные шкафы | C7: Сейф | D7: 0.38 | E7: 0.4
A8: СМ 25 | B8: Сейфы и архивные шкафы | C8: Сейф | D8: 0.38 | E8: 0.4
A9: СМ 25-Э | B9: Сейфы и архивные шкафы | C9: Сейф | D9: 0.38 | E9: 0.4
A10: СМ 23-Э | B10: Сейфы и архивные шкафы | C10: Сейф | D10: 0.38 | E10: 0.4
A11: СМ 23 | B11: Сейфы и архивные шкафы | C11: Сейф | D11: 0.38 | E11: 0.4
A12: СМ 20 | B12: Сейфы и архивные шкафы | C12: Сейф | D12: 0.38 | E12: 0.4
A13: СМ 20-Э | B13: Сейфы и архивные шкафы | C13: Сейф | D13: 0.38 | E13: 0.4
... A27: 200*100*40 4п | B27: Полки и стеллажи | C27: Стеллаж | D27: 0.32 | E27: 0.34

Sheet Прайс СТЕЛЛАЖИ
A2: Ozon
A3: Церера-Мебель | E3: ПРАКТИК | I3: ПАКС-Металл (РегионМебель, GetMet) | M3: ПРАКТИК GetMet г. Москва | Q3: Мебель для бизнеса и дома г. Ростов-на-Дону | U3: Стальной Мир г. Москва
A4: Название позиции | B4: Стоимость без Ozon Карты (без акций) | C4: Нагрузка на полку | D4: Ср. знач | E4: Название позиции | F4: Стоимость без Ozon Карты (без акций) | G4: Нагрузка на полку | H4: Разница | I4: Название позиции | J4: Стоимость без Ozon Карты (без акций) | K4: Нагрузка на полку | L4: Разница | M4: Название позиции | N4: Стоимость без Ozon Карты | O4: Нагрузка на полку | P4: Разница | Q4: Название позиции | R4: Стоимость без Ozon Карты | S4: Нагрузка на полку | T4: Разница | U4: Название позиции | V4: Стоимость без Ozon Карты | W4: Нагрузка на полку | X4: Разница
A5: Церера-Мебель Стеллаж, 100х40х200 см, 4 п. арт. 258467589 5 358 | B5: 5998 | C5: 150 | D5: =AVERAGE((B5-F5)/F5, (B5-J5)/J5, (B5-N5)/N5, (B5-R5)/R5, (B5-V5)/V5) -> -0.084637676 | E5: Металлический стеллаж Практик 195х100х40 см, 4 полки, серый. арт. 278493974 | F5: 5802 | G5: 100 | H5: =(F5-B5)/B5*100% -> -0.032677559 | I5: Стеллаж металлический "МС-244Р" (2000х1000х400мм) (4 полки) (до 150кг на полку, до 750кг на стеллаж) арт. 239506639 | J5: 8047 | K5: 150 | L5: =(J5-B5)/B5*100% -> 0.34161387 | M5: Стеллаж металлический усиленный MS Strong 2000x1000x400/4 полки арт. 1591399154 | N5: 6770 | O5: 140 | P5: =(N5-B5)/B5*100% -> 0.12870957 | Q5: Мебель для бизнеса и дома Стеллаж, 100х40х200 см арт. 256777948 | R5: 7103 | S5: 100 | T5: =(R5-B5)/B5*100% -> 0.18422808 | U5: Стеллаж металлический 195х100х40 см, 4 полки арт. 976570526 | V5: 5620 | W5: 100 | X5: =(V5-B5)/B5*100% -> -0.063021007
A6: Церера-Мебель Стеллаж, 100х50х200 см, 4 п. арт. 258473499 6 050 | B6: 6791 | C6: 150 | D6: =AVERAGE((B6-F6)/F6, (B6-J6)/J6, (B6-N6)/N6, (B6-R6)/R6, (B6-V6)/V6) -> -0.046914241 | E6: Металлический стеллаж Практик 195х100х50 см, 4 полки, серый. арт. 523544010 | F6: 5802 | G6: 100 | H6: =(F6-B6)/B6*100% -> -0.14563393 | I6: Стеллаж металлический "МС-254Р" (2000х1000х500мм) (4 полки) (до 150кг на полку, до 750кг на стеллаж) арт. 240961480 | J6: 9071 | K6: 150 | L6: =(J6-B6)/B6*100% -> 0.33573848 | M6: Стеллаж металлический усиленный MS Strong 2000x1000x500/4 арт. 1591399164 | N6: 7310 | O6: 140 | P6: =(N6-B6)/B6*100% -> 0.07642468 | Q6: Мебель для бизнеса и дома Стеллаж, 100х50х200 см арт. 256132554 | R6: 7822 | S6: 100 | T6: =(R6-B6)/B6*100% -> 0.15181858 | U6: Стеллаж металлический 195х100х50 см, 4 полки арт. 1058271817 | V6: 6473 | W6: 100 | X6: =(V6-B6)/B6*100% -> -0.046826682
A7: Церера-Мебель Стеллаж, 100х40х200 см, 6п. арт. 888213183 нов. 7 296 | B7: 8083 | C7: 150 | D7: =AVERAGE((B7-F7)/F7, (B7-J7)/J7, (B7-N7)/N7, (B7-R7)/R7, (B7-V7)/V7) -> -0.036507168 | E7: Металлический стеллаж Практик 195х100х40 см, 6 полок, серый. арт. 523544404 | F7: 8775 | G7: 100 | H7: =(F7-B7)/B7*100% -> 0.085611778 | I7: Металлический стеллаж МС-500 1800x1000x400/6 полок арт. 840928937 | J7: 7844 | K7: 100 | L7: =(J7-B7)/B7*100% -> -0.02956823 | M7: Стеллаж металлический усиленный MS Strong 2000x1000x400/6 арт. 1595531063 | N7: 8601 | O7: 140 | P7: =(N7-B7)/B7*100% -> 0.064085117 | Q7: Мебель для бизнеса и дома Стеллаж, 100х40х200 см арт. 256132309 | R7: 9267 | S7: 100 | T7: =(R7-B7)/B7*100% -> 0.14648027 | U7: Стеллаж металлический 195х100х40 см, 6 полок арт. 1012266977 | V7: 7670 | W7: 100 | X7: =(V7-B7)/B7*100% -> -0.051094891

Sheet Прайс ЯП
A2: Ozon
A3: Церера-Мебель | D3: Stalkersafe | G3: СТАЛЬНЫЕ РЕШЕНИЯ порядок во всем | J3: Пакс-Металл
A4: Название позиции | B4: Стоимость без Ozon Карты | C4: Ср. значение | D4: Название позиции | E4: Стоимость без Ozon Карты | F4: Разница | G4: Название позиции | H4: Стоимость без Ozon Карты | I4: Разница | J4: Название позиции | K4: Стоимость без Ozon Карты | L4: Разница
A5: Церера-Мебель Почтовый ящик 4 секц. 474 мм x 377 мм x 190 мм, светло-серый арт. 632063202 | B5: 3630 | C5: =AVERAGE((B5-E5)/E5, (B5-H5)/H5, (B5-K5)/K5) -> 0.17714307 | D5: Почтовый ящик СПР-4 на 4 секции, размер 542x383x186 мм., светло-серый 2371633866 | E5: 2924 | F5: =(E5-B5)/B5*100% -> -0.19449036 | G5: Почтовый ящик "Оптима люкс" на 4 секции с задней стенкой 515x140 1644899208 | H5: 2666 | I5: =(H5-B5)/B5*100% -> -0.26556474 | J5: ПАКС-металл Почтовый ящик 4 секц. 500 мм x 385 мм x 195 мм, серый 594991331 | K5: 3910 | L5: =(K5-B5)/B5*100% -> 0.077134986
A6: Церера-Мебель Почтовый ящик 5 секц. 559 мм x 377 мм x 190 мм, светло-серый арт. 631939684 | B6: 4219 | C6: =AVERAGE((B6-E6)/E6,(B6-H6)/H6) -> 0.016380611 | D6: Почтовый ящик СПР-5 на 5 секции, размер 642x383x186 мм., светло-серый с задней стенкой 2371723244 | E6: 5700 | F6: =(E6-B6)/B6*100% -> 0.35103105 | G6: ОПТИМА ЛЮКС почтовый ящик на 5 секций, с задней стенкой 610x140 1673111906 | H6: 3264 | I6: =(H6-B6)/B6*100% -> -0.22635696
A7: Церера-Мебель Почтовый ящик 6 секц. 643 мм x 377 мм x 190 мм, светло-серый арт. 631949713 | B7: 4534 | C7: =AVERAGE((B7-H7)/H7) -> 0.16525315 | D7: Почтовый ящик СПРУ-6 на 6 секции, размер 742x383x96 мм., светло-серый, замки в комплекте 1916745096 | G7: ОПТИМА ЛЮКС почтовый ящик на 6 секций, с задней стенкой. 1655540120 | H7: 3891 | I7: =(H7-B7)/B7*100% -> -0.14181738
A8: Церера-Мебель Почтовый ящик 8 секц. 812 мм x 377 мм x 190 мм, светло-серый арт. 631946118 | B8: 6344 | C8: =AVERAGE((B8-E8)/E8, (B8-K8)/K8) -> -0.042535085 | D8: Почтовый ящик СПРУ-8 на 8 секции, размер 942x383x96 мм., светло-серый, замки в комплекте 1916745227 | E8: 5527 | F8: =(E8-B8)/B8*100% -> -0.1287831 | G8: ОПТИМА ЛЮКС почтовый ящик на 7 секций, с задней стенкой. 800 мм x 340 мм x 140 мм, светло-серый | J8: ПАКС-металл Почтовый ящик 8 секц. 860 мм x 385 мм x 195 мм, серый 595007368 | K8: 8270 | L8: =(K8-B8)/B8*100% -> 0.30359395

Sheet Прайс КЛЮЧНИЦЫ
A1: Церера-Мебель | D1: ЗАВОД РУБИН | G1: ГИПЕРМАРКЕТ СЕЙФОВ AIKO | J1: Altezza Trade АНКОНА
A2: Название позиции | B2: Стоимость без Ozon Карты | C2: Ср. знач | D2: Название позиции | E2: Стоимость без Ozon Карты | F2: Разница | G2: Название позиции | H2: Стоимость без Ozon Карты | I2: Разница | J2: Название позиции | K2: Стоимость без Ozon Карты | L2: Разница
A3: Церера-Мебель Ключница настенная с 20 крюч., 1 шт | B3: 1195 | C3: =AVERAGE((B3-E3)/E3, (B3-H3)/H3, (B3-K3)/K3) -> -0.37675409 | D3: Ключница настенная металлическая КЛ 20 с брелками 573445457 | E3: 1235 | F3: =(E3-B3)/B3*100% -> 0.033472803 | G3: Шкаф для ключей (ключница) Aiko KEY-20 644365412 | H3: 2356 | I3: =(H3-B3)/B3*100% -> 0.97154812 | J3: Металлическая ключница КЛ-20 / комплект с 20 брелками 1249246622 | K3: 3026 | L3: =(K3-B3)/B3*100% -> 1.5322176
A4: Церера-Мебель Ключница настенная с 40 крюч., 1 шт | B4: 2308 | C4: =AVERAGE((B4-E4)/E4, (B4-H4)/H4, (B4-K4)/K4) -> -0.096462942 | D4: Ключница настенная металлическая КЛ 40 с брелками 576980267 | E4: 1835 | F4: =(E4-B4)/B4*100% -> -0.20493934 | G4: Шкаф для ключей (ключница) Aiko KEY-40 644344940 | H4: 3037 | I4: =(H4-B4)/B4*100% -> 0.31585789 | J4: Металлическая ключница КЛ-40 / комплект с брелками 653924752 | K4: 3331 | L4: =(K4-B4)/B4*100% -> 0.4432409
A5: Церера-Мебель Ключница настенная с 60 крюч., 1 шт | B5: 2679 | C5: =AVERAGE((B5-E5)/E5, (B5-H5)/H5, (B5-K5)/K5) -> -0.21703965 | D5: Ключница настенная металлическая КЛ 60 с брелками 576978763 | E5: 2618 | F5: =(E5-B5)/B5*100% -> -0.02276969 | G5: Шкаф для ключей (ключница) Aiko KEY-60 644333958 | H5: 3765 | I5: =(H5-B5)/B5*100% -> 0.40537514 | J5: Металлическая ключница КЛ-60 / комплект 60 брелками 653028565 | K5: 4363 | L5: =(K5-B5)/B5*100% -> 0.62859276
A6: Церера-Мебель Ключница настенная с 148 крюч., 1 шт | B6: 4158 | C6: =AVERAGE((B6-E6)/E6, (B6-H6)/H6, (B6-K6)/K6) -> -0.19360877 | D6: Ключница настенная металлическая КЛ 100 с брелками 576979649 | E6: 4042 | F6: =(E6-B6)/B6*100% -> -0.027898028 | G6: Шкаф для ключей (ключница) Aiko KEY-100 644336558 | H6: 5800 | I6: =(H6-B6)/B6*100% -> 0.39490139 | J6: Металлическая ключница КЛ-100 / комплект с брелками 728824973 | K6: 6173 | L6: =(K6-B6)/B6*100% -> 0.48460798

Sheet Прайс СЕЙФЫ ШБС
A2: Ozon
A3: Церера-Мебель | G3: РегионМебель | J3: ООО Передовые технологии
A4: Название позиции | B4: Стоимость без Ozon Карты | C4: Ср. знач | D4: Название позиции | E4: Стоимость без Ozon Карты | F4: Разница | G4: Название позиции | H4: Стоимость без Ozon Карты | I4: Разница | J4: Название позиции | K4: Стоимость без Ozon Карты | L4: Разница
A5: Сейф ШБС-мини 445х365х355 | B5: 7544 | C5: =AVERAGE((B5-E5)/E5, (B5-H5)/H5, (B5-K5)/K5) -> -0.18128653 | D5: Шкаф бухгалтерский "SL-32" (320х420х350мм) 419063729 | E5: 7504 | F5: =(E5-B5)/B5*100% -> -0.0053022269 | G5: Шкаф бухгалтерский "КБС 02" (320х420х350мм) (Ключевой замок) 356528667 | H5: 14523 | I5: =(H5-B5)/B5*100% -> 0.92510604 | J5: Бухгалтерский шкаф-сейф AIKO SL-32 (320x460x340). 1765228214 | K5: 8100 | L5: =(K5-B5)/B5*100% -> 0.073700954
A6: Сейф ШБС-мини Т 440х360х350 | B6: 7818 | C6: =AVERAGE((B6-E6)/E6, (B6-H6)/H6, (B6-K6)/K6) -> -0.19665879 | D6: Шкаф бухгалтерский "SL-32T" (с трейзером) (320х420х350мм) (Ключевой замок) 661574766 | E6: 8052 | F6: =(E6-B6)/B6*100% -> 0.029930929 | G6: Шкаф бухгалтерский "КБС 02тн" (с трейзером) (320х420х350мм) (Ключевой замок) 356711210 | H6: 14783 | I6: =(H6-B6)/B6*100% -> 0.89089281 | J6: Шкаф сейф офисный Aiko SL 32T, шкаф бухгалтерский, металлический для хранения документов, с ключевым замком, ВхШхГ: 320х420х350 мм 419065187 | K6: 8589 | L6: =(K6-B6)/B6*100% -> 0.098618573

Sheet Прайс АПТЕЧКА
A2: Ozon
A3: Церера-Мебель | D3: Рубин | G3: Регион Мебель | J3: СТАЛЬНЫЕ РЕШЕНИЯ (FERRUMFORMAT)
A4: Название позиции | B4: Стоимость без Ozon Карты | C4: Ср. знач | D4: Название позиции | E4: Стоимость без Ozon Карты | F4: Разница | G4: Название позиции | H4: Стоимость без Ozon Карты | I4: Разница | J4: Название позиции | K4: Стоимость без Ozon Карты | L4: Разница
A5: Аптечка для медикаментов металлическая, ЦЕРЕРА | B5: 2079 | C5: =AVERAGE((B5-E5)/E5,(B5-H5)/H5,(B5-K5)/K5) -> -0.027136865 | D5: Аптечка металлическая с замком 1586082268 | E5: 1696 | F5: =(E5-B5)/B5*100% -> -0.18422318 | G5: Аптечка металлическая настенная АМ-1 для медикаментов 1389063816 | H5: 3035 | I5: =(H5-B5)/B5*100% -> 0.45983646 | J5: Аптечка настенная металлическая с замком, 4 полки. Размер 320*300*140мм 1662685252 | K5: 2063 | L5: =(K5-B5)/B5*100% -> -0.0076960077

Sheet Прайс СЕЙФЫ СМ
A2: Ozon
A3: Церера-Мебель | D3: Меткон (Юнион Сейф Плюс) | G3: Klesto | J3: МеталлСити26
A4: Название позиции | B4: Стоимость без Ozon Карты | C4: Ср. знач | D4: Название позиции | E4: Стоимость без Ozon Карты | F4: Разница | G4: Название позиции | H4: Стоимость без Ozon Карты | I4: Разница | J4: Название позиции | K4: Стоимость без Ozon Карты | L4: Разница
A5: Сейф СМ-20 200х310х200 | B5: 4100 | C5: =AVERAGE((B5-E5)/E5,(B5-H5)/H5,(B5-K5)/K5) -> -0.17038431 | D5: Шкаф мебельный Меткон ШМ-20, В.Ш.Г. 200х310х200 1508446739 | E5: 4545 | F5: =(E5-B5)/B5*100% -> 0.10853659 | G5: Сейф маленький мебельный для денег Klesto 20K, ключевой замок, Ш31хВ20хГ20 см 230701350 | H5: 6234 | I5: =(H5-B5)/B5*100% -> 0.5204878 | J5: Сейф ШМ-20 621080165 | K5: 4413 | L5: =(K5-B5)/B5*100% -> 0.076341463
A6: Сейф СМ-20Э 200х310х200 | B6: 5800 | C6: =AVERAGE((B6-E6)/E6,(B6-H6)/H6,(B6-K6)/K6) -> -0.17114418 | D6: Шкаф мебельный Меткон ШМ-20Э, В.Ш.Г. 200х310х200 1508447850 | E6: 6928 | F6: =(E6-B6)/B6*100% -> 0.19448276 | G6: Сейф маленький мебельный для денег Klesto 20E, кодовой замок, Ш31хВ20хГ20 см 230700112 | H6: 8859 | I6: =(H6-B6)/B6*100% -> 0.52741379 | J6: Сейф ШМ20 Эл 621224521 | K6: 5831 | L6: =(K6-B6)/B6*100% -> 0.0053448276
A7: Сейф СМ-23 229х405х335 | B7: 5600 | C7: =AVERAGE((B7-E7)/E7) -> -0.29710054 | D7: Шкаф мебельный Меткон ШМ-23, В.Ш.Г. 230х406х335 1508446734 | E7: 7967 | F7: =(E7-B7)/B7*100% -> 0.42267857
A8: Сейф СМ-23Э 229х405х335 | B8: 7700 | C8: =AVERAGE((B8-E8)/E8) -> -0.026548673 | D8: Шкаф мебельный Меткон ШМ-23Э, В.Ш.Г. 229х405х335 1508446601 | E8: 7910 | F8: =(E8-B8)/B8*100% -> 0.027272727
A9: Сейф СМ-25 250х350х250 | B9: 5100 | C9: =AVERAGE((B9-E9)/E9,(B9-H9)/H9,(B9-K9)/K9) -> -0.14865874 | D9: Шкаф мебельный Меткон ШМ-25, В.Ш.Г. 250х350х250 1508446474 | E9: 5474 | F9: =(E9-B9)/B9*100% -> 0.073333333 | G9: Сейф маленький мебельный для денег Klesto 25K, ключевой замок, Ш35хВ25хГ25 см 230822257 | H9: 7975 | I9: =(H9-B9)/B9*100% -> 0.56372549 | J9: Сейф ШМ 25 623399487 | K9: 5189 | L9: =(K9-B9)/B9*100% -> 0.01745098
A10: Сейфы СМ-25Э 250х350х250 | B10: 6600 | C10: =AVERAGE((B10-E10)/E10,(B10-H10)/H10) -> -0.31242687 | D10: Шкаф мебельный Меткон ШМ-25Э, В.Ш.Г. 250х350х250 1508448071 | E10: 8336 | F10: =(E10-B10)/B10*100% -> 0.2630303 | G10: Сейф маленький мебельный для денег Klesto 25E, кодовый замок, Ш35xВ25xГ25 см 230697386 | H10: 11313 | I10: =(H10-B10)/B10*100% -> 0.71409091 | J10: Сейф ШМ25 Эл
A11: Сейчас СМ-30 300х380х300 | B11: 6400 | C11: =AVERAGE((B11-E11)/E11,(B11-H11)/H11,(B11-K11)/K11) -> -0.34955592 | D11: Шкаф мебельный Меткон ШМ-30, В.Ш.Г. 300х380х300 1508447298 | E11: 7459 | F11: =(E11-B11)/B11*100% -> 0.16546875 | G11: Сейф мебельный Klesto 30TK с ключевым ящиком внутри, Ш38хВ30хГ30 см 230844016 | H11: 16125 | I11: =(H11-B11)/B11*100% -> 1.5195312 | J11: Сейф ШМ30 623396553 | K11: 9190 | L11: =(K11-B11)/B11*100% -> 0.4359375
A12: Сейф СМ-30Э 300х380х300 | B12: 8200 | C12: =AVERAGE((B12-E12)/E12,(B12-H12)/H12,(B12-K12)/K12) -> -0.27102335 | D12: Шкаф мебельный Меткон ШМ-30Э, В.Ш.Г. 300х380х300 1508447288 | E12: 9255 | F12: =(E12-B12)/B12*100% -> 0.12865854 | G12: Сейф мебельный для денег Klesto 30E, кодовый замок, Ш38хВ30хГ30 см 230697537 | H12: 14509 | I12: =(H12-B12)/B12*100% -> 0.76939024 | J12: Сейф ШМ30 эл 623428062 | K12: 11145 | L12: =(K12-B12)/B12*100% -> 0.35914634
A13: Сейф СМ-50 500х350х310 | B13: 8300 | C13: =AVERAGE((B13-E13)/E13,(B13-K13)/K13) -> -0.08649387 | D13: Шкаф мебельный Меткон ШМ-50, В.Ш.Г. 500х350х310 1508447236 | E13: 9923 | F13: =(E13-B13)/B13*100% -> 0.19554217 | J13: Сейф ШМ-50 181441952 | K13: 8379 | L13: =(K13-B13)/B13*100% -> 0.0095180723
A14: Сейф СМ-50Э 500х350х310 | B14: 9900 | C14: =AVERAGE((B14-E14)/E14,(B14-K14)/K14) -> -0.17265433 | D14: Шкаф мебельный Меткон ШМ-50Э, В.Ш.Г. 500х350х310 1508446736 | E14: 10497 | F14: =(E14-B14)/B14*100% -> 0.06030303 | J14: Сейф ШМ-50 Эл 181441970 | K14: 13913 | L14: =(K14-B14)/B14*100% -> 0.40535354

Sheet ВС-С.1400х22
F1: УТВЕРЖДАЮ
F2: генеральный директор
F3: ООО "Вика-Двина"
F4: В.А. Иванов _____________
B5: Калькуляция | F5: подпись
B6: ВС-С.1400х22
A8: № | B8: Наименование статьи затрат | C8: ед. изм. | D8: кол-во | E8: цена, руб. | F8: стоимость, руб. | G8: расход г/м2
B9: Лист 1,0 оцинк | C9: кг | D9: 9.4441686 | E9: 69.67 | F9: =D9*E9 -> 657.97522
B10: МДФ 22 1396х697 | C10: шт | D10: 1 | E10: 1896 | F10: =D10*E10 -> 1896
B11: Гайка врезная М6 | C11: шт | D11: 4 | E11: 1.65 | F11: =D11*E11 -> 6.6
B12: Всего на материалы без НДС | F12: =SUM(F9:F11) -> 2560.5752
B13: Наценка на материалы | E13: 0.01 | F13: =F12*E13 -> 25.605752
B14: Итого: | F14: =SUM(F12:F13) -> 2586.181
A15: 2 | B15: Основная з/п цеховых рабочих | E15: 0.14 | F15: =F14*E15 -> 362.06534
B16: Дополнительная з/п | E16: 0.14 | F16: =F15*E16 -> 50.689147
B17: Отчисления на социальные нужды | F17: =(F15+F16)*31.3% -> 129.19215
A18: 3 | B18: Общепроизводственные (накладные) расходы | E18: 1.5 | F18: =F15*E18 -> 543.09801
A19: 4 | B19: Цеховая себестоимость | F19: =F14+F15+F16+F17+F18 -> 3671.2256
A20: 5 | B20: Общехозяйственные расходы | E20: 1 | F20: =F15*E20 -> 362.06534
E21: 0.8 | F21: =F15*E21 -> 289.65227
A22: 6 | B22: СЕБЕСТОИМОСТЬ: | F22: =F19+F20 -> 4033.291
F23: =F19+F21 -> 3960.8779
A24: 7 | B24: Прибыль | E24: 0.4 | F24: =F22*E24 -> 1613.3164
E25: 0.07 | F25: =F23*E25 -> 277.26145
A26: 8 | B26: Расходы на упаковку | F26: 20
A27: 9 | B27: Цена без НДС | F27: =F22+F24+F26 -> 5666.6073
F28: =F23+F25+F26 -> 4258.1393
A29: 10 | B29: НДС | E29: 0.22 | F29: =F27*E29 -> 1246.6536
E30: 0.22 | F30: =F28*E30 -> 936.79066
A31: 11 | B31: ОТПУСКАЯ ЦЕНА | E31: розн | F31: =F27+F29 -> 6913.261
E32: опт | F32: =F28+F30 -> 5194.93
B36: Главный бухгалтер _________________

Sheet ВС-ПС.1400.0 Полка-стенка
F1: УТВЕРЖДАЮ
F2: генеральный директор
F3: ООО "Вика-Двина"
F4: В.А. Иванов _____________
B5: Калькуляция | F5: подпись
B6: ВС-ПС.1400.0 Полка-стенка
A8: № | B8: Наименование статьи затрат | C8: ед. изм. | D8: кол-во | E8: цена, руб. | F8: стоимость, руб. | G8: расход г/м2
B9: Рулон 0,9*1250 | C9: кг | D9: =8.843 -> 8.843 | E9: 61.48 | F9: =D9*E9 -> 543.66764
B10: Краска RAL 7035 | C10: кг | D10: =0.294 -> 0.294 | E10: 208.95 | F10: =D10*E10 -> 61.4313 | G10: 0.133
B11: Площадь (Химия ) | C11: м2 | D11: =2.21 -> 2.21 | E11: 0.52 | F11: =D11*E11*G11 -> 5.746 | G11: 5
B12: Болт М6х12 | C12: шт | D12: =8 -> 8 | E12: 0.91 | F12: =D12*E12 -> 7.28
B13: Гайка М6 ГОСТ 5927-70 | C13: шт | D13: 8 | E13: 0.46 | F13: =D13*E13 -> 3.68
B14: Шайба А.6. ГОСТ 11371-78 | C14: шт | D14: 8 | E14: 0.16 | F14: =D14*E14 -> 1.28
B15: Всего на материалы без НДС | F15: =SUM(F9:F14) -> 623.08494
B16: Наценка на материалы | E16: 0.01 | F16: =F15*E16 -> 6.2308494
B17: Итого: | F17: =SUM(F15:F16) -> 629.31579
A18: 2 | B18: Основная з/п цеховых рабочих | E18: 0.14 | F18: =F17*E18 -> 88.104211
B19: Дополнительная з/п | E19: 0.14 | F19: =F18*E19 -> 12.334589
B20: Отчисления на социальные нужды | F20: =(F18+F19)*30.9% -> 31.035589
A21: 3 | B21: Общепроизводственные (накладные) расходы | E21: 1.5 | F21: =F18*E21 -> 132.15632
A22: 4 | B22: Цеховая себестоимость | F22: =F17+F18+F19+F20+F21 -> 892.94649
A23: 5 | B23: Общехозяйственные расходы | E23: 1 | F23: =F18*E23 -> 88.104211
E24: 0.8 | F24: =F18*E24 -> 70.483368
A25: 6 | B25: СЕБЕСТОИМОСТЬ: | F25: =F22+F23 -> 981.0507
F26: =F22+F24 -> 963.42986
A27: 7 | B27: Прибыль | E27: 0.4 | F27: =F25*E27 -> 392.42028
E28: 0.07 | F28: =F26*E28 -> 67.44009
A29: 8 | B29: Расходы на упаковку | F29: 55
A30: 9 | B30: Цена без НДС | F30: =F25+F27+F29 -> 1428.471
F31: =F26+F28+F29 -> 1085.87
A32: 10 | B32: НДС | E32: 0.22 | F32: =F30*E32 -> 314.26362
E33: 0.22 | F33: =F31*E33 -> 238.89139
A34: 11 | B34: ОТПУСКАЯ ЦЕНА | E34: розн | F34: =F30+F32 -> 1742.7346
E35: опт | F35: =F31+F33 -> 1324.7613
B39: Главный бухгалтер _________________

Sheet ВС-О Опора
F1: УТВЕРЖДАЮ
F2: генеральный директор
F3: ООО "Вика-Двина"
F4: В.А. Иванов _____________
B5: Калькуляция | F5: подпись
B6: ВС-О Опора
A8: № | B8: Наименование статьи затрат | C8: ед. изм. | D8: кол-во | E8: цена, руб. | F8: стоимость, руб. | G8: расход г/м2
B9: Рулон 0,9*1250 | C9: кг | D9: 4.4017154 | E9: 61.48 | F9: =D9*E9 -> 270.61746
B10: Краска RAL 7035 | C10: кг | D10: 0.13837107 | E10: 208.95 | F10: =D10*E10 -> 28.912635 | G10: 0.133
B11: Площадь (Химия ) | C11: м2 | D11: 1.040384 | E11: 0.52 | F11: =D11*E11*G11 -> 2.7049984 | G11: 5
B12: Саморезы 4,2*13 пресс-шайба острый | C12: шт. | D12: 2 | E12: 0.3 | F12: =D12*E12 -> 0.6
B13: Гайка М6 оцинк. | C13: кг. | D13: 0.005 | E13: 179 | F13: =D13*E13 -> 0.895
B14: Болт 6*40 с полукруг. головкой и усом оц. | C14: кг. | D14: 0.019 | E14: 220 | F14: =D14*E14 -> 4.18
B15: Шайба 6 цинк DIN 125 | C15: кг. | D15: 0.002 | E15: 180 | F15: =D15*E15 -> 0.36
B16: Всего на материалы без НДС | F16: =SUM(F9:F15) -> 308.2701
B17: Наценка на материалы | E17: 0.01 | F17: =F16*E17 -> 3.082701
B18: Итого: | F18: =SUM(F16:F17) -> 311.3528
A19: 2 | B19: Основная з/п цеховых рабочих | E19: 0.14 | F19: =F18*E19 -> 43.589392
B20: Дополнительная з/п | E20: 0.14 | F20: =F19*E20 -> 6.1025149
B21: Отчисления на социальные нужды | F21: =(F19+F20)*31.3% -> 15.553567
A22: 3 | B22: Общепроизводственные (накладные) расходы | E22: 1.5 | F22: =F19*E22 -> 65.384088
A23: 4 | B23: Цеховая себестоимость | F23: =F18+F19+F20+F21+F22 -> 441.98236
A24: 5 | B24: Общехозяйственные расходы | E24: 1 | F24: =F19*E24 -> 43.589392
E25: 0.8 | F25: =F19*E25 -> 34.871514
A26: 6 | B26: СЕБЕСТОИМОСТЬ: | F26: =F23+F24 -> 485.57175
F27: =F23+F25 -> 476.85387
A28: 7 | B28: Прибыль | E28: 0.4 | F28: =F26*E28 -> 194.2287
E29: 0.07 | F29: =F27*E29 -> 33.379771
A30: 8 | B30: Расходы на упаковку | F30: 53 | H30: Прокладка 1850*280 | I30: шт | J30: 2
A31: 9 | B31: Цена без НДС | F31: =F26+F28+F30 -> 732.80045
F32: =F27+F29+F30 -> 563.23365
A33: 10 | B33: НДС | E33: 0.22 | F33: =F31*E33 -> 161.2161
E34: 0.22 | F34: =F32*E34 -> 123.9114
A35: 11 | B35: ОТПУСКАЯ ЦЕНА | E35: розн | F35: =F31+F33 -> 894.01655
E36: опт | F36: =F32+F34 -> 687.14505
B40: Главный бухгалтер _________________

Sheet ВС-ПС.1200.0 Полка-стенка
F1: УТВЕРЖДАЮ
F2: генеральный директор
F3: ООО "Вика-Двина"
F4: В.А. Иванов _____________
B5: Калькуляция | F5: подпись
B6: ВС-ПС.1200.0 Полка-стенка
A8: № | B8: Наименование статьи затрат | C8: ед. изм. | D8: кол-во | E8: цена, руб. | F8: стоимость, руб. | G8: расход г/м2
B9: Рулон 0,9*1250 | C9: кг | D9: 7.3102148 | E9: 61.48 | F9: =D9*E9 -> 449.43201
B10: Краска RAL 7035 | C10: кг | D10: 0.24256646 | E10: 208.95 | F10: =D10*E10 -> 50.684263 | G10: 0.133
B11: Площадь (Химия ) | C11: м2 | D11: 1.823808 | E11: 0.52 | F11: =D11*E11*G11 -> 4.7419008 | G11: 5
B12: Болт М6х12 | C12: шт | D12: =8 -> 8 | E12: 0.91 | F12: =D12*E12 -> 7.28
B13: Гайка М6 ГОСТ 5927-70 | C13: шт | D13: 8 | E13: 0.46 | F13: =D13*E13 -> 3.68
B14: Шайба А.6. ГОСТ 11371-78 | C14: шт | D14: 8 | E14: 0.16 | F14: =D14*E14 -> 1.28
B15: Всего на материалы без НДС | F15: =SUM(F9:F14) -> 517.09817
B16: Наценка на материалы | E16: 0.01 | F16: =F15*E16 -> 5.1709817
B17: Итого: | F17: =SUM(F15:F16) -> 522.26915
A18: 2 | B18: Основная з/п цеховых рабочих | E18: 0.14 | F18: =F17*E18 -> 73.117682
B19: Дополнительная з/п | E19: 0.14 | F19: =F18*E19 -> 10.236475
B20: Отчисления на социальные нужды | F20: =(F18+F19)*31.3% -> 26.089851
A21: 3 | B21: Общепроизводственные (накладные) расходы | E21: 1.5 | F21: =F18*E21 -> 109.67652
A22: 4 | B22: Цеховая себестоимость | F22: =F17+F18+F19+F20+F21 -> 741.38968
A23: 5 | B23: Общехозяйственные расходы | E23: 1 | F23: =F18*E23 -> 73.117682
E24: 0.8 | F24: =F18*E24 -> 58.494145
A25: 6 | B25: СЕБЕСТОИМОСТЬ: | F25: =F22+F23 -> 814.50737
F26: =F22+F24 -> 799.88383
A27: 7 | B27: Прибыль | E27: 0.4 | F27: =F25*E27 -> 325.80295
E28: 0.07 | F28: =F26*E28 -> 55.991868
A29: 8 | B29: Расходы на упаковку | F29: 10
A30: 9 | B30: Цена без НДС | F30: =F25+F27+F29 -> 1150.3103
F31: =F26+F28+F29 -> 865.8757
A32: 10 | B32: НДС | E32: 0.22 | F32: =F30*E32 -> 253.06827
E33: 0.22 | F33: =F31*E33 -> 190.49265
A34: 11 | B34: ОТПУСКАЯ ЦЕНА | E34: розн | F34: =F30+F32 -> 1403.3786
E35: опт | F35: =F31+F33 -> 1056.3684
B39: Главный бухгалтер _________________

Sheet ВС-С.1200х22
F1: УТВЕРЖДАЮ
F2: генеральный директор
F3: ООО "Вика-Двина"
F4: В.А. Иванов _____________
B5: Калькуляция | F5: подпись
B6: ВС-С.1200х22
A8: № | B8: Наименование статьи затрат | C8: ед. изм. | D8: кол-во | E8: цена, руб. | F8: стоимость, руб. | G8: расход г/м2
B9: Лист 1,0 оцинк | C9: кг | D9: 8.1627346 | E9: 69.67 | F9: =D9*E9 -> 568.69772
B10: МДФ 22 1196х697 | C10: шт | D10: 1 | E10: 1602 | F10: =D10*E10 -> 1602
B11: Гайка врезная М6 | C11: шт | D11: 4 | E11: 1.65 | F11: =D11*E11 -> 6.6
B12: Всего на материалы без НДС | F12: =SUM(F9:F11) -> 2177.2977
B13: Наценка на материалы | E13: 0.01 | F13: =F12*E13 -> 21.772977
B14: Итого: | F14: =SUM(F12:F13) -> 2199.0707
A15: 2 | B15: Основная з/п цеховых рабочих | E15: 0.14 | F15: =F14*E15 -> 307.8699
B16: Дополнительная з/п | E16: 0.14 | F16: =F15*E16 -> 43.101786
B17: Отчисления на социальные нужды | F17: =(F15+F16)*31.3% -> 109.85414
A18: 3 | B18: Общепроизводственные (накладные) расходы | E18: 1.5 | F18: =F15*E18 -> 461.80485
A19: 4 | B19: Цеховая себестоимость | F19: =F14+F15+F16+F17+F18 -> 3121.7014
A20: 5 | B20: Общехозяйственные расходы | E20: 1 | F20: =F15*E20 -> 307.8699
E21: 0.8 | F21: =F15*E21 -> 246.29592
A22: 6 | B22: СЕБЕСТОИМОСТЬ: | F22: =F19+F20 -> 3429.5713
F23: =F19+F21 -> 3367.9973
A24: 7 | B24: Прибыль | E24: 0.4 | F24: =F22*E24 -> 1371.8285
E25: 0.07 | F25: =F23*E25 -> 235.75981
A26: 8 | B26: Расходы на упаковку | F26: 20
A27: 9 | B27: Цена без НДС | F27: =F22+F24+F26 -> 4821.3998
F28: =F23+F25+F26 -> 3623.7571
A29: 10 | B29: НДС | E29: 0.22 | F29: =F27*E29 -> 1060.7079
E30: 0.22 | F30: =F28*E30 -> 797.22656
A31: 11 | B31: ОТПУСКАЯ ЦЕНА | E31: розн | F31: =F27+F29 -> 5882.1077
E32: опт | F32: =F28+F30 -> 4420.9836
B36: Главный бухгалтер _________________

Sheet 40(4) NEW
F1: УТВЕРЖДАЮ
F2: генеральный директор
F3: ООО "Вика-Двина"
F4: В.А. Иванов _________
A5: Калькуляция | F5: подпись
A7: Стеллаж металлический СТ-СПЭ 2000*1000*400, 4 полки (150)
A9: № | B9: Наименование статьи затрат | C9: Ед.изм. | D9: Кол-во | E9: Цена. руб | F9: Стоимость. руб
A10: 1 | B10: Болт 6*12 оцинк. | C10: кг | D10: 0.491 | E10: 177 | F10: =D10*E10 -> 86.907 | H10: Болт 6*12 оцинк. | I10: кг | J10: 0,491
A11: 2 | B11: Гайка М6 оцинк. | C11: кг | D11: 0.24 | E11: 176 | F11: =D11*E11 -> 42.24 | H11: Гайка М6 оцинк. | I11: кг | J11: 0,24
A12: 3 | B12: Паспорт на продукцию | C12: шт | D12: 1 | E12: 4.96 | F12: =D12*E12 -> 4.96 | H12: Паспорт на продукцию | I12: шт | J12: 1
A13: 4 | B13: Подпятник пластмассовый под профилированные стойки | C13: шт | D13: 4 | E13: 2.45 | F13: =D13*E13 -> 9.8 | H13: Подпятник пластмассовый под профилированные стойки | I13: шт | J13: 4
A14: 5 | B14: Этикетка 58*60 полуглянец | C14: шт | D14: 1 | E14: 0.41 | F14: =D14*E14 -> 0.41 | H14: Этикетка 58*60 полуглянец | I14: шт | J14: 0,002
A15: 6 | B15: Рулон оцин 0.9*1250 | C15: кг | D15: 0.496 | E15: 80 | F15: =D15*E15 -> 39.68 | H15: Рулон оцин 0,9*1250 | I15: кг | J15: 0,496
A16: 7 | B16: ELB52I EE BUG GRIGIO 7035 GL TR св.серая | C16: кг | D16: 0.892 | E16: 213.1 | F16: =D16*E16 -> 190.0852 | H16: ELB52I EE BUG GRIGIO 7035 GL TR св.серая | I16: кг | J16: 0,892
A17: 8 | B17: Лента 1.2*74.5 | C17: кг | D17: 5.752 | E17: 70 | F17: =D17*E17 -> 402.64 | H17: Лента 1,2*74,5 | I17: кг | J17: 5,752
A18: 9 | B18: Лист 1.2мм | C18: кг | D18: 0.54 | E18: 68.75 | F18: =D18*E18 -> 37.125 | H18: Лист 1,2мм | I18: кг | J18: 0,54
A19: 10 | B19: Лента 0.5*517 | C19: кг | D19: 8.116 | E19: 66.67 | F19: =D19*E19 -> 541.09372 | H19: Лента 0,5*517 | I19: кг | J19: 8,116
A20: 11 | B20: Лента 0.5*115 | C20: кг | D20: 1.804 | E20: 66.67 | F20: =D20*E20 -> 120.27268 | H20: Лента 0,5*115 | I20: кг | J20: 1,804
A21: 12 | B21: Рулон х/к 0.9*1250 | C21: кг | D21: 1.424 | E21: 69.17 | F21: =D21*E21 -> 98.49808 | H21: Лист 0,9мм | I21: кг | J21: 1,424
A22: 13 | B22: Общая химия | C22: кг | D22: 0.035 | E22: 290 | F22: =D22*E22 -> 10.15 | H22: Общая химия | I22: кг | J22: 0,035
B23: Всего на материалы без НДС | F23: =SUM(F10:F22) -> 1583.8617
B24: Наценка на материалы | E24: 0.01 | F24: =F23*E24 -> 15.838617
B25: Итого | F25: =SUM(F23,F24) -> 1599.7003
A26: 2 | B26: Основная з/п цеховых рабочих | E26: 0.11 | F26: =F25*E26 -> 175.96703
B27: Дополнительная з/п | E27: 0.14 | F27: =F26*E27 -> 24.635385
B28: Отчисления на социальные нужды цеховые | E28: 0.309 | F28: =(F26+F27)*E28 -> 61.986147
B29: Отчисления на социальные нужды Дополнительная з/п | E29: 0 | F29: 0
A30: 3 | B30: Общепроизводственные (накладные) расходы | E30: 1.5 | F30: =F26*E30 -> 263.95055
A31: 4 | B31: Цеховая себестоимость | F31: =F25+F26+F27+F28+F29+F30 -> 2126.2394
A32: 5 | B32: Общехозяйственные расходы | E32: 1 | F32: =F26*E32 -> 175.96703
E33: 0.8 | F33: =F26*E33 -> 140.77363
A34: 6 | B34: СЕБЕСТОИМОСТЬ | F34: =F31+F32 -> 2302.2064
F35: =F31+F33 -> 2267.013
A36: 7 | B36: Прибыль | E36: 0.4 | F36: =F34*E36 -> 920.88258
E37: 0.07 | F37: =F35*E37 -> 158.69091
A38: 8 | B38: Расходы на упаковку | F38: 65.45
B39: Цена без НДС | F39: =F34+F36+F38 -> 3288.539
F40: =F35+F37+F38 -> 2491.1539
B41: НДС | E41: 0.22 | F41: =F39*E41 -> 723.47858
E42: 0.22 | F42: =F40*E42 -> 548.05387
B43: ОТПУСКНАЯ ЦЕНА | E43: розн | F43: =F39+F41 -> 4012.0176
E44: опт | F44: =F40+F42 -> 3039.2078
B47: Главный бухгалтер ________________

Sheet 10.3 100 кг
A1: Стеллаж 10.3
A2: Полка | L2: Стойка
A3: № | B3: Наименование статьи затрат | C3: ед. изм. | D3: кол-во | E3: цена, руб. | F3: стоимость, руб. | G3: расход г/м2 | L3: № | M3: Наименование статьи затрат | N3: ед. изм. | O3: кол-во | P3: цена, руб. | Q3: стоимость, руб. | R3: расход г/м2
B4: Лента 0,4*417 | C4: кг | D4: 1.440318 | E4: 55 | F4: =D4*E4 -> 79.21749 | L4: 1 | M4: Лента 0,5*417 | N4: кг | O4: 1.636725 | P4: 50.82 | Q4: =O4*P4 -> 83.178365
B5: Лента 0,4*115 | C5: кг | D5: 0.39721 | E5: 55 | F5: =D5*E5 -> 21.84655 | M5: Рулон х/к 0,9*1250 | N5: кг | O5: 0.24054347 | P5: 61.48 | Q5: =O5*P5 -> 14.788612
B6: Рулон х/к 0,4 | C6: кг | D6: 0.13143161 | E6: 65.83 | F6: =D6*E6 -> 8.6521428 | M6: Лента 0,5*115 | N6: кг | O6: 0.451375 | P6: 50.82 | Q6: =O6*P6 -> 22.938878
B7: Краска RAL 7035 | C7: кг | D7: 0.14833011 | E7: 211.42 | F7: =D7*E7 -> 31.359952 | G7: 0.133 | M7: Краска RAL 7035 | N7: кг | O7: 0.14833011 | P7: 208.95 | Q7: =O7*P7 -> 30.993577 | R7: 0.133
B8: Площадь (Химия ) | C8: м2 | D8: 1.115264 | E8: 290 | F8: =D8*E8*G8/1000 -> 1.6171328 | G8: 5 | M8: Площадь (Химия ) | N8: м2 | O8: 1.115264 | P8: 290 | Q8: =O8*P8*R8/1000 -> 1.6171328 | R8: 5
B9: Болт 6*12 оцинк. | C9: шт. | D9: 8 | E9: 0.91 | F9: =D9*E9 -> 7.28 | M9: Болт 6*12 оцинк. | N9: кг | O9: 0.04096 | P9: 180 | Q9: =O9*P9 -> 7.3728
B10: Гайка М6 оцинк. | C10: шт. | D10: 8 | E10: 0.46 | F10: =D10*E10 -> 3.68 | M10: Гайка М6 оцинк. | N10: кг | O10: 0.02 | P10: 179 | Q10: =O10*P10 -> 3.58
B11: Всего на материалы без НДС | F11: =SUM(F4:F10) -> 153.65327 | M11: Шайба Ф6,5 | N11: шт | O11: 2 | P11: 0.25 | Q11: =O11*P11 -> 0.5
B12: Наценка на материалы | E12: 0.01 | F12: =F11*E12 -> 1.5365327 | M12: Всего на материалы без НДС | Q12: =SUM(Q4:Q11) -> 164.96936
B13: Итого: | F13: =SUM(F11:F12) -> 155.1898 | M13: Наценка на материалы | P13: 0.01 | Q13: =Q12*P13 -> 1.6496936
A14: 2 | B14: Основная з/п цеховых рабочих | E14: 0.14 | F14: =F13*E14 -> 21.726572 | M14: Итого: | Q14: =SUM(Q12:Q13) -> 166.61906
B15: Дополнительная з/п | E15: 0.14 | F15: =F14*E15 -> 3.0417201 | L15: 2 | M15: Основная з/п цеховых рабочих | P15: 0.14 | Q15: =Q14*P15 -> 23.326668
B16: Отчисления на социальные нужды | F16: =(F14+F15)*31.3% -> 7.7524754 | M16: Дополнительная з/п | P16: 0.14 | Q16: =Q15*P16 -> 3.2657335
A17: 3 | B17: Общепроизводственные (накладные) расходы | E17: 1.5 | F17: =F14*E17 -> 32.589858 | M17: Отчисления на социальные нужды | Q17: =(Q15+Q16)*30.9% -> 8.2170521
A18: 4 | B18: Цеховая себестоимость | F18: =F13+F14+F15+F16+F17 -> 220.30043 | L18: 3 | M18: Общепроизводственные (накладные) расходы | P18: 1.5 | Q18: =Q15*P18 -> 34.990002
A19: 5 | B19: Общехозяйственные расходы | E19: 1 | F19: =F14*E19 -> 21.726572 | L19: 4 | M19: Цеховая себестоимость | Q19: =Q14+Q15+Q16+Q17+Q18 -> 236.41851
E20: 0.8 | F20: =F14*E20 -> 17.381258 | L20: 5 | M20: Общехозяйственные расходы | P20: 1 | Q20: =Q15*P20 -> 23.326668
A21: 6 | B21: СЕБЕСТОИМОСТЬ: | F21: =F18+F19 -> 242.027 | P21: 0.8 | Q21: =Q15*P21 -> 18.661334
F22: =F18+F20 -> 237.68168 | L22: 6 | M22: СЕБЕСТОИМОСТЬ: | Q22: =Q19+Q20 -> 259.74518
A23: 7 | B23: Прибыль | E23: 0.4 | F23: =F21*E23 -> 96.810799 | Q23: =Q19+Q21 -> 255.07985
E24: 0.07 | F24: =F22*E24 -> 16.637718 | L24: 7 | M24: Прибыль | P24: 0.4 | Q24: =Q22*P24 -> 103.89807
A25: 8 | B25: Расходы на упаковку | F25: 37 | H25: Гофрокартон СТ-П 3 (40) 6 | I25: шт. | J25: 0.333 | P25: 0.05 | Q25: =Q23*P25 -> 12.753992
A26: 9 | B26: Цена без НДС | F26: =F21+F23+F25 -> 375.8378 | H26: Полиэтилен т/у полотно 1075*0,100 | I26: кг. | J26: 0.02 | L26: 8 | M26: Расходы на упаковку | Q26: 20 | S26: Гофрокартон СТ-П 3 (40) 6 | T26: шт | U26: 0.33333333
F27: =F22+F24+F25 -> 291.3194 | L27: 9 | M27: Цена без НДС | Q27: =Q22+Q24+Q26 -> 383.64325 | S27: Полиэтилен т/у полотно 1075*0,100 | T27: кг | U27: 0.017495625
A28: 10 | B28: НДС | E28: 0.22 | F28: =F26*E28 -> 82.684315 | Q28: =Q23+Q25+Q26 -> 287.83384
E29: 0.22 | F29: =F27*E29 -> 64.090268 | L29: 10 | M29: НДС | P29: 0.22 | Q29: =Q27*P29 -> 84.401516
A30: 11 | B30: ОТПУСКАЯ ЦЕНА | E30: розн | F30: =F26+F28 -> 458.52211 | P30: 0.22 | Q30: =Q28*P30 -> 63.323445 | W30: 10.3 4п | X30: =F31*4+Q32*4+17*4 -> 2894.2678
E31: опт | F31: =F27+F29 -> 355.40967 | L31: 11 | M31: ОТПУСКАЯ ЦЕНА | P31: розн | Q31: =Q27+Q29 -> 468.04477 | W31: 10.3 6п | X31: =F31*6+Q32*4+17*4 -> 3605.0872
P32: опт | Q32: =Q28+Q30 -> 351.15729

Sheet 10.6 100кг
A1: Стеллаж 10.6
A2: Полка | L2: Стойка
A3: № | B3: Наименование статьи затрат | C3: ед. изм. | D3: кол-во | E3: цена, руб. | F3: стоимость, руб. | G3: расход г/м2 | L3: № | M3: Наименование статьи затрат | N3: ед. изм. | O3: кол-во | P3: цена, руб. | Q3: стоимость, руб. | R3: расход г/м2
B4: Лента 0,4*717 | C4: кг | D4: 2.476518 | E4: 55 | F4: =D4*E4 -> 136.20849 | L4: 1 | M4: Лента 0,5*417 | N4: кг | O4: 3.0956475 | P4: 50.82 | Q4: =O4*P4 -> 157.32081
B5: Лента 0,4*115 | C5: кг | D5: 0.39721 | E5: 55 | F5: =D5*E5 -> 21.84655 | M5: Рулон х/к 0,9*1250 | N5: кг | O5: 0.48932473 | P5: 61.48 | Q5: =O5*P5 -> 30.083684
B6: Рулон х/к 0,4 | C6: кг | D6: 0.26199281 | E6: 65.83 | F6: =D6*E6 -> 17.246987 | M6: Лента 0,9*115 | N6: кг | O6: 0.812475 | P6: 50.82 | Q6: =O6*P6 -> 41.289979
B7: Краска RAL 7035 | C7: кг | D7: 0.23579091 | E7: 211.42 | F7: =D7*E7 -> 49.850915 | G7: 0.133 | M7: Краска RAL 7035 | N7: кг | O7: 0.2358473 | P7: 208.95 | Q7: =O7*P7 -> 49.280294 | R7: 0.133
B8: Площадь (Химия ) | C8: м2 | D8: 1.772864 | E8: 290 | F8: =D8*E8*G8/1000 -> 2.5706528 | G8: 5 | M8: Площадь (Химия ) | N8: м2 | O8: 1.773288 | P8: 290 | Q8: =O8*P8*R8/1000 -> 2.5712676 | R8: 5
B9: Болт 6*12 оцинк. | C9: шт. | D9: 8 | E9: 0.91 | F9: =D9*E9 -> 7.28 | M9: Болт 6*12 оцинк. | N9: кг | O9: 0.04096 | P9: 180 | Q9: =O9*P9 -> 7.3728
B10: Гайка М6 оцинк. | C10: шт. | D10: 8 | E10: 0.46 | F10: =D10*E10 -> 3.68 | M10: Гайка М6 оцинк. | N10: кг | O10: 0.02 | P10: 179 | Q10: =O10*P10 -> 3.58
B11: Всего на материалы без НДС | F11: =SUM(F4:F10) -> 238.68359 | M11: Шайба Ф6,5 | N11: шт | O11: 2 | P11: 0.25 | Q11: =O11*P11 -> 0.5
B12: Наценка на материалы | E12: 0.01 | F12: =F11*E12 -> 2.3868359 | M12: Всего на материалы без НДС | Q12: =SUM(Q4:Q11) -> 291.99883
B13: Итого: | F13: =SUM(F11:F12) -> 241.07043 | M13: Наценка на материалы | P13: 0.01 | Q13: =Q12*P13 -> 2.9199883
A14: 2 | B14: Основная з/п цеховых рабочих | E14: 0.14 | F14: =F13*E14 -> 33.74986 | M14: Итого: | Q14: =SUM(Q12:Q13) -> 294.91882
B15: Дополнительная з/п | E15: 0.14 | F15: =F14*E15 -> 4.7249804 | L15: 2 | M15: Основная з/п цеховых рабочих | P15: 0.14 | Q15: =Q14*P15 -> 41.288635
B16: Отчисления на социальные нужды | F16: =(F14+F15)*31.3% -> 12.042625 | M16: Дополнительная з/п | P16: 0.14 | Q16: =Q15*P16 -> 5.7804089
A17: 3 | B17: Общепроизводственные (накладные) расходы | E17: 1.5 | F17: =F14*E17 -> 50.62479 | M17: Отчисления на социальные нужды | Q17: =(Q15+Q16)*30.9% -> 14.544334
A18: 4 | B18: Цеховая себестоимость | F18: =F13+F14+F15+F16+F17 -> 342.21269 | L18: 3 | M18: Общепроизводственные (накладные) расходы | P18: 1.5 | Q18: =Q15*P18 -> 61.932952
A19: 5 | B19: Общехозяйственные расходы | E19: 1 | F19: =F14*E19 -> 33.74986 | L19: 4 | M19: Цеховая себестоимость | Q19: =Q14+Q15+Q16+Q17+Q18 -> 418.46515
E20: 0.8 | F20: =F14*E20 -> 26.999888 | L20: 5 | M20: Общехозяйственные расходы | P20: 1 | Q20: =Q15*P20 -> 41.288635
A21: 6 | B21: СЕБЕСТОИМОСТЬ: | F21: =F18+F19 -> 375.96255 | P21: 0.8 | Q21: =Q15*P21 -> 33.030908
F22: =F18+F20 -> 369.21257 | L22: 6 | M22: СЕБЕСТОИМОСТЬ: | Q22: =Q19+Q20 -> 459.75378
A23: 7 | B23: Прибыль | E23: 0.4 | F23: =F21*E23 -> 150.38502 | Q23: =Q19+Q21 -> 451.49606
E24: 0.07 | F24: =F22*E24 -> 25.84488 | L24: 7 | M24: Прибыль | P24: 0.4 | Q24: =Q22*P24 -> 183.90151
A25: 8 | B25: Расходы на упаковку | F25: 38.5 | H25: Гофрокартон СТ-П 6 (40) 6 | I25: шт. | J25: 0.333 | P25: 0.25 | Q25: =Q23*P25 -> 112.87401
A26: 9 | B26: Цена без НДС | F26: =F21+F23+F25 -> 564.84756 | H26: Полиэтилен т/у полотно 1075*0,100 | I26: кг. | J26: 0.038 | L26: 8 | M26: Расходы на упаковку | Q26: 20 | S26: Гофрокартон СТ-П 6 (40) 6 | T26: шт | U26: 0.33333333
F27: =F22+F24+F25 -> 433.55745 | L27: 9 | M27: Цена без НДС | Q27: =Q22+Q24+Q26 -> 663.6553 | S27: Полиэтилен т/у полотно 1075*0,100 | T27: кг | U27: 0.027493125
A28: 10 | B28: НДС | E28: 0.2 | F28: =F26*E28 -> 112.96951 | Q28: =Q23+Q25+Q26 -> 584.37007
E29: 0.2 | F29: =F27*E29 -> 86.711491 | L29: 10 | M29: НДС | P29: 0.22 | Q29: =Q27*P29 -> 146.00417
A30: 11 | B30: ОТПУСКАЯ ЦЕНА | E30: розн | F30: =F26+F28 -> 677.81708 | P30: 0.22 | Q30: =Q28*P30 -> 128.56142
E31: опт | F31: =F27+F29 -> 520.26895 | L31: 11 | M31: ОТПУСКАЯ ЦЕНА | P31: розн | Q31: =Q27+Q29 -> 809.65946 | S31: 10.6 4п | T31: =F31*4+Q32*4+17*4 -> 5000.8017
P32: опт | Q32: =Q28+Q30 -> 712.93149 | S32: 10.6 6п | T32: =F31*6+Q32*4+17*4 -> 6041.3396

Sheet 40(6) NEW
F1: УТВЕРЖДАЮ
F2: генеральный директор
F3: ООО "Вика-Двина"
F4: В.А. Иванов _________
A5: Калькуляция | F5: подпись
A7: Стеллаж металлический СТ-СПЭ 2000*1000*400, 6 полок (150)
A9: № | B9: Наименование статьи затрат | C9: Ед.изм. | D9: Кол-во | E9: Цена. руб | F9: Стоимость. руб
A10: 1 | B10: Болт 6*12 оцинк. | C10: кг | D10: 0.573 | E10: 177 | F10: =D10*E10 -> 101.421 | H10: Болт 6*12 оцинк. | I10: кг | J10: 0,573
A11: 2 | B11: Гайка М6 оцинк. | C11: кг | D11: 0.28 | E11: 176 | F11: =D11*E11 -> 49.28 | H11: Гайка М6 оцинк. | I11: кг | J11: 0,28
A12: 3 | B12: Паспорт на продукцию | C12: шт | D12: 1 | E12: 4.96 | F12: =D12*E12 -> 4.96 | H12: Паспорт на продукцию | I12: шт | J12: 1
A13: 4 | B13: Подпятник пластмассовый под профилированные стойки | C13: шт | D13: 4 | E13: 2.45 | F13: =D13*E13 -> 9.8 | H13: Подпятник пластмассовый под профилированные стойки | I13: шт | J13: 4
A14: 5 | B14: Этикетка 58*60 полуглянец | C14: шт | D14: 1 | E14: 0.41 | F14: =D14*E14 -> 0.41 | H14: Этикетка 58*60 полуглянец | I14: шт | J14: 0,002
A15: 6 | B15: Рулон оцин 0.9*1250 | C15: кг | D15: 0.496 | E15: 80 | F15: =D15*E15 -> 39.68 | H15: Рулон оцин 0,9*1250 | I15: кг | J15: 0,496
A16: 7 | B16: ELB52I EE BUG GRIGIO 7035 GL TR св.серая | C16: кг | D16: 1.256 | E16: 213.1 | F16: =D16*E16 -> 267.6536 | H16: ELB52I EE BUG GRIGIO 7035 GL TR св.серая | I16: кг | J16: 1,256
A17: 8 | B17: Лента 1.2*74.5 | C17: кг | D17: 5.752 | E17: 70 | F17: =D17*E17 -> 402.64 | H17: Лента 1,2*74,5 | I17: кг | J17: 5,752
A18: 9 | B18: Лист 1.2мм | C18: кг | D18: 0.54 | E18: 68.75 | F18: =D18*E18 -> 37.125 | H18: Лист 1,2мм | I18: кг | J18: 0,54
A19: 10 | B19: Лента 0.5*517 | C19: кг | D19: 12.174 | E19: 66.67 | F19: =D19*E19 -> 811.64058 | H19: Лента 0,5*517 | I19: кг | J19: 12,174
A20: 11 | B20: Лента 0.5*115 | C20: кг | D20: 2.706 | E20: 66.67 | F20: =D20*E20 -> 180.40902 | H20: Лента 0,5*115 | I20: кг | J20: 2,706
A21: 12 | B21: Рулон х/к 0.9*1250 | C21: кг | D21: 2.136 | E21: 69.17 | F21: =D21*E21 -> 147.74712 | H21: Лист 0,9мм | I21: кг | J21: 2,136
A22: 13 | B22: Общая химия | C22: кг | D22: 0.048 | E22: 290 | F22: =D22*E22 -> 13.92 | H22: Общая химия | I22: кг | J22: 0,048
B23: Всего на материалы без НДС | F23: =SUM(F10:F22) -> 2066.6863
B24: Наценка на материалы | E24: 0.01 | F24: =F23*E24 -> 20.666863
B25: Итого | F25: =SUM(F23,F24) -> 2087.3532
A26: 2 | B26: Основная з/п цеховых рабочих | E26: 0.11 | F26: =F25*E26 -> 229.60885
B27: Дополнительная з/п | E27: 0.14 | F27: =F26*E27 -> 32.145239
B28: Отчисления на социальные нужды цеховые | E28: 0.309 | F28: =(F26+F27)*E28 -> 80.882014
B29: Отчисления на социальные нужды Дополнительная з/п | E29: 0 | F29: 0
A30: 3 | B30: Общепроизводственные (накладные) расходы | E30: 1.5 | F30: =F26*E30 -> 344.41328
A31: 4 | B31: Цеховая себестоимость | F31: =F25+F26+F27+F28+F29+F30 -> 2774.4026
A32: 5 | B32: Общехозяйственные расходы | E32: 1 | F32: =F26*E32 -> 229.60885
E33: 0.8 | F33: =F26*E33 -> 183.68708
A34: 6 | B34: СЕБЕСТОИМОСТЬ | F34: =F31+F32 -> 3004.0114
F35: =F31+F33 -> 2958.0896
A36: 7 | B36: Прибыль | E36: 0.4 | F36: =F34*E36 -> 1201.6046
E37: 0.07 | F37: =F35*E37 -> 207.06627
A38: 8 | B38: Расходы на упаковку | F38: 67.85
B39: Цена без НДС | F39: =F34+F36+F38 -> 4273.466
F40: =F35+F37+F38 -> 3233.0059
B41: НДС | E41: 0.22 | F41: =F39*E41 -> 940.16251
E42: 0.22 | F42: =F40*E42 -> 711.2613
B43: ОТПУСКНАЯ ЦЕНА | E43: розн | F43: =F39+F41 -> 5213.6285
E44: опт | F44: =F40+F42 -> 3944.2672
B47: Главный бухгалтер ________________

Sheet 50(4) NEW
F1: УТВЕРЖДАЮ
F2: генеральный директор
F3: ООО "Вика-Двина"
F4: В.А. Иванов _________
A5: Калькуляция | F5: подпись
A7: Стеллаж металлический СТ-СПЭ 2000*1000*500, 4 полки (150)
A9: № | B9: Наименование статьи затрат | C9: Ед.изм. | D9: Кол-во | E9: Цена. руб | F9: Стоимость. руб
A10: 1 | B10: Болт 6*12 оцинк. | C10: кг | D10: 0.491 | E10: 177 | F10: =D10*E10 -> 86.907 | H10: Болт 6*12 оцинк. | I10: кг | J10: 0,491
A11: 2 | B11: Гайка М6 оцинк. | C11: кг | D11: 0.24 | E11: 176 | F11: =D11*E11 -> 42.24 | H11: Гайка М6 оцинк. | I11: кг | J11: 0,24
A12: 3 | B12: Паспорт на продукцию | C12: шт | D12: 1 | E12: 4.96 | F12: =D12*E12 -> 4.96 | H12: Паспорт на продукцию | I12: шт | J12: 1
A13: 4 | B13: Подпятник пластмассовый под профилированные стойки | C13: шт | D13: 4 | E13: 2.45 | F13: =D13*E13 -> 9.8 | H13: Подпятник пластмассовый под профилированные стойки | I13: шт | J13: 4
A14: 5 | B14: Этикетка 58*60 полуглянец | C14: шт | D14: 1 | E14: 0.41 | F14: =D14*E14 -> 0.41 | H14: Этикетка 58*60 полуглянец | I14: шт | J14: 0,002
A15: 6 | B15: Рулон оцин 0.9*1250 | C15: кг | D15: 0.496 | E15: 80 | F15: =D15*E15 -> 39.68 | H15: Рулон оцин 0,9*1250 | I15: кг | J15: 0,496
A16: 7 | B16: ELB52I EE BUG GRIGIO 7035 GL TR св.серая | C16: кг | D16: 0.992 | E16: 213.1 | F16: =D16*E16 -> 211.3952 | H16: ELB52I EE BUG GRIGIO 7035 GL TR св.серая | I16: кг | J16: 0,992
A17: 8 | B17: Лента 1.2*74.5 | C17: кг | D17: 5.752 | E17: 70 | F17: =D17*E17 -> 402.64 | H17: Лента 1,2*74,5 | I17: кг | J17: 5,752
A18: 9 | B18: Лист 1.2мм | C18: кг | D18: 0.54 | E18: 68.75 | F18: =D18*E18 -> 37.125 | H18: Лист 1,2мм | I18: кг | J18: 0,54
A19: 10 | B19: Лента 0.5*517 | C19: кг | D19: 9.684 | E19: 66.67 | F19: =D19*E19 -> 645.63228 | H19: Лента 0,5*617 | I19: кг | J19: 9,684
A20: 11 | B20: Лента 0.5*115 | C20: кг | D20: 1.804 | E20: 66.67 | F20: =D20*E20 -> 120.27268 | H20: Лента 0,5*115 | I20: кг | J20: 1,804
A21: 12 | B21: Рулон х/к 0.9*1250 | C21: кг | D21: 1.784 | E21: 69.17 | F21: =D21*E21 -> 123.39928 | H21: Лист 0,9мм | I21: кг | J21: 1,784
A22: 13 | B22: Общая химия | C22: кг | D22: 0.039 | E22: 290 | F22: =D22*E22 -> 11.31 | H22: Общая химия | I22: кг | J22: 0,039
B23: Всего на материалы без НДС | F23: =SUM(F10:F22) -> 1735.7714
B24: Наценка на материалы | E24: 0.01 | F24: =F23*E24 -> 17.357714
B25: Итого | F25: =SUM(F23,F24) -> 1753.1292
A26: 2 | B26: Основная з/п цеховых рабочих | E26: 0.11 | F26: =F25*E26 -> 192.84421
B27: Дополнительная з/п | E27: 0.14 | F27: =F26*E27 -> 26.998189
B28: Отчисления на социальные нужды цеховые | E28: 0.309 | F28: =(F26+F27)*E28 -> 67.9313
B29: Отчисления на социальные нужды Дополнительная з/п | E29: 0 | F29: 0
A30: 3 | B30: Общепроизводственные (накладные) расходы | E30: 1.5 | F30: =F26*E30 -> 289.26631
A31: 4 | B31: Цеховая себестоимость | F31: =F25+F26+F27+F28+F29+F30 -> 2330.1692
A32: 5 | B32: Общехозяйственные расходы | E32: 1 | F32: =F26*E32 -> 192.84421
E33: 0.8 | F33: =F26*E33 -> 154.27537
A34: 6 | B34: СЕБЕСТОИМОСТЬ | F34: =F31+F32 -> 2523.0134
F35: =F31+F33 -> 2484.4445
A36: 7 | B36: Прибыль | E36: 0.4 | F36: =F34*E36 -> 1009.2053
E37: 0.07 | F37: =F35*E37 -> 173.91112
A38: 8 | B38: Расходы на упаковку | F38: 73.55
B39: Цена без НДС | F39: =F34+F36+F38 -> 3605.7687
F40: =F35+F37+F38 -> 2731.9056
B41: НДС | E41: 0.22 | F41: =F39*E41 -> 793.26912
E42: 0.22 | F42: =F40*E42 -> 601.01924
B43: ОТПУСКНАЯ ЦЕНА | E43: розн | F43: =F39+F41 -> 4399.0378
E44: опт | F44: =F40+F42 -> 3332.9249
B47: Главный бухгалтер ________________

Sheet СПЭ(4)
F1: УТВЕРЖДАЮ
F2: генеральный директор
F3: ООО "Вика-Двина"
F4: В.А. Иванов _____________
B5: Калькуляция | F5: подпись
B6: СТ-ПЭ 20(25)
A8: № | B8: Наименование статьи затрат | C8: ед. изм. | D8: кол-во | E8: цена, руб. | F8: стоимость, руб. | G8: расход г/м2 | L8: Калькуляция
B9: Лента 0,9*74,5 | C9: кг | D9: 1.067 | E9: 56.56 | F9: =D9*E9 -> 60.34952 | L9: СТ-П10,4
B10: Рулон оц 0,9*1250 | C10: кг | D10: 0.12421966 | E10: 70.49 | F10: =D10*E10 -> 8.7562436
B11: Краска RAL 7035 | C11: кг | D11: 0.039891621 | E11: 191.41 | F11: =D11*E11 -> 7.6356552 | G11: 0.133 | K11: № | L11: Наименование статьи затрат | M11: ед. изм. | N11: кол-во | O11: цена, руб. | P11: стоимость, руб. | Q11: расход г/м2
B12: Площадь (Химия ) | C12: м2 | D12: 0.299937 | E12: 290 | F12: =D12*E12*G12/1000 -> 0.43490865 | G12: 5 | K12: 1 | L12: Лента 0,4*517 | M12: кг | N12: 1.62338 | O12: 51.64 | P12: =N12*O12 -> 83.831343
B13: Болт 6*12 оцинк. | C13: шт. | D13: 8 | E13: 0.91 | F13: =D13*E13 -> 7.28 | L13: Рулон х/к 0,9*1250 | M13: кг | N13: 0.32292137 | O13: 61.48 | P13: =N13*O13 -> 19.853206
B14: Гайка М6 оцинк. | C14: шт. | D14: 8 | E14: 0.46 | F14: =D14*E14 -> 3.68 | L14: Лента 0,5*115 | M14: кг | N14: 0.451375 | O14: 50.82 | P14: =N14*O14 -> 22.938878
B15: Всего на материалы без НДС | F15: =SUM(F9:F14) -> 88.136327 | L15: Краска RAL 7035 | M15: кг | N15: 0.17748371 | O15: 191.41 | P15: =N15*O15 -> 33.972157 | Q15: 0.133
B16: Наценка на материалы | E16: 0.01 | F16: =F15*E16 -> 0.88136327 | L16: Площадь (Химия ) | M16: м2 | N16: 1.334464 | O16: 290 | P16: =N16*O16*Q16/1000 -> 1.9349728 | Q16: 5
B17: Итого: | F17: =SUM(F15:F16) -> 89.017691 | L17: Болт 6*12 оцинк. | M17: кг | N17: 0.04096 | O17: 180 | P17: =N17*O17 -> 7.3728
A18: 2 | B18: Основная з/п цеховых рабочих | E18: 0.14 | F18: =F17*E18 -> 12.462477 | L18: Гайка М6 оцинк. | M18: кг | N18: 0.02 | O18: 179 | P18: =N18*O18 -> 3.58
B19: Дополнительная з/п | E19: 0.14 | F19: =F18*E19 -> 1.7447467 | L19: Шайба Ф6,5 | M19: шт | N19: 2 | O19: 0.25 | P19: =N19*O19 -> 0.5
B20: Отчисления на социальные нужды | F20: =(F18+F19)*31.3% -> 4.4468609 | L20: Всего на материалы без НДС | P20: =SUM(P12:P19) -> 173.98336
A21: 3 | B21: Общепроизводственные (накладные) расходы | E21: 1.5 | F21: =F18*E21 -> 18.693715 | L21: Наценка на материалы | O21: 0.01 | P21: =P20*O21 -> 1.7398336
A22: 4 | B22: Цеховая себестоимость | F22: =F17+F18+F19+F20+F21 -> 126.36549 | L22: Итого: | P22: =SUM(P20:P21) -> 175.72319
A23: 5 | B23: Общехозяйственные расходы | E23: 1 | F23: =F18*E23 -> 12.462477 | K23: 2 | L23: Основная з/п цеховых рабочих | O23: 0.14 | P23: =P22*O23 -> 24.601247
E24: 0.8 | F24: =F18*E24 -> 9.9699814 | L24: Дополнительная з/п | O24: 0.14 | P24: =P23*O24 -> 3.4441745
A25: 6 | B25: СЕБЕСТОИМОСТЬ: | F25: =F22+F23 -> 138.82797 | L25: Отчисления на социальные нужды | P25: =(P23+P24)*30.9% -> 8.6660351
F26: =F22+F24 -> 136.33547 | K26: 3 | L26: Общепроизводственные (накладные) расходы | O26: 1.5 | P26: =P23*O26 -> 36.90187
A27: 7 | B27: Прибыль | E27: 0.4 | F27: =F25*E27 -> 55.531187 | K27: 4 | L27: Цеховая себестоимость | P27: =P22+P23+P24+P25+P26 -> 249.33652
E28: 0.07 | F28: =F26*E28 -> 9.543483 | K28: 5 | L28: Общехозяйственные расходы | O28: 1 | P28: =P23*O28 -> 24.601247
A29: 8 | B29: Расходы на упаковку | F29: 5 | O29: 0.8 | P29: =P23*O29 -> 19.680997
A30: 9 | B30: Цена без НДС | F30: =F25+F27+F29 -> 199.35915 | H30: Полиэтилен ТУ 300*0,07 | I30: кг. | J30: 0.012 | K30: 6 | L30: СЕБЕСТОИМОСТЬ: | P30: =P27+P28 -> 273.93776
F31: =F26+F28+F29 -> 150.87895 | P31: =P27+P29 -> 269.01751
A32: 10 | B32: НДС | E32: 0.22 | F32: =F30*E32 -> 43.859014 | K32: 7 | L32: Прибыль | O32: 0.4 | P32: =P30*O32 -> 109.57511
E33: 0.22 | F33: =F31*E33 -> 33.19337 | O33: 0.07 | P33: =P31*O33 -> 18.831226
A34: 11 | B34: ОТПУСКАЯ ЦЕНА | E34: розн | F34: =F30+F32 -> 243.21817 | K34: 8 | L34: Расходы на упаковку | P34: 9.1 | R34: Гофрокартон СТ-П 4 (40) 6 | S34: шт | T34: 0.33333333
E35: опт | F35: =F31+F33 -> 184.07232 | K35: 9 | L35: Цена без НДС | P35: =P30+P32+P34 -> 392.61287 | R35: Полиэтилен т/у полотно 1075*0,100 | S35: кг | T35: 0.020828125
P36: =P31+P33+P34 -> 296.94874
K37: 10 | L37: НДС | O37: 0.22 | P37: =P35*O37 -> 86.374831
O38: 0.22 | P38: =P36*O38 -> 65.328723
B39: Главный бухгалтер _________________ | K39: 11 | L39: ОТПУСКАЯ ЦЕНА | O39: розн | P39: =P35+P37 -> 478.9877
O40: опт | P40: =P36+P38 -> 362.27746
R42: 2000x1000x400, 4 | S42: =F35*4+P40*4+17*4 -> 2253.3991
R43: 2000х1000х400, 6 | S43: =F35*4+P40*6+17*4 -> 2977.9541

Sheet СПЭ(5)
F1: УТВЕРЖДАЮ
F2: генеральный директор
F3: ООО "Вика-Двина"
F4: В.А. Иванов _____________
B5: Калькуляция | F5: подпись | N5: Калькуляция | R5: подпись
B6: СТ-ПЭ 20(25) | N6: СТ-П10,5
A8: № | B8: Наименование статьи затрат | C8: ед. изм. | D8: кол-во | E8: цена, руб. | F8: стоимость, руб. | G8: расход г/м2 | M8: № | N8: Наименование статьи затрат | O8: ед. изм. | P8: кол-во | Q8: цена, руб. | R8: стоимость, руб. | S8: расход г/м2
B9: Лента 0,9*74,5 | C9: кг | D9: 1.067 | E9: 56.56 | F9: =D9*E9 -> 60.34952 | M9: 1 | N9: Лента 0,4*617 | O9: кг | P9: 1.93738 | Q9: 51.64 | R9: =P9*Q9 -> 100.0463
B10: Рулон оц 0,9*1250 | C10: кг | D10: 0.12421966 | E10: 70.49 | F10: =D10*E10 -> 8.7562436 | N10: Рулон х/к 0,9*1250 | O10: кг | P10: 0.41024194 | Q10: 61.48 | R10: =P10*Q10 -> 25.221675
B11: Краска RAL 7035 | C11: кг | D11: 0.039891621 | E11: 191.41 | F11: =D11*E11 -> 7.6356552 | G11: 0.133 | N11: Лента 0,5*115 | O11: кг | P11: 0.451375 | Q11: 50.82 | R11: =P11*Q11 -> 22.938878
B12: Площадь (Химия ) | C12: м2 | D12: 0.299937 | E12: 290 | F12: =D12*E12*G12/1000 -> 0.43490865 | G12: 5 | N12: Краска RAL 7035 | O12: кг | P12: 0.20680649 | Q12: 191.41 | R12: =P12*Q12 -> 39.58483 | S12: 0.133
B13: Болт 6*12 оцинк. | C13: шт. | D13: 8 | E13: 0.91 | F13: =D13*E13 -> 7.28 | N13: Площадь (Химия ) | O13: м2 | P13: 1.554936 | Q13: 290 | R13: =P13*Q13*S13/1000 -> 2.2546572 | S13: 5
B14: Гайка М6 оцинк. | C14: шт. | D14: 8 | E14: 0.46 | F14: =D14*E14 -> 3.68 | N14: Болт 6*12 оцинк. | O14: кг | P14: 0.04096 | Q14: 180 | R14: =P14*Q14 -> 7.3728
B15: Всего на материалы без НДС | F15: =SUM(F9:F14) -> 88.136327 | N15: Гайка М6 оцинк. | O15: кг | P15: 0.02 | Q15: 179 | R15: =P15*Q15 -> 3.58
B16: Наценка на материалы | E16: 0.01 | F16: =F15*E16 -> 0.88136327 | N16: Шайба Ф6,5 | O16: шт | P16: 2 | Q16: 0.25 | R16: =P16*Q16 -> 0.5
B17: Итого: | F17: =SUM(F15:F16) -> 89.017691 | N17: Всего на материалы без НДС | R17: =SUM(R9:R16) -> 201.49914
A18: 2 | B18: Основная з/п цеховых рабочих | E18: 0.14 | F18: =F17*E18 -> 12.462477 | N18: Наценка на материалы | Q18: 0.01 | R18: =R17*Q18 -> 2.0149914
B19: Дополнительная з/п | E19: 0.14 | F19: =F18*E19 -> 1.7447467 | N19: Итого: | R19: =SUM(R17:R18) -> 203.51413
B20: Отчисления на социальные нужды | F20: =(F18+F19)*31.3% -> 4.4468609 | M20: 2 | N20: Основная з/п цеховых рабочих | Q20: 0.14 | R20: =R19*Q20 -> 28.491979
A21: 3 | B21: Общепроизводственные (накладные) расходы | E21: 1.5 | F21: =F18*E21 -> 18.693715 | N21: Дополнительная з/п | Q21: 0.14 | R21: =R20*Q21 -> 3.988877
A22: 4 | B22: Цеховая себестоимость | F22: =F17+F18+F19+F20+F21 -> 126.36549 | N22: Отчисления на социальные нужды | R22: =(R20+R21)*30.9% -> 10.036584
A23: 5 | B23: Общехозяйственные расходы | E23: 1 | F23: =F18*E23 -> 12.462477 | M23: 3 | N23: Общепроизводственные (накладные) расходы | Q23: 1.5 | R23: =R20*Q23 -> 42.737968
E24: 0.8 | F24: =F18*E24 -> 9.9699814 | M24: 4 | N24: Цеховая себестоимость | R24: =R19+R20+R21+R22+R23 -> 288.76954
A25: 6 | B25: СЕБЕСТОИМОСТЬ: | F25: =F22+F23 -> 138.82797 | M25: 5 | N25: Общехозяйственные расходы | Q25: 1 | R25: =R20*Q25 -> 28.491979
F26: =F22+F24 -> 136.33547 | Q26: 0.8 | R26: =R20*Q26 -> 22.793583
A27: 7 | B27: Прибыль | E27: 0.4 | F27: =F25*E27 -> 55.531187 | M27: 6 | N27: СЕБЕСТОИМОСТЬ: | R27: =R24+R25 -> 317.26152
E28: 0.07 | F28: =F26*E28 -> 9.543483 | R28: =R24+R26 -> 311.56313
A29: 8 | B29: Расходы на упаковку | F29: 5 | M29: 7 | N29: Прибыль | Q29: 0.4 | R29: =R27*Q29 -> 126.90461
A30: 9 | B30: Цена без НДС | F30: =F25+F27+F29 -> 199.35915 | H30: Полиэтилен ТУ 300*0,07 | I30: кг. | J30: 0.012 | Q30: 0.07 | R30: =R28*Q30 -> 21.809419
F31: =F26+F28+F29 -> 150.87895 | M31: 8 | N31: Расходы на упаковку | R31: 10.3 | T31: Гофрокартон СТ-П 5 (40) 6 | U31: шт | V31: 0.33333333
A32: 10 | B32: НДС | E32: 0.22 | F32: =F30*E32 -> 43.859014 | M32: 9 | N32: Цена без НДС | R32: =R27+R29+R31 -> 454.46613 | T32: Полиэтилен т/у полотно 1075*0,100 | U32: кг | V32: 0.024160625
E33: 0.22 | F33: =F31*E33 -> 33.19337 | R33: =R28+R30+R31 -> 343.67254
A34: 11 | B34: ОТПУСКАЯ ЦЕНА | E34: розн | F34: =F30+F32 -> 243.21817 | M34: 10 | N34: НДС | Q34: 0.22 | R34: =R32*Q34 -> 99.982548
E35: опт | F35: =F31+F33 -> 184.07232 | Q35: 0.22 | R35: =R33*Q35 -> 75.60796
M36: 11 | N36: ОТПУСКАЯ ЦЕНА | Q36: розн | R36: =R32+R34 -> 554.44868 | T36: 2000x1000x500, 4 | U36: =F35*4+R37*4+17*4 -> 2481.4113
Q37: опт | R37: =R33+R35 -> 419.2805
B39: Главный бухгалтер _________________

Sheet СМ-50Э
F1: УТВЕРЖДАЮ
F2: генеральный директор
F3: ООО "Вика-Двина"
F4: В.А. Иванов _________
A5: Калькуляция | F5: подпись
A7: Сейф мебельный СМ-50Э
A9: № | B9: Наименование статьи затрат | C9: Ед.изм. | D9: Кол-во | E9: Цена. руб | F9: Стоимость. руб
A10: 1 | B10: Заклепка вытяжная 4.0*10 (не использовать) | C10: тыс. шт/1000 шт | D10: 0.015 | E10: 616.67 | F10: =E10*D10 -> 9.25005
A11: 2 | B11: Жгут нейлон. 2.5-3*150 | C11: тыс. шт/1000 шт | D11: 0.001 | E11: 468.33 | F11: =E11*D11 -> 0.46833
A12: 3 | B12: Батарейка АА (4 шт) | C12: упак | D12: 1 | E12: 84.78 | F12: =E12*D12 -> 84.78
A13: 4 | B13: Шайба 6 цинк DIN 125 | C13: кг | D13: 0.003 | E13: 154 | F13: =E13*D13 -> 0.462
A14: 5 | B14: Паспорт на продукцию | C14: шт | D14: 1 | E14: 1.4 | F14: =E14*D14 -> 1.4
A15: 6 | B15: Наклейка с заливной смолой 37х23мм "Cerera" | C15: шт | D15: 1 | F15: =E15*D15 -> 0
A16: 7 | B16: Стойка для платы CS-10 | C16: шт | D16: 4 | E16: 0.92 | F16: =E16*D16 -> 3.68
A17: 8 | B17: Саморезы 4.2*13 пресс-шайба острый | C17: шт | D17: 4 | E17: 0.24 | F17: =E17*D17 -> 0.96
A18: 9 | B18: Этикетка 100*60 полуглянец | C18: шт | D18: 1 | F18: =E18*D18 -> 0
A19: 10 | B19: Круг 6 L=4м | C19: кг | D19: 0.014 | E19: 133.33 | F19: =E19*D19 -> 1.86662
A20: 11 | B20: Замок электронный сейфовый LS026 | C20: компл | D20: 1 | E20: 537.5 | F20: =E20*D20 -> 537.5
A21: 12 | B21: ELB52I EE BUG GRIGIO 7035 GL TR св.серая | C21: кг | D21: 0.513 | E21: 202.75 | F21: =E21*D21 -> 104.01075
A22: 13 | B22: Круг лепестковый 125*22мм | C22: шт | D22: 0.201 | E22: 64.68 | F22: =E22*D22 -> 13.00068
A23: 14 | B23: Углекислота | C23: шт | D23: 0.015 | E23: 1000 | F23: =E23*D23 -> 15
A24: 15 | B24: Проволока СВ08 Г2С 0.8 омедн. | C24: кг | D24: 0.229 | E24: 158.33 | F24: =E24*D24 -> 36.25757
A25: 16 | B25: Ковролин | C25: м2 | D25: 0.105 | E25: 638.33 | F25: =E25*D25 -> 67.02465
A26: 17 | B26: Рулон х/к 0.9*1250 | C26: кг | D26: 2.103 | E26: 69.58 | F26: =E26*D26 -> 146.32674
A27: 18 | B27: Лист 2.0мм | C27: кг | D27: 2.47 | E27: 69.17 | F27: =E27*D27 -> 170.8499
A28: 19 | B28: Рулон оцин 0.5*1250 | C28: кг | D28: 0.004 | E28: 85.83 | F28: =E28*D28 -> 0.34332
A29: 20 | B29: Лист 1.2мм | C29: кг | D29: 8.475 | E29: 69.17 | F29: =E29*D29 -> 586.21575
A30: 21 | B30: Петля гаражная 10*60 | C30: шт | D30: 1 | E30: 18.95 | F30: =E30*D30 -> 18.95
A31: 22 | B31: Общая химия | C31: кг | D31: 0.014 | E31: 290 | F31: =E31*D31 -> 4.06
B32: Всего на материалы без НДС | F32: =SUM(F10:F31) -> 1802.4064
B33: Наценка на материалы | E33: 0.01 | F33: =F32*E33 -> 18.024064
B34: Итого | F34: =SUM(F32,F33) -> 1820.4304
A35: 2 | B35: Основная з/п цеховых рабочих | E35: 0.11 | F35: =F34*E35 -> 200.24735
B36: Дополнительная з/п | E36: 0.14 | F36: =F35*E36 -> 28.034629
B37: Отчисления на социальные нужды цеховые | E37: 0.309 | F37: =(F35+F36)*E37 -> 70.53913
B38: Отчисления на социальные нужды Дополнительная з/п
A39: 3 | B39: Общепроизводственные (накладные) расходы | E39: 1.5 | F39: =F35*E39 -> 300.37102
A40: 4 | B40: Цеховая себестоимость | F40: =F34+F35+F36+F37+F38+F39 -> 2419.6225
A41: 5 | B41: Общехозяйственные расходы | E41: 1 | F41: =F35*E41 -> 200.24735
E42: 0.8 | F42: =F35*E42 -> 160.19788
A43: 6 | B43: СЕБЕСТОИМОСТЬ | F43: =F40+F41 -> 2619.8699
F44: =F40+F42 -> 2579.8204
A45: 7 | B45: Прибыль | E45: 0.4 | F45: =F43*E45 -> 1047.948
E46: 0.07 | F46: =F43*E46 -> 183.39089
A47: 8 | B47: Расходы на упаковку | F47: 160.78
B48: Цена без НДС | F48: =F43+F45+F47 -> 3828.5979
F49: =F44+F46+F47 -> 2923.9913
B50: НДС | E50: 0.22 | F50: =F48*E50 -> 842.29153
E51: 0.22 | F51: =F49*E51 -> 643.27809
B52: ОТПУСКНАЯ ЦЕНА | E52: розн | F52: =F48+F50 -> 4670.8894
E53: опт | F53: =F49+F51 -> 3567.2694
B56: Главный бухгалтер ________________

Sheet СМ-50
F1: УТВЕРЖДАЮ
F2: генеральный директор
F3: ООО "Вика-Двина"
F4: В.А. Иванов _________
A5: Калькуляция | F5: подпись
A7: Сейф мебельный СМ-30
A9: № | B9: Наименование статьи затрат | C9: Ед.изм. | D9: Кол-во | E9: Цена. руб | F9: Стоимость. руб
A10: 1 | B10: Заклепка вытяжная 4.0*10 (не использовать) | C10: тыс. шт/1000 шт | D10: 0.012 | E10: 616.67 | F10: =E10*D10 -> 7.40004
A11: 2 | B11: Жгут нейлон. 2.5-3*150 | C11: тыс. шт/1000 шт | D11: 0.001 | E11: 468.33 | F11: =E11*D11 -> 0.46833
A12: 3 | B12: Шайба 6 цинк DIN 125 | C12: кг | D12: 0.003 | E12: 154 | F12: =E12*D12 -> 0.462
A13: 4 | B13: Паспорт на продукцию | C13: шт | D13: 1 | E13: 1.4 | F13: =E13*D13 -> 1.4
A14: 5 | B14: Наклейка с заливной смолой 37х23мм "Cerera" | C14: шт | D14: 1 | F14: =E14*D14 -> 0
A15: 6 | B15: Замок врезной САМ 8-6 (73100) | C15: шт | D15: 1 | E15: 495 | F15: =E15*D15 -> 495
A16: 7 | B16: Этикетка 100*60 полуглянец | C16: шт | D16: 1 | F16: =E16*D16 -> 0
A17: 8 | B17: Круг 6 L=4м | C17: кг | D17: 0.014 | E17: 133.33 | F17: =E17*D17 -> 1.86662
A18: 9 | B18: ELB52I EE BUG GRIGIO 7035 GL TR св.серая | C18: кг | D18: 0.503 | E18: 202.75 | F18: =E18*D18 -> 101.98325
A19: 10 | B19: Рулон х/к 0.9*1250 | C19: кг | D19: 1.977 | E19: 69.58 | F19: =E19*D19 -> 137.55966
A20: 11 | B20: Круг лепестковый 125*22мм | C20: шт | D20: 0.201 | E20: 64.68 | F20: =E20*D20 -> 13.00068
A21: 12 | B21: Углекислота | C21: шт | D21: 0.015 | E21: 1000 | F21: =E21*D21 -> 15
A22: 13 | B22: Проволока СВ08 Г2С 0.8 омедн. | C22: кг | D22: 0.229 | E22: 158.33 | F22: =E22*D22 -> 36.25757
A23: 14 | B23: Петля гаражная 10*60 | C23: шт | D23: 1 | E23: 18.95 | F23: =E23*D23 -> 18.95
A24: 15 | B24: Лист 1.2мм | C24: кг | D24: 8.235 | E24: 69.17 | F24: =E24*D24 -> 569.61495
A25: 16 | B25: Лист 2.0мм | C25: кг | D25: 2.408 | E25: 69.17 | F25: =E25*D25 -> 166.56136
A26: 17 | B26: Общая химия | C26: кг | D26: 0.013 | E26: 278 | F26: =E26*D26 -> 3.614
B27: Всего на материалы без НДС | F27: =SUM(F10:F26) -> 1569.1385
B28: Наценка на материалы | E28: 0.01 | F28: =F27*E28 -> 15.691385
B29: Итого | F29: =SUM(F27,F28) -> 1584.8298
A30: 2 | B30: Основная з/п цеховых рабочих | E30: 0.11 | F30: =F29*E30 -> 174.33128
B31: Дополнительная з/п | E31: 0.14 | F31: =F30*E31 -> 24.40638
B32: Отчисления на социальные нужды цеховые | E32: 0.309 | F32: =(F30+F31)*E32 -> 61.409938
B33: Отчисления на социальные нужды Дополнительная з/п
A34: 3 | B34: Общепроизводственные (накладные) расходы | E34: 1.5 | F34: =F30*E34 -> 261.49692
A35: 4 | B35: Цеховая себестоимость | F35: =F29+F30+F31+F32+F33+F34 -> 2106.4744
A36: 5 | B36: Общехозяйственные расходы | E36: 1 | F36: =F30*E36 -> 174.33128
E37: 0.8 | F37: =F30*E37 -> 139.46503
A38: 6 | B38: СЕБЕСТОИМОСТЬ | F38: =F35+F36 -> 2280.8057
F39: =F35+F37 -> 2245.9394
A40: 7 | B40: Прибыль | E40: 0.4 | F40: =F38*E40 -> 912.32226
E41: 0.07 | F41: =F38*E41 -> 159.6564
A42: 8 | B42: Расходы на упаковку | F42: 160.78
B43: Цена без НДС | F43: =F38+F40+F42 -> 3353.9079
F44: =F39+F41+F42 -> 2566.3758
B45: НДС | E45: 0.22 | F45: =F43*E45 -> 737.85974
E46: 0.22 | F46: =F44*E46 -> 564.60267
B47: ОТПУСКНАЯ ЦЕНА | E47: розн | F47: =F43+F45 -> 4091.7677
E48: опт | F48: =F44+F46 -> 3130.9785
B51: Главный бухгалтер ________________

Sheet СМ-30Э
F1: УТВЕРЖДАЮ
F2: генеральный директор
F3: ООО "Вика-Двина"
F4: В.А. Иванов _________
A5: Калькуляция | F5: подпись
A7: Сейф мебельный СМ-25Э
A9: № | B9: Наименование статьи затрат | C9: Ед.изм. | D9: Кол-во | E9: Цена. руб | F9: Стоимость. руб
A10: 1 | B10: Заклепка вытяжная 4.0*10 (не использовать) | C10: тыс. шт/1000 шт | D10: 0.012 | E10: 616.67 | F10: =E10*D10 -> 7.40004
A11: 2 | B11: Жгут нейлон. 2.5-3*150 | C11: тыс. шт/1000 шт | D11: 0.001 | E11: 468.33 | F11: =E11*D11 -> 0.46833
A12: 3 | B12: Батарейка АА (4 шт) | C12: упак | D12: 1 | E12: 84.78 | F12: =E12*D12 -> 84.78
A13: 4 | B13: Шайба 6 цинк DIN 125 | C13: кг | D13: 0.003 | E13: 154 | F13: =E13*D13 -> 0.462
A14: 5 | B14: Паспорт на продукцию | C14: шт | D14: 1 | E14: 1.4 | F14: =E14*D14 -> 1.4
A15: 6 | B15: Наклейка с заливной смолой 37х23мм "Cerera" | C15: шт | D15: 1 | F15: =E15*D15 -> 0
A16: 7 | B16: Стойка для платы CS-10 | C16: шт | D16: 4 | E16: 0.92 | F16: =E16*D16 -> 3.68
A17: 8 | B17: Саморезы 4.2*13 пресс-шайба острый | C17: шт | D17: 4 | E17: 0.24 | F17: =E17*D17 -> 0.96
A18: 9 | B18: Этикетка 100*60 полуглянец | C18: шт | D18: 1 | F18: =E18*D18 -> 0
A19: 10 | B19: Круг 6 L=4м | C19: кг | D19: 0.014 | E19: 133.33 | F19: =E19*D19 -> 1.86662
A20: 11 | B20: Замок электронный сейфовый LS026 | C20: компл | D20: 1 | E20: 537.5 | F20: =E20*D20 -> 537.5
A21: 12 | B21: ELB52I EE BUG GRIGIO 7035 GL TR св.серая | C21: кг | D21: 0.388 | E21: 202.75 | F21: =E21*D21 -> 78.667
A22: 13 | B22: Рулон х/к 0.9*1250 | C22: кг | D22: 1.714 | E22: 69.58 | F22: =E22*D22 -> 119.26012
A23: 14 | B23: Круг лепестковый 125*22мм | C23: шт | D23: 0.175 | E23: 64.68 | F23: =E23*D23 -> 11.319
A24: 15 | B24: Углекислота | C24: шт | D24: 0.014 | E24: 1000 | F24: =E24*D24 -> 14
A25: 16 | B25: Проволока СВ08 Г2С 0.8 омедн. | C25: кг | D25: 0.211 | E25: 158.33 | F25: =E25*D25 -> 33.40763
A26: 17 | B26: Ковролин | C26: м2 | D26: 0.11 | E26: 638.33 | F26: =E26*D26 -> 70.2163
A27: 18 | B27: Лист 2.0мм | C27: кг | D27: 1.574 | E27: 69.17 | F27: =E27*D27 -> 108.87358
A28: 19 | B28: Рулон оцин 0.5*1250 | C28: кг | D28: 0.004 | E28: 85.83 | F28: =E28*D28 -> 0.34332
A29: 20 | B29: Лист 1.2мм | C29: кг | D29: 6.604 | E29: 69.17 | F29: =E29*D29 -> 456.79868
A30: 21 | B30: Петля гаражная 10*60 | C30: шт | D30: 1 | E30: 18.95 | F30: =E30*D30 -> 18.95
A31: 22 | B31: Общая химия | C31: кг | D31: 0.011 | E31: 290 | F31: =E31*D31 -> 3.19
B32: Всего на материалы без НДС | F32: =SUM(F10:F31) -> 1553.5426
B33: Наценка на материалы | E33: 0.01 | F33: =F32*E33 -> 15.535426
B34: Итого | F34: =SUM(F32,F33) -> 1569.078
A35: 2 | B35: Основная з/п цеховых рабочих | E35: 0.11 | F35: =F34*E35 -> 172.59859
B36: Дополнительная з/п | E36: 0.14 | F36: =F35*E36 -> 24.163802
B37: Отчисления на социальные нужды цеховые | E37: 0.309 | F37: =(F35+F36)*E37 -> 60.799578
B38: Отчисления на социальные нужды Дополнительная з/п
A39: 3 | B39: Общепроизводственные (накладные) расходы | E39: 1.5 | F39: =F35*E39 -> 258.89788
A40: 4 | B40: Цеховая себестоимость | F40: =F34+F35+F36+F37+F38+F39 -> 2085.5379
A41: 5 | B41: Общехозяйственные расходы | E41: 1 | F41: =F35*E41 -> 172.59859
E42: 0.8 | F42: =F35*E42 -> 138.07887
A43: 6 | B43: СЕБЕСТОИМОСТЬ | F43: =F40+F41 -> 2258.1365
F44: =F40+F42 -> 2223.6168
A45: 7 | B45: Прибыль | E45: 0.4 | F45: =F43*E45 -> 903.25459
E46: 0.07 | F46: =F43*E46 -> 158.06955
A47: 8 | B47: Расходы на упаковку | F47: 114.48
B48: Цена без НДС | F48: =F43+F45+F47 -> 3275.8711
F49: =F44+F46+F47 -> 2496.1663
B50: НДС | E50: 0.22 | F50: =F48*E50 -> 720.69163
E51: 0.22 | F51: =F49*E51 -> 549.15659
B52: ОТПУСКНАЯ ЦЕНА | E52: розн | F52: =F48+F50 -> 3996.5627
E53: опт | F53: =F49+F51 -> 3045.3229
B56: Главный бухгалтер ________________

Sheet СМ-30
F1: УТВЕРЖДАЮ
F2: генеральный директор
F3: ООО "Вика-Двина"
F4: В.А. Иванов _________
A5: Калькуляция | F5: подпись
A7: Сейф мебельный СМ-30
A9: № | B9: Наименование статьи затрат | C9: Ед.изм. | D9: Кол-во | E9: Цена. руб | F9: Стоимость. руб
A10: 1 | B10: Заклепка вытяжная 4.0*10 (не использовать) | C10: тыс. шт/1000 шт | D10: 0.009 | E10: 616.67 | F10: =E10*D10 -> 5.55003
A11: 2 | B11: Жгут нейлон. 2.5-3*150 | C11: тыс. шт/1000 шт | D11: 0.001 | E11: 468.33 | F11: =E11*D11 -> 0.46833
A12: 3 | B12: Шайба 6 цинк DIN 125 | C12: кг | D12: 0.003 | E12: 154 | F12: =E12*D12 -> 0.462
A13: 4 | B13: Паспорт на продукцию | C13: шт | D13: 1 | E13: 1.4 | F13: =E13*D13 -> 1.4
A14: 5 | B14: Наклейка с заливной смолой 37х23мм "Cerera" | C14: шт | D14: 1 | F14: =E14*D14 -> 0
A15: 6 | B15: Замок врезной САМ 8-6 (73100) | C15: шт | D15: 1 | E15: 495 | F15: =E15*D15 -> 495
A16: 7 | B16: Этикетка 100*60 полуглянец | C16: шт | D16: 1 | F16: =E16*D16 -> 0
A17: 8 | B17: Круг 6 L=4м | C17: кг | D17: 0.014 | E17: 133.33 | F17: =E17*D17 -> 1.86662
A18: 9 | B18: ELB52I EE BUG GRIGIO 7035 GL TR св.серая | C18: кг | D18: 0.378 | E18: 202.75 | F18: =E18*D18 -> 76.6395
A19: 10 | B19: Рулон х/к 0.9*1250 | C19: кг | D19: 1.604 | E19: 69.58 | F19: =E19*D19 -> 111.60632
A20: 11 | B20: Петля гаражная 10*60 | C20: шт | D20: 1 | E20: 18.95 | F20: =E20*D20 -> 18.95
A21: 12 | B21: Лист 1.2мм | C21: кг | D21: 6.327 | E21: 69.17 | F21: =E21*D21 -> 437.63859
A22: 13 | B22: Лист 2.0мм | C22: кг | D22: 1.512 | E22: 69.17 | F22: =E22*D22 -> 104.58504
A23: 14 | B23: Общая химия | C23: кг | D23: 0.01 | E23: 290 | F23: =E23*D23 -> 2.9
B24: Всего на материалы без НДС | F24: =SUM(F10:F23) -> 1257.0664
B25: Наценка на материалы | E25: 0.01 | F25: =F24*E25 -> 12.570664
B26: Итого | F26: =SUM(F24,F25) -> 1269.6371
A27: 2 | B27: Основная з/п цеховых рабочих | E27: 0.11 | F27: =F26*E27 -> 139.66008
B28: Дополнительная з/п | E28: 0.14 | F28: =F27*E28 -> 19.552411
B29: Отчисления на социальные нужды цеховые | E29: 0.309 | F29: =(F27+F28)*E29 -> 49.19666
B30: Отчисления на социальные нужды Дополнительная з/п
A31: 3 | B31: Общепроизводственные (накладные) расходы | E31: 1.5 | F31: =F27*E31 -> 209.49012
A32: 4 | B32: Цеховая себестоимость | F32: =F26+F27+F28+F29+F30+F31 -> 1687.5364
A33: 5 | B33: Общехозяйственные расходы | E33: 1 | F33: =F27*E33 -> 139.66008
E34: 0.8 | F34: =F27*E34 -> 111.72806
A35: 6 | B35: СЕБЕСТОИМОСТЬ | F35: =F32+F33 -> 1827.1964
F36: =F32+F34 -> 1799.2644
A37: 7 | B37: Прибыль | E37: 0.4 | F37: =F35*E37 -> 730.87858
E38: 0.07 | F38: =F35*E38 -> 127.90375
A39: 8 | B39: Расходы на упаковку | F39: 122.56
B40: Цена без НДС | F40: =F35+F37+F39 -> 2680.635
F41: =F36+F38+F39 -> 2049.7282
B42: НДС | E42: 0.22 | F42: =F40*E42 -> 589.73971
E43: 0.22 | F43: =F41*E43 -> 450.9402
B44: ОТПУСКНАЯ ЦЕНА | E44: розн | F44: =F40+F42 -> 3270.3747
E45: опт | F45: =F41+F43 -> 2500.6684
B48: Главный бухгалтер ________________

Sheet СМ-25Э
F1: УТВЕРЖДАЮ
F2: генеральный директор
F3: ООО "Вика-Двина"
F4: В.А. Иванов _________
A5: Калькуляция | F5: подпись
A7: Сейф мебельный СМ-25Э
A9: № | B9: Наименование статьи затрат | C9: Ед.изм. | D9: Кол-во | E9: Цена. руб | F9: Стоимость. руб
A10: 1 | B10: Заклепка вытяжная 4.0*10 (не использовать) | C10: тыс. шт/1000 шт | D10: 0.01 | E10: 616.67 | F10: =E10*D10 -> 6.1667
A11: 2 | B11: Жгут нейлон. 2.5-3*150 | C11: тыс. шт/1000 шт | D11: 0.001 | E11: 468.33 | F11: =E11*D11 -> 0.46833
A12: 3 | B12: Батарейка АА (4 шт) | C12: упак | D12: 1 | E12: 84.78 | F12: =E12*D12 -> 84.78
A13: 4 | B13: Шайба 6 цинк DIN 125 | C13: кг | D13: 0.003 | E13: 154 | F13: =E13*D13 -> 0.462
A14: 5 | B14: Паспорт на продукцию | C14: шт | D14: 1 | E14: 1.4 | F14: =E14*D14 -> 1.4
A15: 6 | B15: Наклейка с заливной смолой 37х23мм "Cerera" | C15: шт | D15: 1 | F15: =E15*D15 -> 0
A16: 7 | B16: Стойка для платы CS-10 | C16: шт | D16: 4 | E16: 0.92 | F16: =E16*D16 -> 3.68
A17: 8 | B17: Саморезы 4.2*13 пресс-шайба острый | C17: шт | D17: 4 | E17: 0.24 | F17: =E17*D17 -> 0.96
A18: 9 | B18: Этикетка 100*60 полуглянец | C18: шт | D18: 1 | F18: =E18*D18 -> 0
A19: 10 | B19: Круг 6 L=4м | C19: кг | D19: 0.014 | E19: 133.33 | F19: =E19*D19 -> 1.86662
A20: 11 | B20: Замок электронный сейфовый LS026 | C20: компл | D20: 1 | E20: 537.5 | F20: =E20*D20 -> 537.5
A21: 12 | B21: ELB52I EE BUG GRIGIO 7035 GL TR св.серая | C21: кг | D21: 0.295 | E21: 202.75 | F21: =E21*D21 -> 59.81125
A22: 13 | B22: Рулон х/к 0.9*1250 | C22: кг | D22: 1.315 | E22: 69.58 | F22: =E22*D22 -> 91.4977
A23: 14 | B23: Ковролин | C23: м2 | D23: 0.084 | E23: 638.33 | F23: =E23*D23 -> 53.61972
A24: 15 | B24: Лист 2.0мм | C24: кг | D24: 1.195 | E24: 69.17 | F24: =E24*D24 -> 82.65815
A25: 16 | B25: Рулон оцин 0.5*1250 | C25: кг | D25: 0.004 | E25: 85.83 | F25: =E25*D25 -> 0.34332
A26: 17 | B26: Лист 1.2мм | C26: кг | D26: 5.072 | E26: 69.17 | F26: =E26*D26 -> 350.83024
A27: 18 | B27: Петля гаражная 10*60 | C27: шт | D27: 1 | E27: 18.95 | F27: =E27*D27 -> 18.95
A28: 19 | B28: Общая химия | C28: кг | D28: 0.008 | E28: 290 | F28: =E28*D28 -> 2.32
B29: Всего на материалы без НДС | F29: =SUM(F10:F28) -> 1297.314
B30: Наценка на материалы | E30: 0.01 | F30: =F29*E30 -> 12.97314
B31: Итого | F31: =SUM(F29,F30) -> 1310.2872
A32: 2 | B32: Основная з/п цеховых рабочих | E32: 0.11 | F32: =F31*E32 -> 144.13159
B33: Дополнительная з/п | E33: 0.14 | F33: =F32*E33 -> 20.178422
B34: Отчисления на социальные нужды цеховые | E34: 0.309 | F34: =(F32+F33)*E34 -> 50.771793
B35: Отчисления на социальные нужды Дополнительная з/п
A36: 3 | B36: Общепроизводственные (накладные) расходы | E36: 1.5 | F36: =F32*E36 -> 216.19738
A37: 4 | B37: Цеховая себестоимость | F37: =F31+F32+F33+F34+F35+F36 -> 1741.5664
A38: 5 | B38: Общехозяйственные расходы | E38: 1 | F38: =F32*E38 -> 144.13159
E39: 0.8 | F39: =F32*E39 -> 115.30527
A40: 6 | B40: СЕБЕСТОИМОСТЬ | F40: =F37+F38 -> 1885.6979
F41: =F37+F39 -> 1856.8716
A42: 7 | B42: Прибыль | E42: 0.4 | F42: =F40*E42 -> 754.27918
E43: 0.07 | F43: =F40*E43 -> 131.99886
A44: 8 | B44: Расходы на упаковку | F44: 114.48
B45: Цена без НДС | F45: =F40+F42+F44 -> 2754.4571
F46: =F41+F43+F44 -> 2103.3505
B47: НДС | E47: 0.22 | F47: =F45*E47 -> 605.98057
E48: 0.22 | F48: =F46*E48 -> 462.73711
B49: ОТПУСКНАЯ ЦЕНА | E49: розн | F49: =F45+F47 -> 3360.4377
E50: опт | F50: =F46+F48 -> 2566.0876
B53: Главный бухгалтер ________________

Sheet СМ-25
F1: УТВЕРЖДАЮ
F2: генеральный директор
F3: ООО "Вика-Двина"
F4: В.А. Иванов _________
A5: Калькуляция | F5: подпись
A7: Сейф мебельный СМ-25
A9: № | B9: Наименование статьи затрат | C9: Ед.изм. | D9: Кол-во | E9: Цена. руб | F9: Стоимость. руб
A10: 1 | B10: Заклепка вытяжная 4.0*10 (не использовать) | C10: тыс. шт/1000 шт | D10: 0.007 | E10: 616.67 | F10: =E10*D10 -> 4.31669
A11: 2 | B11: Жгут нейлон. 2.5-3*150 | C11: тыс. шт/1000 шт | D11: 0.001 | E11: 468.33 | F11: =E11*D11 -> 0.46833
A12: 3 | B12: Шайба 6 цинк DIN 125 | C12: кг | D12: 0.003 | E12: 154 | F12: =E12*D12 -> 0.462
A13: 4 | B13: Паспорт на продукцию | C13: шт | D13: 1 | E13: 1.4 | F13: =E13*D13 -> 1.4
A14: 5 | B14: Наклейка с заливной смолой 37х23мм "Cerera" | C14: шт | D14: 1 | F14: =E14*D14 -> 0
A15: 6 | B15: Замок врезной САМ 8-6 (73100) | C15: шт | D15: 1 | E15: 495 | F15: =E15*D15 -> 495
A16: 7 | B16: Этикетка 100*60 полуглянец | C16: шт | D16: 1 | F16: =E16*D16 -> 0
A17: 8 | B17: Круг 6 L=4м | C17: кг | D17: 0.014 | E17: 133.33 | F17: =E17*D17 -> 1.86662
A18: 9 | B18: ELB52I EE BUG GRIGIO 7035 GL TR св.серая | C18: кг | D18: 0.283 | E18: 202.75 | F18: =E18*D18 -> 57.37825
A19: 10 | B19: Рулон х/к 0.9*1250 | C19: кг | D19: 1.216 | E19: 69.58 | F19: =E19*D19 -> 84.60928
A20: 11 | B20: Петля гаражная 10*60 | C20: шт | D20: 1 | E20: 18.95 | F20: =E20*D20 -> 18.95
A21: 12 | B21: Лист 1.2мм | C21: кг | D21: 4.724 | E21: 69.17 | F21: =E21*D21 -> 326.75908
A22: 13 | B22: Лист 2.0мм | C22: кг | D22: 1.133 | E22: 69.17 | F22: =E22*D22 -> 78.36961
A23: 14 | B23: Общая химия | C23: кг | D23: 0.007 | E23: 290 | F23: =E23*D23 -> 2.03
B24: Всего на материалы без НДС | F24: =SUM(F10:F23) -> 1071.6099
B25: Наценка на материалы | E25: 0.01 | F25: =F24*E25 -> 10.716099
B26: Итого | F26: =SUM(F24,F25) -> 1082.326
A27: 2 | B27: Основная з/п цеховых рабочих | E27: 0.11 | F27: =F26*E27 -> 119.05586
B28: Дополнительная з/п | E28: 0.14 | F28: =F27*E28 -> 16.66782
B29: Отчисления на социальные нужды цеховые | E29: 0.309 | F29: =(F27+F28)*E29 -> 41.938616
B30: Отчисления на социальные нужды Дополнительная з/п
A31: 3 | B31: Общепроизводственные (накладные) расходы | E31: 1.5 | F31: =F27*E31 -> 178.58378
A32: 4 | B32: Цеховая себестоимость | F32: =F26+F27+F28+F29+F30+F31 -> 1438.572
A33: 5 | B33: Общехозяйственные расходы | E33: 1 | F33: =F27*E33 -> 119.05586
E34: 0.8 | F34: =F27*E34 -> 95.244684
A35: 6 | B35: СЕБЕСТОИМОСТЬ | F35: =F32+F33 -> 1557.6279
F36: =F32+F34 -> 1533.8167
A37: 7 | B37: Прибыль | E37: 0.4 | F37: =F35*E37 -> 623.05116
E38: 0.07 | F38: =F35*E38 -> 109.03395
A39: 8 | B39: Расходы на упаковку | F39: 114.48
B40: Цена без НДС | F40: =F35+F37+F39 -> 2295.159
F41: =F36+F38+F39 -> 1757.3307
B42: НДС | E42: 0.22 | F42: =F40*E42 -> 504.93499
E43: 0.22 | F43: =F41*E43 -> 386.61275
B44: ОТПУСКНАЯ ЦЕНА | E44: розн | F44: =F40+F42 -> 2800.094
E45: опт | F45: =F41+F43 -> 2143.9434
B48: Главный бухгалтер ________________

Sheet СМ-23Э
F1: УТВЕРЖДАЮ
F2: генеральный директор
F3: ООО "Вика-Двина"
F4: В.А. Иванов _________
A5: Калькуляция | F5: подпись
A7: Сейф мебельный СМ-23Э
A9: № | B9: Наименование статьи затрат | C9: Ед.изм. | D9: Кол-во | E9: Цена. руб | F9: Стоимость. руб
A10: 1 | B10: Заклепка вытяжная 4.0*10 (не использовать) | C10: тыс. шт/1000 шт | D10: 0.011 | E10: 616.67 | F10: =E10*D10 -> 6.78337
A11: 2 | B11: Жгут нейлон. 2.5-3*150 | C11: тыс. шт/1000 шт | D11: 0.001 | E11: 468.33 | F11: =E11*D11 -> 0.46833
A12: 3 | B12: Батарейка АА (4 шт) | C12: упак | D12: 1 | E12: 84.78 | F12: =E12*D12 -> 84.78
A13: 4 | B13: Шайба 6 цинк DIN 125 | C13: кг | D13: 0.003 | E13: 154 | F13: =E13*D13 -> 0.462
A14: 5 | B14: Паспорт на продукцию | C14: шт | D14: 1 | E14: 1.4 | F14: =E14*D14 -> 1.4
A15: 6 | B15: Наклейка с заливной смолой 37х23мм "Cerera" | C15: шт | D15: 1 | F15: =E15*D15 -> 0
A16: 7 | B16: Стойка для платы CS-10 | C16: шт | D16: 4 | E16: 0.92 | F16: =E16*D16 -> 3.68
A17: 8 | B17: Саморезы 4.2*13 пресс-шайба острый | C17: шт | D17: 4 | E17: 0.24 | F17: =E17*D17 -> 0.96
A18: 9 | B18: Этикетка 100*60 полуглянец | C18: шт | D18: 1 | F18: =E18*D18 -> 0
A19: 10 | B19: Круг 6 L=4м | C19: кг | D19: 0.014 | E19: 133.33 | F19: =E19*D19 -> 1.86662
A20: 11 | B20: Замок электронный сейфовый LS026 | C20: компл | D20: 1 | E20: 537.5 | F20: =E20*D20 -> 537.5
A21: 12 | B21: ELB52I EE BUG GRIGIO 7035 GL TR св.серая | C21: кг | D21: 0.37 | E21: 202.75 | F21: =E21*D21 -> 75.0175
A22: 13 | B22: Рулон х/к 0.9*1250 | C22: кг | D22: 1.584 | E22: 69.58 | F22: =E22*D22 -> 110.21472
A23: 14 | B23: Ковролин | C23: м2 | D23: 0.132 | E23: 638.33 | F23: =E23*D23 -> 84.25956
A24: 15 | B24: Лист 2.0мм | C24: кг | D24: 1.255 | E24: 69.17 | F24: =E24*D24 -> 86.80835
A25: 16 | B25: Рулон оцин 0.5*1250 | C25: кг | D25: 0.004 | E25: 85.83 | F25: =E25*D25 -> 0.34332
A26: 17 | B26: Лист 1.2мм | C26: кг | D26: 6.335 | E26: 69.17 | F26: =E26*D26 -> 438.19195
A27: 18 | B27: Петля гаражная 10*60 | C27: шт | D27: 1 | E27: 18.95 | F27: =E27*D27 -> 18.95
A28: 19 | B28: Общая химия | C28: кг | D28: 0.01 | E28: 290 | F28: =E28*D28 -> 2.9
B29: Всего на материалы без НДС | F29: =SUM(F10:F28) -> 1454.5857
B30: Наценка на материалы | E30: 0.01 | F30: =F29*E30 -> 14.545857
B31: Итого | F31: =SUM(F29,F30) -> 1469.1316
A32: 2 | B32: Основная з/п цеховых рабочих | E32: 0.11 | F32: =F31*E32 -> 161.60447
B33: Дополнительная з/п | E33: 0.14 | F33: =F32*E33 -> 22.624626
B34: Отчисления на социальные нужды цеховые | E34: 0.309 | F34: =(F32+F33)*E34 -> 56.926792
B35: Отчисления на социальные нужды Дополнительная з/п
A36: 3 | B36: Общепроизводственные (накладные) расходы | E36: 1.5 | F36: =F32*E36 -> 242.40671
A37: 4 | B37: Цеховая себестоимость | F37: =F31+F32+F33+F34+F35+F36 -> 1952.6942
A38: 5 | B38: Общехозяйственные расходы | E38: 1 | F38: =F32*E38 -> 161.60447
E39: 0.8 | F39: =F32*E39 -> 129.28358
A40: 6 | B40: СЕБЕСТОИМОСТЬ | F40: =F37+F38 -> 2114.2987
F41: =F37+F39 -> 2081.9778
A42: 7 | B42: Прибыль | E42: 0.4 | F42: =F40*E42 -> 845.71946
E43: 0.07 | F43: =F40*E43 -> 148.00091
A44: 8 | B44: Расходы на упаковку | F44: 144.12
B45: Цена без НДС | F45: =F40+F42+F44 -> 3104.1381
F46: =F41+F43+F44 -> 2374.0987
B47: НДС | E47: 0.22 | F47: =F45*E47 -> 682.91038
E48: 0.22 | F48: =F46*E48 -> 522.30171
B49: ОТПУСКНАЯ ЦЕНА | E49: розн | F49: =F45+F47 -> 3787.0485
E50: опт | F50: =F46+F48 -> 2896.4004
B53: Главный бухгалтер ________________

Sheet СМ-23
F1: УТВЕРЖДАЮ
F2: генеральный директор
F3: ООО "Вика-Двина"
F4: В.А. Иванов _________
A5: Калькуляция | F5: подпись
A7: Сейф мебельный СМ-23
A9: № | B9: Наименование статьи затрат | C9: Ед.изм. | D9: Кол-во | E9: Цена. руб | F9: Стоимость. руб
A10: 1 | B10: Заклепка вытяжная 4.0*10 (не использовать) | C10: тыс. шт/1000 шт | D10: 0.008 | E10: 616.67 | F10: =E10*D10 -> 4.93336
A11: 2 | B11: Жгут нейлон. 2.5-3*150 | C11: тыс. шт/1000 шт | D11: 0.001 | E11: 468.33 | F11: =E11*D11 -> 0.46833
A12: 3 | B12: Шайба 6 цинк DIN 125 | C12: кг | D12: 0.003 | E12: 154 | F12: =E12*D12 -> 0.462
A13: 4 | B13: Паспорт на продукцию | C13: шт | D13: 1 | E13: 1.4 | F13: =E13*D13 -> 1.4
A14: 5 | B14: Наклейка с заливной смолой 37х23мм "Cerera" | C14: шт | D14: 1 | F14: =E14*D14 -> 0
A15: 6 | B15: Замок врезной САМ 8-6 (73100) | C15: шт | D15: 1 | E15: 495 | F15: =E15*D15 -> 495
A16: 7 | B16: Этикетка 100*60 полуглянец | C16: шт | D16: 1 | F16: =E16*D16 -> 0
A17: 8 | B17: Круг 6 L=4м | C17: кг | D17: 0.014 | E17: 133.33 | F17: =E17*D17 -> 1.86662
A18: 9 | B18: ELB52I EE BUG GRIGIO 7035 GL TR св.серая | C18: кг | D18: 0.361 | E18: 202.75 | F18: =E18*D18 -> 73.19275
A19: 10 | B19: Круг лепестковый 125*22мм | C19: шт | D19: 0.192 | E19: 64.68 | F19: =E19*D19 -> 12.41856
A20: 11 | B20: Углекислота | C20: шт | D20: 0.014 | E20: 1000 | F20: =E20*D20 -> 14
A21: 12 | B21: Проволока СВ08 Г2С 0.8 омедн. | C21: кг | D21: 0.12 | E21: 158.33 | F21: =E21*D21 -> 18.9996
A22: 13 | B22: Рулон х/к 0.9*1250 | C22: кг | D22: 1.476 | E22: 69.58 | F22: =E22*D22 -> 102.70008
A23: 14 | B23: Петля гаражная 10*60 | C23: шт | D23: 1 | E23: 18.95 | F23: =E23*D23 -> 18.95
A24: 15 | B24: Лист 1.2мм | C24: кг | D24: 6.075 | E24: 69.17 | F24: =E24*D24 -> 420.20775
A25: 16 | B25: Лист 2.0мм | C25: кг | D25: 1.193 | E25: 69.17 | F25: =E25*D25 -> 82.51981
A26: 17 | B26: Общая химия | C26: кг | D26: 0.009 | E26: 290 | F26: =E26*D26 -> 2.61
B27: Всего на материалы без НДС | F27: =SUM(F10:F26) -> 1249.7289
B28: Наценка на материалы | E28: 0.01 | F28: =F27*E28 -> 12.497289
B29: Итого | F29: =SUM(F27,F28) -> 1262.2261
A30: 2 | B30: Основная з/п цеховых рабочих | E30: 0.11 | F30: =F29*E30 -> 138.84488
B31: Дополнительная з/п | E31: 0.14 | F31: =F30*E31 -> 19.438283
B32: Отчисления на социальные нужды цеховые | E32: 0.309 | F32: =(F30+F31)*E32 -> 48.909496
B33: Отчисления на социальные нужды Дополнительная з/п
A34: 3 | B34: Общепроизводственные (накладные) расходы | E34: 1.5 | F34: =F30*E34 -> 208.26731
A35: 4 | B35: Цеховая себестоимость | F35: =F29+F30+F31+F32+F33+F34 -> 1677.6861
A36: 5 | B36: Общехозяйственные расходы | E36: 1 | F36: =F30*E36 -> 138.84488
E37: 0.8 | F37: =F30*E37 -> 111.0759
A38: 6 | B38: СЕБЕСТОИМОСТЬ | F38: =F35+F36 -> 1816.531
F39: =F35+F37 -> 1788.762
A40: 7 | B40: Прибыль | E40: 0.4 | F40: =F38*E40 -> 726.6124
E41: 0.07 | F41: =F38*E41 -> 127.15717
A42: 8 | B42: Расходы на упаковку | F42: 144.12
B43: Цена без НДС | F43: =F38+F40+F42 -> 2687.2634
F44: =F39+F41+F42 -> 2060.0392
B45: НДС | E45: 0.22 | F45: =F43*E45 -> 591.19795
E46: 0.22 | F46: =F44*E46 -> 453.20862
B47: ОТПУСКНАЯ ЦЕНА | E47: розн | F47: =F43+F45 -> 3278.4613
E48: опт | F48: =F44+F46 -> 2513.2478
B51: Главный бухгалтер ________________

Sheet СМ-20
F1: УТВЕРЖДАЮ
F2: генеральный директор
F3: ООО "Вика-Двина"
F4: В.А. Иванов _________
A5: Калькуляция | F5: подпись
A7: Сейф мебельный СМ-20
A9: № | B9: Наименование статьи затрат | C9: Ед.изм. | D9: Кол-во | E9: Цена. руб | F9: Стоимость. руб
A10: 1 | B10: Заклепка вытяжная 4.0*10 (не использовать) | C10: тыс. шт/1000 шт | D10: 0.006 | E10: 616.67 | F10: =E10*D10 -> 3.70002
A11: 2 | B11: Жгут нейлон. 2.5-3*150 | C11: тыс. шт/1000 шт | D11: 0.001 | E11: 468.33 | F11: =E11*D11 -> 0.46833
A12: 3 | B12: Шайба 6 цинк DIN 125 | C12: кг | D12: 0.003 | E12: 154 | F12: =E12*D12 -> 0.462
A13: 4 | B13: Паспорт на продукцию | C13: шт | D13: 1 | E13: 1.4 | F13: =E13*D13 -> 1.4
A14: 5 | B14: Наклейка с заливной смолой 37х23мм "Cerera" | C14: шт | D14: 1 | F14: =E14*D14 -> 0
A15: 6 | B15: Этикетка 100*60 полуглянец | C15: шт | D15: 1 | F15: =E15*D15 -> 0
A16: 7 | B16: Круг 6 L=4м | C16: кг | D16: 0.014 | E16: 133.33 | F16: =E16*D16 -> 1.86662
A17: 8 | B17: ELB52I EE BUG GRIGIO 7035 GL TR св.серая | C17: кг | D17: 0.198 | E17: 202.75 | F17: =E17*D17 -> 40.1445
A18: 9 | B18: Рулон х/к 0.9*1250 | C18: кг | D18: 0.863 | E18: 69.58 | F18: =E18*D18 -> 60.04754
A19: 10 | B19: Замок врезной САМ 8-6 (73100) | C19: шт | D19: 1 | E19: 495 | F19: =E19*D19 -> 495
A20: 11 | B20: Лист 1.2мм | C20: кг | D20: 3.98 | E20: 69.17 | F20: =E20*D20 -> 275.2966
A21: 12 | B21: Лист 2.0мм | C21: кг | D21: 0.774 | E21: 69.17 | F21: =E21*D21 -> 53.53758
A22: 13 | B22: Петля гаражная 10*60 | C22: шт | D22: 1 | E22: 18.95 | F22: =E22*D22 -> 18.95
A23: 14 | B23: Общая химия | C23: кг | D23: 0.006 | E23: 290 | F23: =E23*D23 -> 1.74
B24: Всего на материалы без НДС | F24: =SUM(F10:F23) -> 952.61319
B25: Наценка на материалы | E25: 0.01 | F25: =F24*E25 -> 9.5261319
B26: Итого | F26: =SUM(F24,F25) -> 962.13932
A27: 2 | B27: Основная з/п цеховых рабочих | E27: 0.11 | F27: =F26*E27 -> 105.83533
B28: Дополнительная з/п | E28: 0.14 | F28: =F27*E28 -> 14.816946
B29: Отчисления на социальные нужды цеховые | E29: 0.309 | F29: =(F27+F28)*E29 -> 37.281552
B30: Отчисления на социальные нужды Дополнительная з/п
A31: 3 | B31: Общепроизводственные (накладные) расходы | E31: 1.5 | F31: =F27*E31 -> 158.75299
A32: 4 | B32: Цеховая себестоимость | F32: =F26+F27+F28+F29+F30+F31 -> 1278.8261
A33: 5 | B33: Общехозяйственные расходы | E33: 1 | F33: =F27*E33 -> 105.83533
E34: 0.8 | F34: =F27*E34 -> 84.66826
A35: 6 | B35: СЕБЕСТОИМОСТЬ | F35: =F32+F33 -> 1384.6615
F36: =F32+F34 -> 1363.4944
A37: 7 | B37: Прибыль | E37: 0.4 | F37: =F35*E37 -> 553.86458
E38: 0.07 | F38: =F35*E38 -> 96.926302
A39: 8 | B39: Расходы на упаковку | F39: 107.08
B40: Цена без НДС | F40: =F35+F37+F39 -> 2045.606
F41: =F36+F38+F39 -> 1567.5007
B42: НДС | E42: 0.22 | F42: =F40*E42 -> 450.03333
E43: 0.22 | F43: =F41*E43 -> 344.85015
B44: ОТПУСКНАЯ ЦЕНА | E44: розн | F44: =F40+F42 -> 2495.6394
E45: опт | F45: =F41+F43 -> 1912.3508
B48: Главный бухгалтер ________________

Sheet СМ-20Э
F1: УТВЕРЖДАЮ
F2: генеральный директор
F3: ООО "Вика-Двина"
F4: В.А. Иванов _________
A5: Калькуляция | F5: подпись
A7: Сейф мебельный СМ-20Э
A9: № | B9: Наименование статьи затрат | C9: Ед.изм. | D9: Кол-во | E9: Цена. руб | F9: Стоимость. руб
A10: 1 | B10: Заклепка вытяжная 4.0*10 (не использовать) | C10: тыс. шт/1000 шт | D10: 0.009 | E10: 616.67 | F10: =E10*D10 -> 5.55003
A11: 2 | B11: Жгут нейлон. 2.5-3*150 | C11: тыс. шт/1000 шт | D11: 0.001 | E11: 468.33 | F11: =E11*D11 -> 0.46833
A12: 3 | B12: Батарейка АА (4 шт) | C12: упак | D12: 1 | E12: 84.78 | F12: =E12*D12 -> 84.78
A13: 4 | B13: Шайба 6 цинк DIN 125 | C13: кг | D13: 0.003 | E13: 154 | F13: =E13*D13 -> 0.462
A14: 5 | B14: Паспорт на продукцию | C14: шт | D14: 1 | E14: 1.4 | F14: =E14*D14 -> 1.4
A15: 6 | B15: Наклейка с заливной смолой 37х23мм "Cerera" | C15: шт | D15: 1 | F15: =E15*D15 -> 0
A16: 7 | B16: Стойка для платы CS-10 | C16: шт | D16: 4 | E16: 0.92 | F16: =E16*D16 -> 3.68
A17: 8 | B17: Саморезы 4.2*13 пресс-шайба острый | C17: шт | D17: 4 | E17: 0.24 | F17: =E17*D17 -> 0.96
A18: 9 | B18: Этикетка 100*60 полуглянец | C18: шт | D18: 1 | F18: =E18*D18 -> 0
A19: 10 | B19: Круг 6 L=4м | C19: кг | D19: 0.014 | E19: 129.05 | F19: =E19*D19 -> 1.8067
A20: 11 | B20: ELB52I EE BUG GRIGIO 7035 GL TR св.серая | C20: кг | D20: 0.189 | E20: 201.72 | F20: =E20*D20 -> 38.12508
A21: 12 | B21: Круг лепестковый 125*22мм | C21: шт | D21: 0.127 | E21: 64.68 | F21: =E21*D21 -> 8.21436
A22: 13 | B22: Углекислота | C22: шт | D22: 0.011 | E22: 1000 | F22: =E22*D22 -> 11
A23: 14 | B23: Проволока СВ08 Г2С 0.8 омедн. | C23: кг | D23: 0.168 | E23: 158.33 | F23: =E23*D23 -> 26.59944
A24: 15 | B24: Замок электронный сейфовый LS026 | C24: компл | D24: 1 | E24: 537.5 | F24: =E24*D24 -> 537.5
A25: 16 | B25: Ковролин | C25: м2 | D25: 0.059 | E25: 638.33 | F25: =E25*D25 -> 37.66147
A26: 17 | B26: Рулон х/к 0.9*1250 | C26: кг | D26: 0.493 | E26: 67.08 | F26: =E26*D26 -> 33.07044
A27: 18 | B27: Лист 2.0мм | C27: кг | D27: 0.836 | E27: 68.33 | F27: =E27*D27 -> 57.12388
A28: 19 | B28: Рулон оцин 0.5*1250 | C28: кг | D28: 0.004 | E28: 85.83 | F28: =E28*D28 -> 0.34332
A29: 20 | B29: Лист 1.2мм | C29: кг | D29: 4.197 | E29: 70 | F29: =E29*D29 -> 293.79
A30: 21 | B30: Петля гаражная 10*60 | C30: шт | D30: 1 | E30: 17.83 | F30: =E30*D30 -> 17.83
A31: 22 | B31: Общая химия | C31: кг | D31: 0.006 | E31: 278 | F31: =E31*D31 -> 1.668
B32: Всего на материалы без НДС | F32: =SUM(F10:F31) -> 1162.033
B33: Наценка на материалы | E33: 0.01 | F33: =F32*E33 -> 11.62033
B34: Итого | F34: =SUM(F32,F33) -> 1173.6534
A35: 2 | B35: Основная з/п цеховых рабочих | E35: 0.11 | F35: =F34*E35 -> 129.10187
B36: Дополнительная з/п | E36: 0.14 | F36: =F35*E36 -> 18.074262
B37: Отчисления на социальные нужды цеховые | E37: 0.309 | F37: =(F35+F36)*E37 -> 45.477425
B38: Отчисления на социальные нужды Дополнительная з/п
A39: 3 | B39: Общепроизводственные (накладные) расходы | E39: 1.5 | F39: =F35*E39 -> 193.65281
A40: 4 | B40: Цеховая себестоимость | F40: =F34+F35+F36+F37+F38+F39 -> 1559.9597
A41: 5 | B41: Общехозяйственные расходы | E41: 1 | F41: =F35*E41 -> 129.10187
E42: 0.8 | F42: =F35*E42 -> 103.2815
A43: 6 | B43: СЕБЕСТОИМОСТЬ | F43: =F40+F41 -> 1689.0616
F44: =F40+F42 -> 1663.2412
A45: 7 | B45: Прибыль | E45: 0.4 | F45: =F43*E45 -> 675.62465
E46: 0.07 | F46: =F43*E46 -> 118.23431
A47: 8 | B47: Расходы на упаковку | F47: 107.08
B48: Цена без НДС | F48: =F43+F45+F47 -> 2471.7663
F49: =F44+F46+F47 -> 1888.5556
B50: НДС | E50: 0.22 | F50: =F48*E50 -> 543.78858
E51: 0.22 | F51: =F49*E51 -> 415.48222
B52: ОТПУСКНАЯ ЦЕНА | E52: розн | F52: =F48+F50 -> 3015.5548
E53: опт | F53: =F49+F51 -> 2304.0378
B56: Главный бухгалтер ________________

Sheet ШБС-01 мини
F1: УТВЕРЖДАЮ
F2: генеральный директор
F3: ООО "Вика-Двина"
F4: В.А. Иванов _________
A5: Калькуляция | F5: подпись
A7: Шкаф ШБС-01 мини
A9: № | B9: Наименование статьи затрат | C9: Ед.изм. | D9: Кол-во | E9: Цена. руб | F9: Стоимость. руб
A10: 1 | B10: Заклепка вытяжная 4.0*10 (не использовать) | C10: тыс. шт/1000 шт | D10: 0.01 | E10: 616.67 | F10: =E10*D10 -> 6.1667
A11: 2 | B11: Жгут нейлон. 2.5-3*150 | C11: тыс. шт/1000 шт | D11: 0.001 | E11: 468.33 | F11: =E11*D11 -> 0.46833
A12: 3 | B12: Паспорт на продукцию | C12: шт | D12: 1 | E12: 1.4 | F12: =E12*D12 -> 1.4
A13: 4 | B13: Наклейка с заливной смолой 37х23мм "Cerera" | C13: шт | D13: 1 | F13: =E13*D13 -> 0
A14: 5 | B14: Замок врезной сувальдный ЗВ8-6/03 секр. (080503) | C14: шт | D14: 1 | E14: 440.83 | F14: =E14*D14 -> 440.83
A15: 6 | B15: Этикетка 100*60 полуглянец | C15: шт | D15: 1 | F15: =E15*D15 -> 0
A16: 7 | B16: Этикетка 58*60 полуглянец | C16: шт | D16: 1 | F16: =E16*D16 -> 0
A17: 8 | B17: ELB52I EE BUG GRIGIO 7035 GL TR св.серая | C17: кг | D17: 0.07 | E17: 202.75 | F17: =E17*D17 -> 14.1925
A18: 9 | B18: Рулон х/к 0.9*1250 | C18: кг | D18: 8.274 | E18: 69.58 | F18: =E18*D18 -> 575.70492
A19: 10 | B19: Краска порошковая RAL 7011 (шагрень матовая) | C19: кг | D19: 0.36 | E19: 296.62 | F19: =E19*D19 -> 106.7832
A20: 11 | B20: Петля гаражная 12*80 | C20: шт | D20: 2 | E20: 25.73 | F20: =E20*D20 -> 51.46
